Workbook

Sheet Sep-18
A1: Name : Rahul
A2: Phone : 9209141067
A3: Name : Vikram singh
A4: Phone : 6005702812
A5: Name : Lool bail
A6: Phone : 7896645431

Sheet 19.09.24
A1: CLIENT | B1: REMARK
A2: Name : brg
A3: Phone : 9696969961 | B3: cb
A4: Name : ARUN PANDURANG Lahamge
A5: Name : Ashu gupta ji Phone : 9215441441 | B5: ni
A6: Name : Babu
A7: Name : Chandan Pradhan Phone : 9556002317
A8: Name : Darshan
A9: Name : Debanjan Chakraborty
A10: Name : Dhairya Agarwal
A11: Name : ganapathi
A12: Name : Gautam Barman
A13: Name : Harsh Agarwal Phone : 9110112574 | B13: cd
A14: Name : hsndnke Phone : 9977657766 | B14: off
A15: Name : Jeevan Chavhan | B15: ni
A16: Name : Jignesh Mhapralkar Phone : 9372207414 | B16: cd
A17: Name : Kk Phone : 7777777777 | B17: invalid
A18: Name : MOHAMMAD HAFIZ MANIHAR Phone : 9175007475 | B18: INTERESRED | C18: MAHENDRA
A19: Name : Neeru Phone : 9650709814 | B19: INTRUSTED
A20: Name : Piyush sharma Phone : 7982613924 | B20: npc
A21: Name : Pratik
A22: Name : Pruthibiraj Patel Phone : 8658640336
A23: Name : Raghavendra Phone : 9886630662 | B23: npc
A24: Name : Rishi Phone : 8828737975 | B24: busy
A25: Name : Ritishi kaul Phone : 8899775847 | B25: off
A26: Name : Rohit Phone : 8898800696 | B26: off
A27: Name : Rupali Phone : 9870339945 | B27: CB
A28: Name : Saibal Ghosh
A29: Name : Santha
A30: Name : Santhosh
A31: Name : Saraswathy MR
A32: Name : Saraswathy MR Phone : 9449275034 | B32: ni
A33: Name : Sathish Phone : 8838202699 | B33: followup
A34: Name : Shanmukha
A35: Name : Srinath S Phone : 8050549720 | B35: FT | C35: amit
A36: Name : SUMANGAL BISWAS Phone : 7076502262 | B36: INTRUSTED
A37: Name : Swaraj
A38: Name : Tanmoy
A39: Name : Tanmoy Phone : 9641107291
A40: Name : Tejal Pujari Phone : 9372697443 | B40: npc
A41: Name : Tejas Phone : 8459444274 | B41: busy
A42: Name : Umair Phone : 8377919230 | B42: ni
A43: Name : VAIBHAV PAWAR
A44: Name : Vivek Sharma
A45: Phone : 6383141718 | B45: cb
A46: Phone : 7069953728 | B46: off
A47: Phone : 7588977794
A48: Phone : 7635862347 | B48: cd
A49: Phone : 7775092425
A50: Phone : 7977756312 | B50: cd
A51: Phone : 7993025349 | B51: ni
A52: Phone : 8348400090 | B52: npc
A53: Phone : 8838925662
A54: Phone : 9356155388 | B54: cd
A55: Phone : 9449275034 | B55: ni
A56: Phone : 9650964376 | B56: FT | C56: rishi
A57: Phone : 9711319448 | B57: busy
A58: Phone : 9756297390 | B58: ni
A59: Phone : 9830790776 | B59: off
A60: Phone : 9840218133 | B60: npc
A61: Phone : 9945684848 | B61: ft | C61: amit
A62: Phone : 9972380701 | B62: make pay
A63: Name : Abhay
A64: Phone : 8793593581 | B64: PAID | C64: rishi

Sheet 20.09.24
A1: Name : Ajit
A2: Phone : 8412059100 | B2: cb
A3: Name : Shahraaz Phone : 9076378461 | B3: low
A4: Name : Biplab shill Phone : 8402015072 | B4: cb
A5: Name : Nalini Phone : 9750581992 | B5: npc
A6: Name : Priyanjana Saha Phone : 6291034461 | B6: ni
A7: Name : Razak Phone : 9746447138 | B7: cd
A8: Name : Shalu Balan Phone : 9326548305 | B8: cd
A9: Name : Vimal Phone : 9841162338 | B9: npc
A10: Name : Anil kumar Pradhan Phone : 8093477991 | B10: ofs
A11: Name : Selva Phone : 7892484905 | B11: off
A12: Name : Rasheswari meher Phone : 6370524859 | B12: ni
A13: Name : Sajid Phone : 8447292344 | B13: npc
A14: Name : Rekha Das Phone : 7576813140 | B14: ni
A15: Name : Pradeep ku behari Phone : 9437265483 | B15: FT | C15: NARMADA | F15: 27/12/2024
A16: Name : Sbw Phone : 7892104884 | B16: cd
A17: Name : Vijay Phone : 9944998783 | B17: npc
A18: Name : Mainul Islam Phone : 9864934575 | B18: cb
A19: Name : Sajal Biswas Phone : 8961323563 | B19: invalid
A20: Name : Rajkishorepandey Phone : 9131791220 | B20: off
A21: Name : ANUP CHATTERJEE Phone : 9749684372 | B21: npc
A22: Name : Raj Phone : 8561082963 | B22: off
A23: Name : Manohar mhaske Phone : 9011191477 | B23: followup
A24: Name : JITHIN K Phone : 8089957491 | B24: npc
A25: Name : DATTATRAY MATE Phone : 9130057340 | B25: busy
A26: Name : Shreenivas Phone : 7259870553 | B26: cd
A27: Name : abc
A28: Phone : 9876543210 | B28: busy
A29: Name : Sree avenash Phone : 7538824243 | B29: cd
A30: Name : Partha sarkar Phone : 9709031035 | B30: ni
A31: Name : Usha Phone : 9326189007 | B31: followup
A32: Name : Ajit Phone : 8412059100 | B32: no fund
A33: Name : Sanjeeb Mohanty
A34: Phone : 9323791057 | B34: NI
A35: Name : ANEESH
A36: Phone : 9947775292 | B36: npc
A37: Name : Raju
A38: Phone : 9494956056 | B38: old client
A39: Name : Sumit
A40: Phone : 9163420355 | B40: intrusted
A41: Name : Ganesh
A42: Phone : 9597150201 | B42: npc
A43: Name : Sheh Phone : 9373763667
A44: Name : Sunny
A45: Phone : 9136734961
A46: Name : Pratiksha
A47: Phone : 7874300073 | B47: Ni
A48: Name : Harish Kumar Bhola
A49: Phone : 8076484162
A50: Name : A Banerjee
A51: Phone : 9748617554 | B51: ft | C51: 50k

Sheet 21.09.24
A1: Name : Karanveer thapa
A2: Phone : 9717871816 | B2: NI
A3: Name : Bheem singh Phone : 7503012006 | B3: NI
A4: Name : MOJIBUR RAHMAN Phone : 9064745645 | B4: BUSY
A5: Name : Sujit Phone : 9937148555 | B5: CB
A6: Name : Vasu Phone : 9787593672 | B6: FT
A7: Name : Rafeeque Phone : 9846789594 | B7: BUSY
A8: Name : Atiisha dev Phone : 9789645727 | B8: CD
A9: Name : Parvez Khan Phone : 9922424526 | B9: NI
A10: Name : Sandesh MK Phone : 9747910441 | B10: OFS
A11: Name : SIVANNA G Phone : 9449615340 | B11: FT
A12: Name : Madhu Phone : 9860767804 | B12: NI
A13: Name : Naveen Sharma Phone : 9811728340 | B13: BUSY
A14: Name : Bas Phone : 9940489606 | B14: CD
A15: Name : Rohit Sheikh Phone : 9775259483 | B15: NI | D15: SS
A16: Name : Abhishek Phone : 8087460075 | B16: NI
A17: Name : Onkar Phone : 8485858190 | B17: CD
A18: Name : Suraj Phone : 9846665011 | B18: FT | C18: AMIT
A19: Name : shivaprasad s k Phone : 7892144731
A20: Name : AYUSH Phone : 8527232077 | B20: INTRUSTED | G20: intrusted
A21: Name : ARIJITROY Phone : 8001604222 | B21: CB
A22: Name : Jj Phone : 9637140238 | B22: NPC | C22: **********
A23: Name : Pankaj karmakar Phone : 8789302722 | B23: INTRUSTED
A24: Name : Pramod Somkuwar Phone : 9764717880 | B24: NPC
A25: Name : Sunny Phone : 9958863906 | B25: NPC
A26: Name : Rahul Phone : 8766206998 | B26: FT
A27: Name : A Banerjee Phone : 9748617554 | B27: INTRUSTED
A28: Name : Harish Kumar Bhola Phone : 8076484162 | B28: NPC
A29: Name : VIDHI GALA Phone : 8779293324 | B29: NPC
A30: Name : Kavya
A31: Phone : 7028832966 | B31: NI | C31: *******
A32: Name : Phool kumar
A33: Phone : 8882635904 | B33: INTRUSTED
A34: Name : Aashiya
A35: Phone : 9022044154 | B35: CB | C35: MAHENDRA
A36: Name : Ashis Kumar hazra
A37: Phone : 9434433452 | B37: CD
A38: Name : Somnath Ghosal
A39: Phone : 9748281010
A40: Name : Shweta Phone : 9999472738 | B40: NPC
A41: Name : Ganesh D
A42: Phone : 9108497469 | B42: NPC
A43: Name : sonu Phone : 8055675252 | B43: FT
A44: Name : Navin Phone : 9136758798 | B44: CALL BACK
A45: Name : Vikas Phone : 6361120971 | B45: NPC
A46: Name : Gowtham
A47: Phone : 8667514143 | B47: FT
A48: Name : Sarika Sharma
A49: Phone : 8864957541 | B49: FOLLOW UP
A50: Name : Sarika Sharma Phone : 8864957541 | B50: FOLLOW UP
A51: Name : Manish jani Phone : 9518974685 | B51: ft
A52: Name : Soham kathe Phone : 9083877214 | B52: WRONG
A53: Name : dattatrey suresh kedase Phone : 7045475470 | B53: INTRUSTED
A54: Name : Om Phone : 9421210344 | B54: cd
A55: Name : Ujjawal Pandey Phone : 9354695317 | B55: NI
A56: Name : Mohammad Shamim | B56: FT
A57: Phone : 8420450654
A58: Name : Kathiravan Subramanian
A59: Phone : 9940045511 | B59: NPC
A60: Name : OMAR FARUK
A61: Phone : 9083462343 | B61: NPC
A62: Name : Keshav
A63: Phone : 7875225039 | B63: NPC
A64: Name : Subrata Phone : 8145285561
A65: Name : Jitendra Baruah
A66: Phone : 8404081083 | B66: npc
A67: Name : sachinfakatkar
A68: Phone : 7620303085
A69: Name : Gandu kuamr Phone : 8088555135 | B69: npc
A70: Name : MC Amit
A71: Phone : 9591956292
A72: Name : Srinath Phone : 9940448147 | B72: ft
A73: Name : Bilung NG
A74: Phone : 9233290063
A75: Name : Amit Phone : 8447984591 | B75: ft

Sheet 22.23.09.24
A1: Name : Hemraj
A2: Phone : 8939259332 | B2: NI
A3: Name : Rahul kumbalkar Phone : 7587794750 | B3: NI
A4: Name : Nba Phone : 8638656375 | B4: NPC
A5: Name : SHIBAM HALDER Phone : 8967116407 | B5: NI
A6: Name : Balaram kar Phone : 8900245786 | B6: INVALID
A7: Name : saroj bhagat Phone : 8806944827 | B7: FRESHER
A8: Name : Ninjh Phone : 9884694477 | B8: NI
A9: Name : RAJENDRA AMBORE Phone : 9730652223 | B9: FT
A10: Name : Rahul Patil Phone : 9975536165 | B10: BUSY
A11: Name : Niranjan Bhowmick Phone : 9038471201 | B11: NPC
A12: Name : Kabirul Phone : 9836132501 | B12: NI
A13: Name : Mohandas Phone : 9535948486 | B13: NPC
... A17: Name : Nikhil shah Phone : 8779675103 | B17: NI
A18: Name : Rahul Lende
A19: Phone : 7709453093 | B19: BUSY
A20: Name : ASHOK KUMAR K N
A21: Phone : 8073056665 | B21: CD
A22: Name : Ramaraju Manthina Phone : 9533807776 | B22: NI
A23: Name : Vijayakumar SR Phone : 9741066256 | B23: NPC
A24: Name : Chandan N U Phone : 9019770641 | B24: NPC
A25: Name : N C Barman Phone : 7908058591 | B25: FT
A26: Name : Manjunath Phone : 9986191317 | B26: NI
A27: Name : Lakshman Dhakarge Phone : 9325579327 | B27: FT
A28: Name : Dibyajyoti Dash Phone : 9583636025 | B28: CB
A29: Name : Saheb sk Phone : 8617892442 | B29: FT
A30: Name : DARAMKISHORE Phone : 9493248748 | B30: FT
A31: Name : Dk Phone : 8102270029 | B31: WRONG
A32: Name : Lokesh Phone : 9398548345 | B32: NPC
... A34: Name : Vijayakumar SR Phone : 9876543210 | B34: BUSY
A35: Name : Kuppi
A36: Phone : 8277672562
A37: Name : Subhankar Bhowmik Phone : 9046388879 | B37: NPC
A38: Name : Mallesha TG Phone : 9019555736 | B38: FT
A39: Name : Rohit Paradhe
A40: Phone : 9324986602 | B40: FT ALGO
A41: Name : Balu Phone : 6300342742 | B41: NPC
A42: Name : Samir Phone : 8812006695 | B42: NPC
A43: Name : Kuppi Phone : 8277672562 | B43: NPC
A44: Name : Khalid
A45: Phone : 8296972180 | B45: CB
A46: Name : Dushyant Kumar Kharwar
A47: Phone : 6394921620 | B47: NI
A48: Name : Joy Chakraborty Phone : 6290637924 | B48: FT
A49: Name : Anand Singh Phone : 8910036346
A50: Name : Madhusmita Phone : 9707492208 | B50: FT
A51: Name : Panna lal roy Phone : 9434791408 | B51: NI
A52: Name : Anuhith Phone : 8618483675 | B52: NPC
A53: Name : Anu Phone : 8618483675 | B53: NPC
A54: Name : Srusti Phone : 7019427133 | B54: WRONG
A55: Name : SUNIL S NAIR Phone : 6291845915 | B55: CB
A56: Name : Sandeep Phone : 9999999999 | B56: WRONG
A57: Name : MAHA VEER Phone : 9821210989 | B57: NI
A58: Name : Sukhendra bisheshar Bunkar Phone : 9702466219 | B58: OFF
A59: Name : SESHA CHALAPATHI REDDY Phone : 8147543481 | B59: NI
A60: Name : Prathviraj chauhan Phone : 9330346847 | B60: NPC
A61: Name : Jagdish ji Phone : 9853662288 | B61: OFF
... A66: Name : Sanjeevan Mohapatra Phone : 9938116280 | B66: NPC
A67: Name : Rohit Paradhe Phone : 9324986602
A68: Name : Nafisa Phone : 8975020004
A69: Name : Joble Joy
A70: Phone : 7907106283 | B70: FT
A71: Name : Aishwarya Kukreja
A72: Phone : 9818928544
A73: Name : Akash Kakade Phone : 9005400597 | B73: invalid
A74: Name : Manohar Phone : 8169590239 | B74: npc
A75: Name : Joble Joy Phone : 7907106283 | B75: ft
A76: Name : Ankit
A77: Phone : 9871043520 | B77: npc
A78: Name : Mayank Phone : 9871043520 | B78: npc
A79: Name : amrit
A80: Phone : 9810009536 | B80: FT | C80: MAHENDRA
A81: Name : pritam
A82: Phone : 9611570304 | B82: ni
A83: Name : vinay kumar
A84: Phone : 7207946065
A85: Name : Pradeep
A86: Phone : 9894625310
A87: Name : Vinay Phone : 9326436956 | B87: intrusted
A88: Name : Pratik salunkhe Phone : 7888081308 | B88: cb
A89: Name : Susanto das
A90: Phone : 7059068969 | B90: busy
A91: Name : tarun Phone : 8652296218
A92: Name : Sonali
A93: Phone : 9130081687 | B93: npc
A94: Name : Vicky Phone : 8220497698 | B94: busy
A95: Name : Pande Prashant
A96: Phone : 9423681476 | B96: ft
A97: Name : Saravanan Phone : 9789414492 | B97: intrusted
A98: Name : Umesh
A99: Phone : 9654056271 | B99: followup
A100: Name : Sayan Pattanayak Phone : 6295881849
A101: Name : Rajiv
A102: Phone : 9619159356
A103: Name : shrabonti chakraborty
A104: Phone : 6291534537 | B104: ni
A105: Name : Padmanabhan Krishnamurthy Phone : 9740289932 | B105: cb
A106: Name : Raju Phone : 8106239780
A107: Name : Muni Phone : 9494587509
A108: Name : Karthick
...

Sheet 24.09.24
A1: name | B1: remark | C1: EMP.
A2: Name : Aravindh S | B2: 0
A3: Phone : 9566662953 | B3: CB
A4: Name : Suvendu Kamila Phone : 8910626514 | B4: INTRUSTED | C4: pawan
A5: Name : Dibyendu Phone : 9051904454 | B5: low investment | C5: amit
A6: Name : Hardik Phone : 8851660633 | B6: 0
A7: Name : Kapish Phone : 9832638201 | B7: call back
A8: Name : Rishi Aneja Phone : 9654332370 | B8: Follow up
A9: Name : T Phone : 9888532644 | B9: NPC
A10: Name : Ramesh Madiwalar Phone : 8217490542 | B10: SWITCH OF
A11: Name : Prasad Khartude Phone : 9960606789 | B11: CALL CUT
A12: Name : Khushal pawar Phone : 8169561139 | B12: CB
A13: Name : Sure.Subbarao Phone : 8008879504 | B13: 0
A14: Name : Venkat Phone : 9942691093 | B14: CB | C14: VIKASH
A15: Name : Rajan Phone : 9004478262 | B15: 0
A16: Name : Vishal Eknath Shivatare Phone : 9923245833 | B16: CB
A17: Name : Yaseen Phone : 9032712106 | B17: IN
A18: Name : Dipak sarkar Phone : 9832575982 | B18: low investment
A19: Name : Preeti Phone : 9342939266 | B19: NPC
A20: Name : SIVAKUMAR Phone : 9940710203 | B20: FT
A21: Name : NIHAL MANISH DEVKAR Phone : 8850694190 | B21: NI
A22: Name : Jony MD Phone : 7377327811 | B22: FT | C22: Rishi
A23: Name : Umar Khan Phone : 9073846362 | B23: LI | C23: ABHAY
A24: Name : Iyyappan Phone : 9751559220 | B24: NPC
A25: Name : Kakali Bagui Phone : 9836160994 | B25: NPC
A26: Name : Mahesh suryawanshi Phone : 9689363869 | B26: CB
A27: Name : Renu Kumari Phone : 8826255121 | B27: NPC
A28: Name : Nikita Dahiya Phone : 9468315098 | B28: NI
A29: Name : Puneet Jaiswal Phone : 9540801630 | B29: NI
A30: Name : Krishna Phone : 8639947116 | B30: NPC
A31: Name : prashant thakur Phone : 8084212902 | B31: CB
A32: Name : Mohammed Phone : 8082130587 | B32: CB
A33: Name : Raja Phone : 8658895558 | B33: FT | C33: AMIT
A34: Name : Sainath ramchandra chewale | B34: 0
A35: Phone : 9403249278 | B35: CB
A36: Name : Mahabir Phone : 9625034471 | B36: Fund issue
A37: Name : Jony MD Phone : 7377327811 | B37: FT | C37: Rishi
A38: Name : bhaskar Phone : 7385405149 | B38: AAJ HI PAYMENT DALA HAI
A39: Name : Suvankar pal | B39: 0
A40: Phone : 7432864522 | B40: Cd wc
A41: Name : Sainath ramchandra chewale Phone : 9403249278 | B41: CB
A42: Name : anurag Phone : 9892429167 | B42: NPC
A43: Name : Anil Phone : 9880162106 | B43: NPC
A44: Name : Rakesh Phone : 9922387415 | B44: Follow up | C44: VIKASH
A45: Name : Aadesh Phone : 9990561876 | B45: FT | C45: Akshay
A46: Name : Sanjay Phone : 8754986446 | B46: NPC
A47: Name : Manjappa Koppad Phone : 9900608383 | B47: NI
A48: Name : BIRINCHI DEKA Phone : 9706166743 | B48: NPC
A49: Name : PRITAM JOARDAR Phone : 7980152377 | B49: NPC
A50: Name : Ashish Phone : 7718881977 | B50: NPC
A51: Name : Ashwini Karale Phone : 9867236234 | B51: SWITCH OFF
A52: Name : Krishna k Phone : 9701998199 | B52: CB
A53: Name : Ashok Phone : 9952945511 | B53: Wrong number
A54: Name : Arabinda Phone : 9954195878 | B54: CB
A55: Name : S k Ummat Phone : 9818528227 | B55: NI
A56: Name : Nataraj Phone : 9740737259 | B56: NPC
A57: Name : Nsk Phone : 9704703973 | B57: NPC
... A60: Name : Ajit shivaji kapse Phone : 7620171178 | B60: NPC
A61: Name : Sandeep Pattnayak Phone : 9937049268 | B61: Ft bigner | C61: Amit
A62: Name : Kartik agrawal Phone : 8956349144 | B62: NI
A63: Name : Gehsh Phone : 7826373827 | B63: Invalid
A64: Name : Ram1947 Phone : 9976798578 | B64: NPC
A65: Name : Sandeep deokar Phone : 9403166622 | B65: payment done | C65: VYOM | D65: PAID
A66: Name : Mahabir Phone : 9625034471 | B66: Fund issue
A67: Name : Suresh Phone : 7358905896 | B67: NPC
A68: Name : ASHWANI BHATIA Phone : 9354432012 | B68: NPC
A69: Name : Mubin Maner Phone : 9822859566 | B69: FT | C69: Rishi
A70: Name : Ashwin Kateelkar Phone : 9840013440 | B70: Interested | C70: PREETI
A71: Name : Shahid Phone : 9664529234 | B71: Interested | C71: SUNITA
A72: Name : Chandan Phone : 9014668233 | B72: NI
A73: Name : Bijay Phone : 9734113033 | B73: Interested | C73: SUNITA
A74: Name : Chandrasekaran s Phone : 9865411136 | B74: NPC
A75: Name : Fasal Phone : 8089401007 | B75: NPC
A76: Name : Arun Phone : 9224231614 | B76: Follow up | C76: KAMINI
A77: Name : S agarwal Phone : 9051614469 | B77: CB
A78: Name : Sudheer Phone : 9704969634 | B78: NPC
A79: Name : Rk Mondal Phone : 9339618932 | B79: INTERESTED | C79: MAHRNDRA
A80: Name : Vijay dogra Phone : 9312144736 | B80: Not reachable
A81: Name : Akshay Phone : 7019335069 | B81: FT | C81: Akshay
A82: Name : Vishal kumar Phone : 9508128723 | B82: Follow up | C82: VISHNU
A83: Name : Ram Phone : 9960109499 | B83: NI
A84: Name : Ranjit Phone : 9619952149 | B84: FT | C84: MAHRNDRA
A85: Name : Amit tupe Phone : 9867849166 | B85: NPC
A86: Name : Aldontomy Phone : 9446744029 | B86: NI
A87: Name : Selvan kumar Phone : 9833484420 | B87: NOT CONNECTED
A88: Name : Subhankar hazra Phone : 7003631224 | B88: NOT CONNECTED
A89: Name : Trupti Parag Bhelave Phone : 8308237040 | B89: NI
A90: Name : Rameshwar Mishra Phone : 9999296749 | B90: CB
A91: Name : Pravin Phone : 9822168164 | B91: NI
A92: Name : Mamta | B92: 0
A93: Phone : 7064186746 | B93: NPC
A94: Name : Prajesh Phone : 8870671694 | B94: NPC | F94: =117/2 -> 58.5
A95: Name : Prashob Phone : 7892774081 | B95: Payment mode
A96: Name : Pankaj Kadam Phone : 8082109986 | B96: NPC
B97: 0
A98: Name : sangram Phone : 9422333384 | B98: FT | C98: Rishi
A99: Name : Sailaja Phone : 7418963106 | B99: CB
A100: Name : Sanjaykamat | B100: 0
A101: Phone : 8126592610 | B101: Wrong No.
A102: Name : muniraj Phone : 8015303607 | B102: Not in service
...

Sheet Sheet4
A1: TOTAL LEADS -98 | F1: TOTAL LEADS - 160
A2: Date -23.09.24 | F2: Date -24.09.24
A3: FT | B3: 15 | F3: FT | G3: 16
A4: INTERESTED | B4: 2 | F4: INTERESTED | G4: 13
A5: FOLLOWUP | B5: 1 | F5: FOLLOWUP | G5: 4
A6: CB | B6: 5 | F6: CB | G6: 19
A7: BUSY | B7: 5 | F7: BUSY | G7: 14
A8: NPC | B8: 23 | F8: NPC | G8: 31
A9: NI | B9: 14 | F9: NI | G9: 20
A10: OTHERS | B10: 33 | F10: OTHERS | G10: 43
A11: EOD - | F11: EOD -

Sheet Sheet3
A1: TOTAL LEADS - 135 | F1: TOTAL LEADS - 141
A2: Date -25.09.24 | F2: Date -26.09.24
A3: FT | B3: =COUNTIFS('25-09-2024'!$D:$D,Sheet3!A3) -> 13 | F3: FT | G3: 9
A4: INTERESTED | B4: =COUNTIFS('25-09-2024'!$D:$D,Sheet3!A4) -> 8 | F4: INTERESTED | G4: 18
A5: FOLLOWUP | B5: 4 | F5: FOLLOWUP | G5: 4
A6: CB | B6: 22 | F6: CB | G6: 10
A7: BUSY | B7: =COUNTIFS('25-09-2024'!$D:$D,Sheet3!A7) -> 17 | F7: BUSY | G7: 20
A8: NPC | B8: 22 | F8: NPC | G8: 34
A9: NI | B9: =COUNTIFS('25-09-2024'!$D:$D,Sheet3!A9) -> 15 | F9: NI | G9: 28
A10: OTHERS | B10: 36 | F10: OTHERS | G10: 18

Sheet 25-09-2024
A1: clint NO. | B1: Name | C1: mobile NO. | D1: Remark | E1: emp. Name
A2: 1 | B2: Glenn | C2: 9820551983 | D2: FT | E2: KAMINI
A3: 2 | B3: MUNEESWARAN G | C3: 8144764304 | D3: FT | E3: KAMINI
A4: 3 | B4: Rahman ansari | C4: 9158594883 | D4: FT | E4: SHRUTI
A5: 4 | B5: Aaaa | C5: 9876543210 | D5: BUSY
A6: 5 | B6: Akshay Choudhar | C6: 7798275453 | D6: CB | E6: PREETI
A7: 6 | B7: Shrishail Kattimani | C7: 8999304796 | D7: NI
A8: 7 | B8: Sabitha | C8: 7306671155 | D8: BUSY
A9: 8 | B9: Tanmay | C9: 9172397171 | D9: FT 12K | E9: AMIT
A10: 9 | B10: Mo u bhiya | C10: 9373504866 | D10: SWITCH OFF
A11: 10 | B11: George K S | C11: 9447480030 | D11: FT | E11: KAMINI
A12: 11 | B12: Manikeshwar | C12: 8340796049 | D12: FT | E12: RISHI
A13: 12 | B13: Venkatappa | C13: 7892575720 | D13: SWITCH OFF
A14: 13 | B14: PAINX_UCHIHA | C14: 7439864710 | D14: FT | E14: AMIT
A15: 14 | B15: Sabena chalke | C15: 9322043326 | D15: CB | E15: MAHENDRA
A16: 15 | B16: Tushar Mandlik | C16: 7757913828 | D16: CB | E16: VOM
A17: 16 | B17: Bablu Dutta | C17: 7984427768 | D17: CB | E17: SHRUTI
A18: 17 | B18: Charles | C18: 8754797783 | D18: NI
A19: 18 | B19: Asif | C19: 9846360014 | D19: INTERESTED | E19: VRADDHI
A20: 19 | B20: Dheeraj R | C20: 8296790961 | D20: LANG. ISSUE
A21: 20 | B21: ARIVUSELVAM | C21: 9843701854 | D21: NI
A22: 21 | B22: Sukanta KUNDU | C22: 9073696055 | D22: CB | E22: AMIT
A23: 23 | B23: no name | C23: 9740101295 | D23: NPC
A24: 24 | B24: RAMESH yadav | C24: 8104536093 | D24: NPC
A25: 25 | B25: Sukhbir Singh | C25: 9953142956 | D25: NC
A26: 26 | B26: Saikat Mondal | C26: 9035251429 | D26: NPC
A27: 27 | B27: Ramesh | C27: 7373710124 | D27: NI
A28: 28 | B28: Atish palmal | C28: 8609420432 | D28: CB | E28: SHRUTI
A29: 29 | B29: KARTHIKA N P | C29: 7483675446 | D29: CB | E29: VOM
A30: 30 | B30: Soujanya mullick | C30: 8336044808 | D30: INTERESTED | E30: PAWAN
A31: 31 | B31: Anuraj | C31: 9744178130 | D31: SWITCH OFF
A32: 33 | B32: Ayyappa | C32: 9538250146 | D32: NI
A33: 34 | B33: Nagaraj | C33: 9964004771 | D33: FOLLOW UP | E33: POONAM
A34: 35 | B34: AYUSMAN KUMAR PATNAIK | C34: 6303124562 | D34: CB | E34: KAMINI
A35: 36 | B35: Priya | C35: 9742123085 | D35: INTERESTED | E35: PREETI
A36: 37 | B36: Arindam Tarafdar | C36: 9477223561 | D36: NPC
A37: 38 | B37: Satyapriya Mohapatra | C37: 7750995177 | D37: NI
A38: 39 | B38: sanu biswas | C38: 9800345683 | D38: NI
A39: 40 | B39: Palash | C39: 8346989573 | D39: SWITCH OFF
A40: 41 | B40: Yash | C40: 9881226385 | D40: CB | E40: R C
A41: 42 | B41: Sujaram patel | C41: 9488021000 | D41: CB | E41: SHRUTI
A42: 43 | B42: Suman Das | C42: 6297218742 | D42: CB | E42: PAWAN
A43: 44 | B43: MD Hamed | C43: 9903999637 | D43: NPC
A44: 45 | B44: Sagar | C44: 8431902189 | D44: BUSY
A45: 46 | B45: U ut7 | C45: 9874467876 | D45: SWITCH OFF
A46: 47 | B46: Manu | C46: 8277934295 | D46: NPC
A47: 48 | B47: Gajanan yeshvant pakhad | C47: 9561342176 | D47: NPC
A48: 49 | B48: Pritam das | C48: 9337717956 | D48: NO
A49: 50 | B49: Praneet singh | C49: 9650585032 | D49: PAYMENT DONE | E49: VISHNU
A50: 51 | B50: Yuvraj Singh Jadon | C50: 9131090258 | D50: NPC
A51: 52 | B51: Rekha | C51: 8451033099 | D51: FT | E51: AMIT
A52: 53 | B52: AYUSMAN KUMAR PATNAIK | C52: 6303124562 | D52: CB | E52: PAWAN
A53: 54 | B53: Nagaraj | C53: 9964004771 | D53: CB | E53: R C
A54: 55 | B54: Priya Ratheesh | C54: 9744571843 | D54: FOLLOW UP | E54: VOM
A55: 56 | B55: GOLLA VENKATAGANESH | C55: 8519925685 | D55: NPC
A56: 57 | B56: Mangesh Ghosalkar | C56: 7798801757 | D56: SWITCH OFF
A57: 58 | B57: Hyeubbsha | C57: 9101415622 | D57: BUSY
A58: 59 | B58: Hahahjs | C58: 9101415622 | D58: BUSY
A59: 60 | B59: Anish Kumar | C59: 7760351600 | D59: FT | E59: KAMINI
A60: 61 | B60: samrat nath | C60: 9620540717 | D60: NPC
A61: 62 | B61: SUJITH A | C61: 9447442627 | D61: FT | E61: AKSHAY
A62: 63 | B62: Kamal | C62: 9810982710 | D62: NI
A63: 64 | B63: Ayyappa | C63: 9538250146 | D63: NPC
A64: 65 | B64: Nitish Kumar | C64: 7082291191 | D64: BUSY
A65: 66 | B65: Priya Ratheesh | C65: 9744571843 | D65: FOLLOW UP | E65: VOM
A66: 67 | B66: Pachamma | C66: 8105733856 | D66: CB | E66: KAMINI
A67: 68 | B67: Sanket | C67: 7071600096 | D67: CB | E67: PREETI
A68: 69 | B68: Nitish Kumar | C68: 7082291191 | D68: BUSY
A69: 70 | B69: Sai Pratik Mishra | C69: 8260621075 | D69: SWITCH OFF
A70: 71 | B70: Shibankur | C70: 9874085007 | D70: NO
A71: 72 | B71: alagarraja49@gmail.com | C71: 9942883355 | D71: NI
A72: 73 | B72: Althaf | C72: 6238073023 | D72: BUSY
A73: 74 | B73: Shivam Das | C73: 9064517238 | D73: BUSY
A74: 75 | B74: Danish | C74: 7057781733 | D74: SWITCH OFF
A75: 76 | B75: Fhh | C75: 8888657998 | D75: NPC
A76: 77 | B76: Koushik | C76: 7001224878 | D76: FT | E76: AMIT
A77: 78 | B77: Priyank Shah | C77: 9769189153 | D77: CALL CUT
A78: 79 | B78: RameshBabu | C78: 9884098855 | D78: CALL CUT
A79: 80 | B79: reetish Kumar mishra | C79: 7735115845 | D79: CB | E79: KAMINI
A80: 81 | B80: Umesh Javane | C80: 9699445633 | D80: NPC
A81: 82 | B81: Sai Pratik Mishra | C81: 8260621075 | D81: SWITCH OFF
A82: 83 | B82: Vinoth | C82: 8105025208 | D82: BUSY
A83: 84 | B83: Shsj | C83: 9833409146 | D83: SWITCH OFF
A84: 85 | B84: Virupaksha | C84: 9972290529 | D84: NO
A85: 86 | B85: Sudhir | C85: 7396848092 | D85: NO
A86: 87 | B86: Sushama Dutta | C86: 7003006530 | D86: CB | E86: PAWAN
A87: 88 | B87: sffs | C87: 9242325365 | D87: INVALID
A88: 90 | B88: alagarraja49@gmail.com | C88: 9942883355 | D88: NI
A89: 92 | B89: Andiran | C89: 8148849122 | D89: NC
A90: 93 | B90: C vijaykumar | C90: 9160234447 | D90: CB | E90: KAMINI
A91: 94 | B91: Rema | C91: 8220385109 | D91: BUSY
A92: 95 | B92: Haroon Ali | C92: 7982423009 | D92: NI
A93: 96 | B93: Shsj | C93: 9833409146 | D93: SWITCH OFF
A94: 97 | B94: Narain Singh | C94: 9811965554 | D94: INTERESTED | E94: PAWAN
A95: 98 | B95: Pragya Satpathy | C95: 8432648445 | D95: NPC
A96: 99 | B96: Dr | C96: 9134567890 | D96: SWITCH OFF
A97: 100 | B97: Shravan | C97: 9820360637 | D97: NPC
A98: 101 | B98: Senthilkumar | C98: 8754858538 | D98: NC
B99: Narain Singh | C99: 9811965554 | D99: INTERESTED | E99: PAWAN
B100: Senthilkumar | C100: 8754858538 | D100: NC
...

Sheet 26-sep-2024
A1: clint details | B1: remark | C1: EMP. DETAILS
A2: NEW 26/SEP/2024
A3: Name : Samir Chakraborty
A4: Phone : 9433777122 | B4: FT | C4: KAMINI
A5: Name : Aaa
A6: Phone : 9789373829 | B6: NI | D6: FT AMIT
A7: Name : Ghogare Tanaji Phone : 7741978721 | B7: CB | C7: SUNITA
A8: Name : ashwin
A9: Phone : 9209199727 | B9: NI
A10: Name : Uv
A11: Phone : 8237484229 | B11: NPC
A12: Name : K P Kumar
A13: Phone : 9566074122 | B13: FT | C13: VOM
A14: Name : ANIL KUMAR
A15: Phone : 9874148118 | B15: INTERESTED | C15: RISHI
A16: Name : Arjuman Khan
A17: Phone : 8655355257 | B17: INTERESTED | C17: PREETI
A18: Name : Nikhil muttur
A19: Phone : 8073463354 | B19: BUSY
A20: Name : ajay
A21: Phone : 9887778877 | B21: WRONG NO.
A22: Name : Suresh
A23: Phone : 7019361155 | B23: FT | C23: AMIT
A24: NAME : NO
A25: Phone : 6238246567 | B25: NI
A26: Name : Utsav Kanji
A27: Phone : 8972542125 | B27: LOW CAPITAL | C27: RISHI
A28: Name : Samsher
A29: Phone : 7420006674 | B29: INTERESTED | C29: PREETI
A30: Name : ARVIND
A31: Phone : 7982557260 | B31: FOLLOW UP | C31: VOM
A32: Name : Tushar
A33: Phone : 7827522307 | B33: CB | C33: KAMINI
A34: Name : Mintu
A35: Phone : 8101560600 | B35: INTERESTED | C35: SUNITA
A36: Name : Md Muzammil Ahmed
A37: Phone : 8050899856 | B37: CB 6 PM | C37: VOM
A38: Mohd Nizamuddin Phone: 9738765021 | B38: INTERESTED | C38: AKSHAY
A39: Name : Karthik .p
A40: Phone : 8438983346 | B40: NPC
A41: Name : CVDHOQ C COQ
A42: Phone : 9899989999 | B42: BUSY
A43: Name : Yogesh Dattatray Phale
A44: Phone : 9765032332 | B44: SWITCH OFF
A45: Name : srinivasareddy
A46: Phone : 9844848223 | B46: INTERESTED | C46: SUNITA
A47: Name : Sunil
A48: Phone : 8075713857 | B48: NPC
A49: Name : Dinesh
A50: Phone : 7012564244 | B50: FT | C50: KAMINI
A51: Name : HARMEET SINGH
A52: Phone : 9654118282 | B52: FUND ISSUE | C52: VOM
A53: Dear:Sara Phone: 8237373161 | B53: INTERESTED | C53: VRADDHI
A54: Name : Pallavi
A55: Phone : 9359238414 | B55: BUSY
A56: Almas Phone: 8617040360 | B56: INTERESTED | C56: PREETI
A57: Rajesh Kumar Jha Phone: 9886561406 | B57: CB | C57: VRADDHI
A58: shivam Phone: 9013403421 | B58: FT | C58: YASH
A59: Vijay saha Phone: 7008055860 | B59: INTERESTED | C59: YASH
A60: Name : WASEEM
A61: Phone : 8433580552
A62: Ankur Singh Phone: 9769971874 | B62: INTERESTED | C62: AKSHAY
A63: Rajesh Banota Phone: 8369387824 | B63: INTERESTED | C63: AKSHAY
A64: Mohd Nizamuddin Phone: 9738765021 | B64: FOLLOW UP | C64: AKSHAY
A65: Name : Jyoti sardar
A66: Phone : 9423184681 | B66: NI
A67: Name : neeraj
A68: Phone : 8125123202 | B68: BUSY
A69: Name : Simon nag
A70: Phone : 8011159633 | B70: CB
A71: Name : Rijwana Shaikh
A72: Phone : 9403187812 | B72: NC
A73: Name : Hardeep singh
A74: Phone : 9810490051 | B74: INTERESTED | C74: KAMINI
A75: Name : Yogesh Chanchlani
A76: Phone : 9373205828 | B76: NPC
A77: Name : Bikash
A78: Phone : 8910289407 | B78: NPC
A79: Name : Gulshan lamba
A80: Phone : 9711665415 | B80: BUSY
A81: Name : Prabhakar Tilve | I81: =80+55 -> 135
A82: Phone : 9763068706 | B82: INTERESTED | C82: KAMINI
A83: Name : Koustav Gupta ********
A84: Phone : 9647020200 | B84: NI
A85: Name : Kushal Raj Phone : 9448006071 | B85: [profit based] | C85: KAMINI
A86: Name : Vinoth Phone : 8105025208
A87: Name : Manish Manhar
A88: Phone : 7856970877 | B88: INVALID
A89: Name : Chetan Madhukar Mhatre Phone : 9029422175 | B89: FOLLOW UP | C89: KAMINI
A90: Name : Arindam Phone : 7980708375 | B90: FT | C90: RISHI
A91: Name : Shahebaaz Phone : 8446812734 | B91: BUSY
A92: Name : Vinayak Phone : 9113284123 | B92: BUSY
A93: Name : Akash Puri Phone : 9147412147 | B93: NPC
A94: Name : Joshith Phone : 8861662083 | B94: NI
A95: Name : Neha Phone : 8287228892 | B95: INTERESTED | C95: SUNITA
A96: Name : Sagar Baban Dhiwar Phone : 9922085488 | B96: BUSY
A97: Name : Jayaprakashnarayan Phone : 9701167405 | B97: FT | C97: RISHI
A98: Name : Hemanth Phone : 7411101734 | B98: NC
A99: Name : Mahesh Ghatage Phone : 9370332200 | B99: NPC
A100: Name : Sugandhi Phone : 9952041247 | B100: INTERESTED | C100: SHRUTI
...

Sheet Sheet2
A1: TOTAL LEADS - 57 | G1: Dear:Amrit Phone: 9074341331 REQUEST Services: | H1: NPC
A2: Date -27.09.24 | G2: Dear:Raghvendra Phone: 7303013125 REQUEST Services: | H2: NI
A3: FT | B3: 9 | G3: Dear:Narayan Ray Phone: 7358205504 REQUEST Services: | H3: CB | I3: PAWAN
A4: INTERESTED | B4: 7 | G4: Dear:Suvra Sankar Bandyopadhyay Phone: 9038533484 REQUEST Services: | H4: CB | I4: SHRUTI
A5: FOLLOWUP | B5: 4 | G5: Dear:Bhavna Phone: 7499109277 REQUEST Services: | H5: NI
A6: CB | B6: 7 | G6: Dear:Arjun Phone: 7339012904 REQUEST Services: | H6: FOLLOW UP | I6: YASH
A7: BUSY | B7: 2 | G7: Dear:Karan jain Phone: 9899549999 REQUEST Services: | H7: NC
A8: NPC | B8: 9 | G8: Dear:Narendar singh Phone: 9079293791 REQUEST Services: | H8: NPC
A9: NI | B9: 4 | G9: Dear:Jithukrishna Phone: 6282241523 REQUEST Services: | H9: NPC
A10: OTHERS | B10: 15 | G10: Dear:Ravindra Phone: 9448141162 REQUEST Services: | H10: BUSY
G11: Dear:Prashant pimpale Phone: 9420608778 REQUEST Services: | H11: NPC
G12: Dear:prateep Phone: 9949110491 REQUEST Services: | H12: NC
G13: Dear:Gaurang Phone: 9537392139 REQUEST Services: | H13: BUSY
G14: Dear:Balasubramani Phone: 6383616335 REQUEST Services: | H14: NPC
G15: Dear:Shree Phone: 8087012263 REQUEST Services: | H15: NPC
G16: Dear:Aishwarya Manna Phone: 9875385905 REQUEST Services: | H16: BUSY
G17: Dear:Alok Sakpilly Phone: 9382645469 REQUEST Services: | H17: BUSY
G18: Dear:RUPESH Phone: 7972101977 REQUEST Services: | H18: BUSY
G19: Dear:narinder kumar Phone: 9168675387 REQUEST Services: | H19: NI
G20: Dear:Naveen Phone: 9015798639 REQUEST Services: | H20: NI
G21: Dear:Bhupal Sarkar Phone: 8638012490 REQUEST Services: | H21: NI
G22: Dear:SATYARAM DAS Phone: 7340930198 REQUEST Services: | H22: NC
... G24: Dear:Aravindraj Phone: 8098223310 REQUEST Services: | H24: LS
H25: NI
G26: Dear:abhishek Phone: 9768811896 REQUEST Services: | H26: NPC
G27: Dear:Pintu Saha Phone: 8145801299 REQUEST Services: | H27: NI
G28: Dear:GILLELLA Phone: 7013391182 REQUEST Services: | H28: NC
G29: Dear:Puskar santra Phone: 6290015054 REQUEST Services: | H29: NI
G30: Dear:Thyagaraj Phone: 9916301078 REQUEST Services: | H30: NPC
G31: Dear:Narendra nath gupta Phone: 7003252099 REQUEST Services: | H31: NPC
G32: Dear:Shaurabh Yadav Phone: 9560662261 REQUEST Services | H32: NO
G33: Dear:Vinod Phone: 8755983919 REQUEST Services: | H33: NPC
G34: Dear:Rty Phone: 6565768798 REQUEST Services: | H34: NC
G35: Dear:ATSIH MORE Phone: 8419993670 REQUEST Services: | H35: INTERESTED | I35: VRADDHI
G36: Dear:Almas Phone: 8617040360 REQUEST Services: | H36: CB | I36: PREETI
G37: Dear:Priyanka Gope Phone: 8257024657 REQUEST Services: | H37: FUND ISSUE
G38: Dear:R C jena Phone: 8249050234 REQUEST Services: | H38: NI
G39: Dear:jagdeep Phone: 9967534248 REQUEST Services: | H39: NPC
G40: Dear:somebody Phone: 1597534560 REQUEST Services: | H40: WRONG NO.
G41: Dear:Pooja Gadekar Phone: 9595150095 REQUEST Services: | H41: BUSY
G42: Dear:Azahar Ali Phone: 8638312936 REQUEST Services: | H42: NC
G43: Dear:Dhanashri More Phone: 9152862751 REQUEST Services: | H43: NPC
G44: Dear:vivek Phone: 9136857890 REQUEST Services: | H44: SWITCH OFF
G45: Dear: A PANI Phone: 9337186746 REQUEST Services: | H45: NI
G46: Dear:Parveen begum Phone: 7439427082 REQUEST Services: | H46: SWITCH OFF
G47: Dear:Bs. Shama Phone: 9966692409 REQUEST Services: | H47: NI
G48: Dear:Suvendu panda Phone: 9438027923 REQUEST Services: | H48: NC
G49: Dear:Suvodip das Phone: 7908509244 REQUEST Services: | H49: BUGET ISSUE | I49: KAMINI
G50: Dear:Nagappa Kalal Phone: 9739101219 REQUEST Services: | H50: NI
G51: Dear:pandurang ugale Phone: 9422070713 REQUEST Services: | H51: NPC
G52: Dear:Ramesh Chand Phone: 9818604970 REQUEST Services: | H52: NPC
G53: Dear:Shubha Phone: 9886121044 REQUEST Services: | H53: NI
G54: Dear:Amreesh Gupta Phone: 9911561179 REQUEST Services: | H54: NPC
G55: Dear:Rakesh Sehgal Phone: 9811114212 REQUEST Services: | H55: NC
G56: Dear:Ashwin Phone: 8668277803 REQUEST Services: | H56: NPC
G57: Dear:Somtirtha Phone: 8910690585 REQUEST Services: | H57: NPC
G58: Dear:Nandeesh Phone: 9611853290 REQUEST Services: | H58: BUSY
G59: Dear:Prashil talpekar Phone: 9970505909 REQUEST Services: | H59: BUSY
G60: Dear:Anirban Phone: 8949785528 REQUEST Services: | H60: FUND ISSUE
G61: Dear:Achhelal Prajapati Phone: 9152480415 REQUEST Services: | H61: NI
... G66: Dear:Manikanta Phone: 7569351331 REQUEST Services: | H66: NI
G67: Dear:Faizuddin Ahmed Phone: 8638481258 REQUEST Services: | H67: INTERESTED | I67: AKSHAY
G68: Dear:Pankaj Phone: 9896480083 REQUEST Services: | H68: NI
G69: Dear:babita Phone: 9989879898 REQUEST Services: | H69: NC
G70: Dear:Mathew Phone: 9895370921 REQUEST Services: | H70: NPC
G71: Dear:shadab khan Phone: 8007956194 REQUEST Services: | H71: CB | I71: VRADDHI
G72: Dear:Samarpreet Phone: 7982877923 REQUEST Services: | H72: NPC
G73: Dear:SANDESH Phone: 9856013520 REQUEST Services: | H73: WRONG NO.
G74: Dear:Moumita Mondal Phone: 8585882858 REQUEST Services: | H74: NPC
G75: Dear:M.Samiappan Phone: 7871315862 REQUEST Services: | H75: NI
G76: Dear:Alam Phone: 8130118852 REQUEST Services: | H76: NI
G77: Dear:Abhi rajak Phone: 8910944757 REQUEST Services: | H77: NPC
G78: Dear:Pallab Phone: 8822862079 REQUEST Services: | H78: NPC
G79: Dear:Vsohsao Phone: 9485813135 REQUEST Services: | H79: NPC

Sheet 27-sep-2024
A1: Client details | B1: Remark | C1: Emp. Details
A2: Name : ERESH
A3: Phone : 8970168856 | B3: LS
A4: Name : Arunkumar Hk
A5: Phone : 9686712001 | B5: INTERESTED | C5: KAMINI
A6: Name : Theja
A7: Phone : 9381424331 | B7: FOLLOW UP | C7: AYUSH
A8: Name : Jjj
A9: Phone : 9357964214 | B9: SWITCH OFF
A10: Name : Mukul
A11: Phone : 9899932212 | B11: INTERESTED | C11: RISHI
A12: Name : Nidesh
A13: Phone : 8778593466 | B13: WRONG NO.
A14: ame : Praful Mahajan
A15: Phone : 7588553060 | B15: INTERESTED | C15: SUNITA
A16: Name : Fg
A17: Phone : 8307280274 | B17: CB | C17: KAMINI
A18: Name : David
A19: Phone : 8999999990 | B19: NPC
A20: Name : Sm
A21: Phone : 9340544720 | B21: FT | C21: SUNITA
A22: Name : Arunkumar Hk
A23: Phone : 9686812001 | B23: INVALID
A24: Name : Saranath kk
A25: Phone : 9092826599 | B25: CB | C25: SUNITA
A26: Name : Aman devkatte
A27: Phone : 8669182245 | B27: SWITCH OFF
A28: Name : Prataprao kishanrao kale
A29: Phone : 9673186210 | B29: NI
A30: Name : Prabhakar Tilve
A31: Phone : 9763068706 | B31: INTERESTED | C31: KAMINI
A32: Name : Gulshan lamba
A33: Phone : 9711665415 | B33: CB | C33: SHRUTI
A34: Name : asdf@sf.com
A35: Phone : 9962012546 | B35: SWITCH OFF
A36: Name : Utpal roy
A37: Phone : 7896572928 | B37: NI
A38: Name : Shajnavas
A39: Phone : 9388871114 | B39: INTERESTED | C39: VRADDHI
A40: Name : ERESH
A41: Phone : 8970168856 | B41: LS
A42: Name : Kumar
A43: Phone : 9003743190 | B43: BUSY
A44: Name : G Suresh
A45: Phone : 9494819486 | B45: CB
A46: Name : 44
A47: Phone : 9876543210 | B47: BUSY | C47: repeat no
A48: Name : Meenakshi Ambekar
A49: Phone : 9820042090 | B49: FOLLOW UP | C49: VOM
A50: Name : Fhhu
A51: Phone : 9876543210 | B51: repeat no.
A52: Name : S
A53: Phone : 7304960606 | B53: INVALID NO.
A54: Name : Mateen Wahid Ali Darvesh
A55: Phone : 9356126773 | B55: NPC
A56: Name : Snehal
A57: Phone : 8080224477 | B57: CB | C57: KAMINI
A58: Name : Subhasis Ghosal
A59: Phone : 9748120313 | B59: NPC
A60: Name : Suraj jagdale
A61: Phone : 7208765972 | B61: NPC
A62: Name : shubham
A63: Phone : 8830801420 | B63: FT | C63: VOM
A64: Name : Bhimrao Patil
A65: Phone : 9975875462 | B65: FT | C65: KAMINI
A66: Name : Gentle John
A67: Phone : 7012705900 | B67: FT | C67: AMIT
A68: Name : Dr md salamat ali
A69: Phone : 9830092743 | B69: CB | C69: KAMINI
A70: Name : Ranjeet Kumar
A71: Phone : 9007328185
A72: Name : AshokKumar PK
A73: Phone : 9789547764 | B73: NPC
A74: Name : Abhijeet Jamdar
A75: Phone : 9175273933 | B75: FOLLOW UP | C75: RISHI
A76: Name :
A77: Phone : 9880932576 | B77: NI
A78: Name : Ranjit
A79: Phone : 9619952149 | B79: INTERESTED | C79: KAMINI
A80: Name : p
A81: Phone : 9584987589 | B81: INVALID
A82: Name : T RAJASEKAR
A83: Phone : 9043051555 | B83: FT | C83: AYUSH
A84: Name : Deb
A85: Phone : 7063093327 | B85: FT | C85: AMIT
A86: Name : Kiran Bakari
A87: Phone : 7760893978 | B87: INTERESTED | C87: RISHI
A88: Name : Quadri S G
A89: Phone : 9970626286 | B89: FT | C89: KAMINI
A90: Name : Mangal Padmakar Khose
A91: Phone : 9356045355 | B91: FOLLOW UP | C91: VOM
A92: Name : saurav
A93: Phone : 9435010050 | B93: INTERESTED | C93: RISHI
A94: Name : Sivaranjani R
A95: Phone : 9585789586 | B95: FT | C95: AMIT
A96: Name : John Samuel
A97: Phone : 8884627263 | B97: NPC
A98: Name : Bhavin Naik
A99: Phone : 6352693749 | B99: CB | C99: VOM
A100: Name : Prasenjit Pradhan
...

Sheet 28-se3p-2024
A1: Client details | B1: Remark | C1: Emp.
A2: Name : K venkatesh
A3: Phone : 9441446419 | B3: LI
A4: Name : ബിനു P
A5: Phone : 7909106846 | B5: BUSY
A6: Name : Bijeeta
A7: Phone : 9801053080 | B7: NI
A8: Name : Madan
A9: Phone : 7411901829 | B9: NI
A10: Name : Sachin Nadkarni
A11: Phone : 9833126708 | B11: CB
A12: Name : Md Enus
A13: Phone : 9533750193 | B13: FT | C13: VOM
A14: Name : Bhanu Nailwal
A15: Phone : 9599953098 | B15: REPEAT
A16: Name : Deepak
A17: Phone : 8178563246 | B17: NPC
A18: Name : Prasanth
A19: Phone : 7356663593 | B19: SWITCH OFF
A20: Name : Vikas Kapoor
A21: Phone : 9910799666 | B21: FOLLO UP | C21: VOM
A22: Name : Hemant lakhe
A23: Phone : 9022139889 | B23: NPC
A24: Name : Prakaashh
A25: Phone : 8855000075 | B25: NPC
A26: Name : Maheswaran V
A27: Phone : 9111300510 | B27: FOLLO UP | C27: AMIT
A28: Name : Sharad patil
A29: Phone : 9096689389 | B29: NI
A30: Name : Yogish
A31: Phone : 9945208371 | B31: NC
A32: Name : chadramani Jadhav
A33: Phone : 8432004192 | B33: WRONG NO.
A34: Name : Prakasam
A35: Phone : 8754827611 | B35: LS
A36: Name : ,m , ,
A37: Phone : 9448526365 | B37: NPC
A38: Name : fasfdjfnwokn
A39: Phone : 9654785213 | B39: SWITCH OFF

Sheet 30-sep-2024
A1: Client details | B1: Remark | C1: Emp.
A2: Name : Bpk
A3: Phone : 8892585700 | B3: CD | C3: KAMINI
A4: Name : Kulesh Dhaneshrao Badwane
A5: Phone : 9764258488 | B5: INTERESTED | C5: RISHI
A6: Name : Harshal salve
A7: Phone : 8767199916 | B7: CD | C7: KAMINI
A8: Name : Mahesha. M
A9: Phone : 9611666930 | B9: FT | C9: RISHI
A10: Name : Pooja
A11: Phone : 9607761499 | B11: INTERESTED | C11: SUNITA
A12: Name : Bala
A13: Phone : 7708647884 | B13: NC
A14: Name : Jayshree goraksh chakane
A15: Phone : 7977640843 | B15: FT | C15: PAWAN
A16: Name : Raj barbar
A17: Phone : 9284852935 | B17: CB | C17: AYUSH
A18: Name : VIJAY TAYADE
A19: Phone : 9637217897 | B19: INTERESTED | C19: SUNITA
A20: Name : SURESH KUMAR
A21: Phone : 9095611138 | B21: SWITCH OFF
A22: Name : Shivaji Pendor
A23: Phone : 7620274600 | B23: BUSY
A24: Name : Karan
A25: Phone : 7768889006 | B25: FOLLOW UP | C25: RISHI
A26: Name : ashish wable
A27: Phone : 9146343814 | B27: INTERESTED | C27: AYUSH
A28: Name : Roshan
A29: Phone : 7208641489 | B29: CB | C29: SHRUTI
A30: Name : Mallikarjun
A31: Phone : 9845482584 | B31: NC
A32: Name : Preetham
A33: Phone : 9901528082 | B33: NPC
A34: Name : diraviam iyadurai
A35: Phone : 8667606434 | B35: NPC
A36: Name : HARDIK DARJI
A37: Phone : 7203008525 | B37: INTERESTED | C37: SHALINA
A38: Name : Nitto
A39: Phone : 9048846248 | B39: NPC
A40: Name : Abhishek malik
A41: Phone : 8860127906 | B41: FOLLOW UP | C41: VIKASH
A42: Name : Ansh Gaikwad
A43: Phone : 8796553812 | B43: NPC
A44: Name : AFSAL THOYAL KATTIL
A45: Phone : 7994143625 | B45: INTERESTED | C45: YASH
A46: Name : Saurabh Suryawanshi
A47: Phone : 8668249572 | B47: NI
A48: Name : Mukeshwaran
A49: Phone : 6383530541
A50: Name : Saurabh Suryawanshi
A51: Phone : 8668249572 | B51: NI
A52: Name : Vipun purushan
A53: Phone : 8943430457 | B53: NPC
A54: Name : jagdish naik
A55: Phone : 8999317448 | B55: BUSY
A56: Name : Uttam
A57: Phone : 8449141004 | B57: NPC
A58: Name : mahesh
A59: Phone : 9898900000 | B59: NPC
A60: Name : Gaurav.kolhe
A61: Phone : 7350333117 | B61: BUSY
A62: Name : sameer vernekar
A63: Phone : 9886306182 | B63: INTERESTED | C63: SHRUTI
A64: Name : R.muthuraman
A65: Phone : 9344590921 | B65: BUSY
A66: Name : Mehul Patadiya
A67: Phone : 9881151153 | B67: BUSY
A68: Name : Shashikant Haridas Bhamble
A69: Phone : 9823511458 | B69: FT | C69: AMIT
A70: Name : GIRISH
A71: Phone : 7337855467 | B71: NI
A72: Name : Prakash suman
A73: Phone : 9702099550 | B73: FOLLOW UP | C73: RISHI
A74: Name : Ramu
A75: Phone : 8744876451 | B75: NI
A76: Name : Vis
A77: Phone : 8608288058 | B77: LI
A78: Name : Chetna
A79: Phone : 8097207446 | B79: NPC
A80: Name : Nishad
A81: Phone : 9745111170 | B81: FOLLOW UP | C81: KAMINI
A82: Name : Prasanna B R
A83: Phone : 9686159308 | B83: CB | C83: SHRUTI
A84: Name : Santhosh Kumar
A85: Phone : 9108482110 | B85: WRONG NO.
A86: Name : Sanjay Kumar Singh
A87: Phone : 9958100941 | B87: FOLLOW UP | C87: AYUSH
A88: Name : Naveen Reddy Baddam
A89: Phone : 8985501654 | B89: NPC
A90: Name : Sun
A91: Phone : 8104126864 | B91: INVALID
A92: Name : Sharad patil
A93: Phone : 9096689389 | B93: NI
A94: Name : ARUNJINDAL
A95: Phone : 9716801015 | B95: NPC
A96: Name : Shubham Chadha
A97: Phone : 9999422355 | B97: BUSY
A98: Name : Ayyasamy
A99: Phone : 9381948862 | B99: INTERESTED | C99: SHRUTI
A100: Name : Surekha
...

Sheet 01-10-2024
A1: CLIENT DETAILS | B1: REMARK | C1: EMP…
A2: Name : Suman kumar
A3: Phone : 7547091469 | B3: ft | C3: SHRUTI
A4: Name : ANTARA BASU Phone : 7890918019 | B4: intrusted | C4: SHRUTI
A5: Name : Anita Phone : 9986616116 | B5: ni
A6: Name : Mukesh Gaikwad Phone : 8412805050 | B6: cb
A7: Name : naveed Phone : 9343830277 | B7: CB
A8: Name : Kuldeep Phone : 8423230016 | B8: INTERESTED AFTER DIWALI | C8: CAPITAL ISSUE | D8: DHARMESH
A9: Name : Munna Phone : 9619718047 | B9: followup | C9: MAHENDRA
A10: Name : Dhanesh
A11: Phone : 7904188933 | B11: cb | C11: SHRUTI
A12: Name : Dhamapal gawai
A13: Phone : 8446688678 | B13: ft | C13: KHUSHI
A14: Name : Wali Phone : 9125813962 | B14: FT | C14: MAHENDRA
A15: Name : Vijay makode Phone : 7385876280 | B15: ft | C15: AMIT
A16: Name : Yusub Phone : 9898823457 | B16: CB | C16: SHRUTI
A17: Name : Vinod S
A18: Phone : 9945264280 | B18: ft | C18: AYUSH
A19: Name : JAYA KUMAR P V
A20: Phone : 9786874475 | B20: NPC
A21: Name : Mohammad MOTESHIM
A22: Phone : 8884077099 | B22: NPC
A23: Name : Aditya Phone : 7710877268 | B23: ft | C23: TANVI
A24: Name : Suraj b Phone : 9667956778 | B24: SWITCH OFF
A25: Name : Sunil kashinath khobragad Phone : 9923740702 | B25: NPC
A26: Name : Sundeep
A27: Phone : 9223519478 | B27: cb | C27: VOM
A28: Name : Ranjan Kumar Tiwari
A29: Phone : 9560580532 | B29: FT | C29: AMIT
A30: Name : Chandrashekar Phone : 9845560830 | B30: ft | C30: KAMINI
A31: Name : JANARDHAN Phone : 9380606060 | B31: NPC
A32: Name : Shankar Phone : 9894825738 | B32: ft | C32: AYUSH
A33: Name : Syam Phone : 9420808861 | B33: NPC
A34: Name : Santhosh p Phone : 8861117385 | B34: SWITCH OFF
A35: Name : ANANDAREUBEN R
A36: Phone : 8220954277 | B36: ft | C36: AMIT
A37: Name : Pravin Rokade Phone : 9740376692 | B37: intrusted | C37: KAMINI
A38: Name : Sajjad Phone : 9920666806 | B38: cb
A39: Name : Amal Phone : 7559006941 | B39: NC
A40: Name : VENKATESH SHA Phone : 8248272532 | B40: BUSY
A41: Name : Mogan
A42: Phone : 9843589965 | B42: BUSY
A43: Name : Gaurav Rajesh gadiya
A44: Phone : 8888947803 | B44: NPC
A45: Name : Ajay Zinjurde
A46: Phone : 9028355214 | B46: NPC
A47: Name : SHAILY SHAW Phone : 8583086803
A48: Name : Priya Gupta Phone : 9871288429 | B48: CB | C48: SHRUTI
A49: Name : SHANTANU SAHA Phone : 7003709675 | B49: CB | C49: VOM
A50: Name : Kiran jai
A51: Phone : 7406020434 | B51: ft
A52: Name : Pelluri Venkatesh
A53: Phone : 9032756008 | B53: INTERESTED | C53: AKASH
A54: Name : Gg
A55: Phone : 7799992200 | B55: NI
A56: Name : Shivakumar G R
A57: Phone : 9743920475 | B57: busy
A58: Name : mahendra Phone : 9650438855 | B58: ft | C58: SHRUTI
A59: Name : Abhuh
A60: Phone : 9884098840 | B60: NPC
A61: Name : john Fernandes Phone : 9820409986 | B61: paid | C61: VOM

Sheet 03-10-2024
A1: Client Details | B1: Remark | C1: Emp.
A2: Name : Prashant Galimath
A3: Phone : 7019122678
A4: Name : Sidhartha Sahoo Phone : 9348661747
A5: Name : Punit Desai Phone : 9823395213 | B5: WRONG
A6: Name : Manohar Dandu Phone : 9481872088 | B6: NPC
A7: Name : Kushal Phone : 8217331219 | B7: NI
A8: Name : Swamireddy Phone : 9949125322 | B8: NPC
A9: Name : Vinothkumar N Phone : 8610891551 | B9: REPEAT
A10: Name : Naveen Payal
A11: Phone : 9810972047 | B11: NPC
A12: Name : rohit kumaar Phone : 8409198769 | B12: INVALID
A13: Name : JAGADISH HARAGOLI Phone : 9901016660 | B13: NI
A14: Name : Bhima Phone : 9861606063 | B14: NI
A15: Name : Dalvir singh Phone : 9899629819 | B15: FT | C15: AKSHAY
A16: Name : Manish Phone : 8806380741 | B16: FT | C16: SANJAY
A17: Name : Tejas Thakur 1 Phone : 8975871687 | B17: NI
A18: Name : Mohan Shukla Phone : 9213092120 | B18: NPC
A19: Name : Sailin Kumar Babu Phone : 9437903581 | B19: CD
A20: Name : SUBHRAKANTI CHAKRABORTy Phone : 7031366643 | B20: NPC
A21: Name : Aman singh Phone : 7379028365 | B21: npc
A22: Name : raghavendra raghu Phone : 8310774730 | B22: ft | C22: SHRUTI
A23: Name : Nabu Phone : 9686449409 | B23: off
A24: Name : Indhu J R Phone : 9847120030 | B24: ni
A25: Name : Vilas Phone : 9926843459 | B25: npc
A26: Name : Siddiraju satyanarayana Phone : 9989760126 | B26: npc
A27: Name : Abhisek Mohanty Phone : 8260707003 | B27: INT | C27: SHIVAM | D27: 45947
A28: Name : Ajay varsolkar Phone : 9021888737 | B28: INT | C28: SHIVAM | D28: 45947 | E28: NOV
A29: Name : Nikhil Popat Jadhav Phone : 7021646159 | B29: npc
A30: Name : Mani Phone : 9943484262 | B30: ni
A31: Name : Nitin Borkar Phone : 9371559992 | B31: ft | C31: AMIT
A32: Name : Srinu Phone : 8179558967 | B32: intrusted | C32: SHRUTI
A33: Name : Vcgg Phone : 9078565434 | B33: busy
A34: Name : Lakshaya Phone : 8112235103 | B34: intrusted | C34: SUNITA
A35: Name : Sharma Mukesh Phone : 9601787874 | B35: npc
A36: Name : GAUTAM NASKAR Phone : 9748706997 | B36: FT | C36: AKSHAY
A37: Name : SHARAD KUMAR SONI Phone : 9423050750 | B37: ft 5LAKH | C37: KAMINI
A38: Name : Justin Phone : 8848180579 | B38: BUSY
A39: Name : Akshay Vaishnav Phone : 9145841162 | B39: cb | C39: AKSHAY
A40: Name : Priyadarshi Mohapatra Phone : 9937010003 | B40: npc
A41: Name : Joy Phone : 7708555002 | B41: npc
A42: Name : Nani Phone : 9912499333 | B42: ni
A43: Name : Jibanjyoti panigrahi Phone : 9437538746 | B43: npc
A44: Name : San Phone : 9945419102 | B44: ofc
A45: Name : Shahid Choudhury Phone : 8553240911 | B45: off
A46: Name : Sainath chavan Phone : 8605062468 | B46: ni
A47: Name : Udayaprakash Katilkar Phone : 9941007000 | B47: ni
A48: Name : Akhilesh Choudhary Phone : 9412000161 | B48: INVALID
A49: Name : adit Phone : 9833986555 | B49: npc
A50: Name : Chirag Phone : 8180041499 | B50: CB | C50: AMIT
A51: Name : PANDIT Phone : 7588629775 | B51: npc
A52: Name : Suresh kannan Phone : 7304720246 | B52: ft 10K | C52: KAMINI
A53: Name : Md Ameer Phone : 9063556366 | B53: npc
A54: Name : Ali
A55: Phone : 9028600858 | B55: ni
A56: Name : VINOTH KUMAR M Phone : 9003375347 | B56: followup | C56: VIKASH
A57: Name : Rajendra Phone : 7719910118 | B57: npc
A58: Name : Shaun Phone : 9113218658 | B58: ni
A59: Name : Amit Goel Phone : 8826004546 | B59: intrusted | C59: YASH
A60: Name : Godwin Abisher
A61: Phone : 8870683399 | B61: npc
A62: Name : Umesha
A63: Phone : 7619110799 | B63: ni
A64: Name : Raza Phone : 8879409056 | B64: intrusted | C64: SHRUTI
A65: Name : Pravin Kamble Phone : 9082547355 | B65: ni
A66: Name : BAPUSOJAGANNATHPUKALE Phone : 8446984419 | B66: ni
A67: Name : Jaya Phone : 8888871419 | B67: invalid
A68: Name : Tufan Phone : 7978856107 | B68: cb
A69: Name : Swapnil Phone : 8208453115 | B69: cb
A70: Name : CraysalRodrigues Phone : 7303135155 | B70: ni
A71: Name : Syed Mohiuddin Phone : 9866790632 | B71: followup
A72: Name : Piyush buwade Phone : 9179796269 | B72: npc
A73: Name : Bhimji Phone : 9323883567 | B73: ft
A74: Name : karan dhanagre
A75: Phone : 7020875546 | B75: cd
A76: Name : Suma j panicker
A77: Phone : 8097874246 | B77: followup
A78: Name : B.srinivasan
A79: Phone : 7013245170 | B79: npc
A80: Name : B.srinivasan Phone : 7013245170 | B80: npc
A81: Name : Nikhil Agarwal Phone : 8884978203 | B81: PAYMENT DONE
A82: Name : Laxman Gawai Phone : 8655108310 | B82: ni
A83: Name : Satatya
A84: Phone : 9830964412 | B84: ni
A85: Name : Sanjay Sharma
A86: Phone : 9438143002 | B86: busy
A87: Name : Gulshan Phone : 8284830851 | B87: npc
A88: Name : Arvind kumar Phone : 7982557260 | B88: followup | C88: VOM
A89: Name : Dipak Dongaerdive Phone : 7263048588 | B89: cd
A90: Name : Sarbudeen Phone : 8778652451 | B90: npc
A91: Name : VIJAYAKUMAR T Phone : 9645338316 | B91: busy
A92: Name : Lalith kumar R Phone : 9789079597 | B92: npc
A93: Name : Ranit shans
A94: Phone : 7810996166 | B94: BIGNER | D94: RITU
A95: Name : Satatya Phone : 9830964412 | B95: ni
A96: Name : santosh thomas
A97: Phone : 9870041339
A98: Name : Muskan Phone : 8252508128
A99: Name : Swerna Raajan Phone : 9388661013 | B99: cb
A100: Name : Amol Sherkhane
...

Sheet 04-10-2024
A1: CLIENTS DETAILS | B1: REMARK | C1: EMP…
A2: Name : Gagan
A3: Phone : 9176629689 | B3: FT | C3: AMIT
A4: Name : Dhanu Phone : 8328107240 | B4: BUSY
A5: Name : Anjini Phone : 9880802509 | B5: NI
A6: Name : Umer
A7: Phone : 7710874517 | B7: CB | C7: AKSHAY
A8: Name : ANANTH NAG Phone : 8830025059 | B8: BUSY
A9: Name : R MALKIYA RASALIN PRINCE
A10: Phone : 9486913582 | B10: CB | C10: SHRUTI
A11: Name : Sampad Rath
A12: Phone : 9438153376 | B12: PAID | C12: MAHENDRA
A13: Name : Niranjan
A14: Phone : 9150987181 | B14: NPC
A15: Name : Sameer
A16: Phone : 8280986957 | B16: BUSY
A17: Name : B G PATIL
A18: Phone : 9901491256 | B18: CB | C18: PAWAN
A19: Name : Ridh
A20: Phone : 9137325390 | B20: BUSY
A21: Name : Rudra Narayan
A22: Phone : 8984103115 | B22: NC
A23: Name : Dhjks
A24: Phone : 8888567128 | B24: SWITCH OFF
A25: Name : Tejas kothawade
A26: Phone : 8856967062 | B26: CB | C26: PAWAN
A27: Name : Abhijith GM
A28: Phone : 6366916567 | B28: BUSY
A29: Name : Subhash D. Pawar
A30: Phone : 8108741627 | B30: NPC
A31: Name : Aaaaaaaa
A32: Phone : 9411110001 | B32: NPC
A33: Name : Vaishali
A34: Phone : 9960687506 | B34: BUSY
A35: Name : RajaMohanKumar G N
A36: Phone : 9916768994 | B36: BUSY
A37: Name : MAMUN
A38: Phone : 9153007412 | B38: NI
A39: Name : Akd
A40: Phone : 9629344221 | B40: NPC
A41: Name : Satish
A42: Phone : 8880790071 | B42: NPC
A43: Name : Basudev Nayak
A44: Phone : 8984576445 | B44: CB 4 | C44: VOM
A45: Name : deepak sahoo
A46: Phone : 8270528043 | B46: INTERESTED | C46: SALINA
A47: Name : Mahe
A48: Phone : 8344830143 | B48: LI
A49: Name : Krushna Khedkar
A50: Phone : 8411841567 | B50: NPC
A51: Name : Jyoti prakash shah
A52: Phone : 9892530736 | B52: NPC
A53: Name : vaibhav khairnar
A54: Phone : 8788492073 | B54: NPC
A55: Name : nitya bala
A56: Phone : 9330583077 | B56: NPC
A57: Name : Xyz
A58: Phone : 7070708989 | B58: NC
A59: Name : Abdul nasar
A60: Phone : 7909200000 | B60: NPC
A61: Name : Mangesh Phone : 8080967005 | B61: FOLLOW UP | C61: AKASH
A62: Name : Sandesh
A63: Phone : 9901862201 | B63: LI
A64: Name : Jignesh
A65: Phone : 9033232399 | B65: NPC
A66: Name : Sahil Arun Kalyankar
A67: Phone : 9324496988 | B67: CB 6 | C67: VOM
A68: Name : Nthin Rao
A69: Phone : 9945129863 | B69: FT | C69: SHRUTI
A70: Name : Manoj mallah
A71: Phone : 8100484817 | B71: CB | C71: AMIT
A72: Name : Rakesh Singh
A73: Phone : 9930432503 | B73: NI
A74: Name : Ganesh Chandra Panda
A75: Phone : 9778170809 | B75: NI
A76: Name : Mohit Sukhwani
A77: Phone : 9518732581 | B77: NI
A78: Name : Shazim
A79: Phone : 7020704739 | B79: BUSY
A80: Name : Viji
A81: Phone : 6374279134 | B81: SWITCH OFF
A82: Name : Franklin
A83: Phone : 8056384237 | B83: FOLLOW UP | C83: AKASH
A84: Name : Rupesh Gole
A85: Phone : 7218085999 | B85: CB | C85: VISHNU | D85: FUND ARRANGE KAR RAHA HE 1/2 WEAK KA BOLA H
A86: Name : Sunilkumar
A87: Phone : 8123545557 | B87: CB | C87: VIKASH
A88: Name : mk
A89: Phone : 7878755603 | B89: NI
A90: Name : XO
A91: Phone : 9087654321 | B91: NC
A92: Name : Bikash Chowdhury
A93: Phone : 9881049200 | B93: NI
A94: Name : Shereek
A95: Phone : 6282607886 | B95: INVALID
A96: Name : Anis Shaikh
A97: Phone : 9673732327 | B97: SWITCH OFF
A98: Name : Sheetal
A99: Phone : 8861257536 | B99: CB | C99: AMIT
A100: Name : Debraj Mallik
...

Sheet 05-10-2024
A1: CLIENTS DETAILS | B1: REMARK | C1: EMP…
A2: Name : Hitesh
A3: Phone : 9321471194 | B3: FOLLOW UP | C3: AYUSH
A4: Name : GOPALAKRISHNAN B
A5: Phone : 9884087735 | B5: BUSY
A6: Name : Seram
A7: Phone : 9566059500 | B7: SWITCH OFF
A8: Name : Xyzpvtltd
A9: Phone : 9999999999 | B9: WRONG NO
A10: Name : Naina Khamkar
A11: Phone : 9967664332 | B11: cb | C11: shalina
A12: Name : Khan Ahmed
A13: Phone : 9372241200 | B13: fund issue
A14: Name : Alok
A15: Phone : 7021984901 | B15: CB 8 | C15: AYUSH | D15: KAL CB
A16: Name : Vinay thakur
A17: Phone : 9682599981 | B17: CB | C17: SHRUTI
A18: Name : Ankit okuj
A19: Phone : 9595807966 | B19: INVALID
A20: Name : Anil Abhyankar
A21: Phone : 8261975761 | B21: WRONG NO
A22: Name : SIVAPRAKAKASAM Sivaprakasam
A23: Phone : 7667456575 | B23: NPC
A24: Name : P chinnasamy
A25: Phone : 9976826148 | B25: FOLLOW UP | C25: VOM
A26: Name : Dibakar
A27: Phone : 9922236769 | B27: FOLLOW UP | C27: VOM
A28: Name : Madhu Aravindh
A29: Phone : 9894744880 | B29: PAID | C29: AYUSH
A30: Name : Boopalan sampath | B30: FT
A31: Phone : 7358028986 | B31: FT | C31: AMIT
A32: Name : Vgr
A33: Phone : 9640223817 | B33: SWITCH OFF
A34: Name : Vijet naik
A35: Phone : 8867223268 | B35: BUSY
A36: Name : Jhilmil Pradhan
A37: Phone : 7459035938 | B37: BUSY
A38: Name : ASHUTOSH VIJAY BAL
A39: Phone : 9821942255 | B39: NPC
A40: Name : Dattatray Thorat
A41: Phone : 9767390014 | B41: NI
A42: Name : C.SARAVANAN
A43: Phone : 9842843424 | B43: SWITCH OFF
A44: Name : Ashi
A45: Phone : 9901254593 | B45: NI
A46: Name : Dalvir
A47: Phone : 9899629819 | B47: INTERESTED | C47: RISHI | D47: REPEAT NO.
A48: Name : Prabakaran G
A49: Phone : 8012421296 | B49: INTERESTED | C49: KAMINI
A50: Name : Mahesh babu
A51: Phone : 8884077099 | B51: NPC
A52: Name : Mugunthraj R
A53: Phone : 9677521809 | B53: INTERESTED | C53: KAMINI
A54: Name : Prakash
A55: Phone : 9960997970 | B55: INVALID
A56: Name : Narayan Padhan
A57: Phone : 7008422163 | B57: BUSY
A58: Name : manoj sharma | B58: FT
A59: Phone : 9252693193 | B59: FT | C59: AMIT

Sheet 07-10-2024
A1: CLIENTS DETAILS | B1: REMARK | C1: EMP…
A2: Name : Sadashiv Dhumal
A3: Phone : 7058327430 | B3: NI
A4: Name : Pradeep tiwari
A5: Phone : 9311674245 | B5: NI
A6: Name : Gopi
A7: Phone : 7051021484 | B7: NI
A8: Name : R
A9: Phone : 9444558520 | B9: NC
A10: Name : Parkash Chander
A11: Phone : 7015227719 | B11: NI
A12: Name : Jayesh
A13: Phone : 9975752279 | B13: BUSY
A14: Name : Nanaware Gaurav Hanumant | B14: FT
A15: Phone : 9561603872 | B15: FT | C15: SHRUTI
A16: Name : Dr SUNDER
A17: Phone : 9486142252 | B17: INTERESTED
A18: Name : Rahul Rankesh
A19: Phone : 8100568442 | B19: BUSY
A20: Name : Rajimol
A21: Phone : 9495195878 | B21: NC
A22: Name : Disha bhatt
A23: Phone : 8050868056 | B23: NPC
A24: Name : Hitesh Zamad
A25: Phone : 8625845494 | B25: WRONG NO
A26: Name : Haribaskaran
A27: Phone : 9003776747 | B27: LI
A28: Name : Shreenivasa
A29: Phone : 8880742296 | B29: BUSY
A30: Name : Yash suryawanshi
A31: Phone : 9021014929 | B31: CB | C31: VISHNU | D31: NPC
A32: Name : Sukhdeep Singh
A33: Phone : 9811325235 | B33: NI
A34: Name : Kumaravel B
A35: Phone : 7397380718 | B35: NC
A36: Name : Ram darade
A37: Phone : 8208481720 | B37: BUSY
A38: Name : Sanjay Kumar Vishwakarma
A39: Phone : 7087568234 | B39: BUSY
A40: Name : Veeraju
A41: Phone : 6281444656 | B41: NI
A42: Name : Faraz Siddiqui
A43: Phone : 9861187061 | B43: NI
A44: Name : Harshad
A45: Phone : 8767760353 | B45: INTERESTED | C45: KAMINI
A46: Name : Vuhgjnhb
A47: Phone : 9876543210 | B47: SWITCH OFF
A48: Name : Vijayakumar
A49: Phone : 9446810760 | B49: NI
A50: Name : sreehari
A51: Phone : 7676772388 | B51: INTERESTED | C51: RAJ
A52: Name : Damu
A53: Phone : 9843316541 | B53: CB 3 | C53: VOM
A54: Name : Supriya bisen
A55: Phone : 7972179831 | B55: SWITCH OFF
A56: Name : Shiva neware
A57: Phone : 9767485415 | B57: NI
A58: Name : Surendra shahare
A59: Phone : 9403161274 | B59: NI
A60: Name : Vinayak Neware
A61: Phone : 7588758037 | B61: NI
A62: Name : Atul Adamane
A63: Phone : 9623390424 | B63: CB 12 | C63: VISHNU
A64: Name : Chaitanya kolhe
A65: Phone : 9766715635 | B65: FOLLOW UP | C65: AYUSH
A66: Name : Vibha chimankar
A67: Phone : 9067930891 | B67: NI
A68: Name : Mahesh Dhone
A69: Phone : 9529043069 | B69: SWITCH OFF
A70: Name : Gayatri Dhone
A71: Phone : 9130584009 | B71: WRONG NO
A72: Name : Viju Kapgate
A73: Phone : 9767662691 | B73: CB | C73: RAJ
A74: Name : Shunmugarani rani
A75: Phone : 9087989531 | B75: NI
A76: Name : Rajullllllllll
A77: Phone : 9899517519 | B77: FT | C77: SANJAY | E77: 27/12/2024
A78: Name : Vishesh
A79: Phone : 7829906000 | B79: BUSY
A80: Name : Vvvhhhhh
A81: Phone : 9999999999 | B81: WRONG NO
A82: Name : Jayaram | B82: FT
A83: Phone : 6282888277 | B83: FT | C83: RISHI | D83: SUNDAY
A84: Name : Yogesh Rajendra Patil | B84: FT
A85: Phone : 8668485243 | B85: FT | C85: BOSS
A86: Name : Sonika Madekar
A87: Phone : 9623585631 | B87: PAID | C87: VISHNU
A88: Name : Bhumeswari neware
A89: Phone : 9356417922 | B89: BUSY
A90: Name : Ale manager
A91: Phone : 9422121443 | B91: NI
A92: Name : Harsha Bhendarkar
A93: Phone : 7350548406 | B93: NI
A94: Name : Vijay mohanlal motwani
A95: Phone : 7507486572 | B95: SWITCH OFF
A96: Name : Hello
A97: Phone : 9198979695 | B97: CB TOMORROW | C97: ayush
A98: Name : Veer
A99: Phone : 7654578990 | B99: NC
A100: Name : Rehan | B100: FT
...

Sheet EXPENSIVE  
A2: 96250 | B2: MOBILE +COVER
A3: 800
A4: 820 | B4: BANER
A5: 700 | B5: NASTA
A6: 3350 | B6: EXPENS | E6: 203978 | F6: BILL + RENT
A7: 2000 | B7: EXPENS | E7: 16895 | F7: BILL + EXPENS
E8: 7000 | F8: BILL
A9: 840 | B9: EXPENS | I9: =132601+227873 -> 360474
A10: 1330 | B10: EXPENS
A11: 1806 | B11: EXPENS
A13: 500 | B13: EXPENS
A14: 10500 | B14: OFFICE PARTY
A15: 1500 | B15: OFFICE PARTY
A16: 500 | B16: EXPENS
A17: 100 | B17: EXPENS
K18: =1156400-200000 -> 956400
A19: 1160 | B19: EXPENS
A20: 850 | B20: EXPENS
A21: 1300 | B21: EXPENS
A22: 880 | B22: EXPENS
A23: 3850 | B23: EXPENS
A24: 1185 | B24: EXPENS
A25: 2100 | B25: EXPENS
A26: 280 | B26: EXPENS
F36: TOTAL LEADS - 53
F37: Date -18.10.24
F38: FT | G38: 6
F39: INTERESTED | G39: 1
F40: FOLLOWUP | G40: 3
F41: CB | G41: 0
F42: BUSY | G42: 12
F43: CD
F44: NI | G44: 5
F45: NPC | G45: 4
F46: OTHERS | G46: 23

Sheet FT 26-10-24
A1: CLIENTS DETAIL | B1: REMARK | C1: INVESTMENT | D1: REMARK
A2: Name : Varsha Seth | I2: TOTAL LEADS - 386
A3: Phone : 9163605584 | B3: FT | C3: 15K | D3: VISHNU | I3: Date -26.10.24
A4: Name : Ravi Bhasamre | I4: FT | J4: 11
A5: Phone : 7666799660 | B5: CB | D5: VISHNU | I5: INTERESTED | J5: 7
A6: Name : Mamta rana | I6: FOLLOWUP | J6: 3
A7: Phone : 9582978824 | B7: FT | C7: 20K | D7: VISHNU | I7: CB | J7: 4
A8: Name : Goga | I8: BUSY | J8: 62
A9: Phone : 9604057974 | B9: FT | C9: 40K | D9: KAMINI | I9: CD | J9: 36
A10: Name : Syed Mohiuddin Phone : 9866790632 | B10: CB | D10: KAMINI | I10: NI | J10: 84
A11: Name : Srinivas Rao | I11: NPC | J11: 104
I12: OTHERS | J12: 79
A13: Janesh 8169098400 | B13: FT | C13: 5LAC CAPITAL
A14: Name : MD HUSAIN
A15: Phone : 8860197989 | B15: FT | D15: VIJAY
A16: Name : Satyajit moharana
A17: Phone : 7978965049 | B17: INTERESTED | D17: SHALINA
A18: Name : Yuvraj
A19: Phone : 9555527783 | B19: FT | D19: AMIT
A20: Name : Vijay Kumar Tak
A21: Phone : 8003933837 | B21: INTERESTED | D21: MAHENDRA
A22: Name : Dhamapal gawai
A23: Phone : 8446688678 | B23: INTERESTED | D23: MAHENDRA
A24: Name : Pramod
A25: Phone : 7021070412 | B25: CB MONDAY
A26: Name : Ramesh Sundaram
A27: Phone : 7418944330 | B27: FT | D27: RISHI
A28: Name : Swapnil Phone : 8208453115 | B28: INTERESTED | D28: RISHI
A29: Name : Umer
A30: Phone : 7710874517 | B30: FOLLOW UP | D30: RISHI
A31: Name : Dalvir singh Phone : 9899629819 | B31: FOLLOW UP | D31: RISHI
A32: Name : Aneeshbala
A33: Phone : 8921297800 | B33: FUTURE INTERESTED | D33: SUNITA
A34: Name : Shubham More
A35: Phone : 8830638246 | B35: CB | D35: MAHENDRA
A36: Name : Srinivasamoorthy sharma
A37: Phone : 8762555960 | B37: FT | D37: AMIT
A38: Name : Ramachandran
A39: Phone : 9500046725 | B39: INTERESTED | D39: AYUSH
A40: Name : Babu
A41: Phone : 6379344544 | B41: FOLLOW UP | D41: AMIT
A42: Name : Aravind
A43: Phone : 9620962201 | B43: FT | D43: VIJAY
A44: Name : Neeraj jain
A45: Phone : 9871195616. | B45: FT | D45: VIJAY
A46: Name : HARISINGH GUSAIN
A47: Phone : 8851002326 | B47: CB | D47: VIJAY
A48: Name Sanjeev kumar Mobile No. 6005891773 | B48: INTERESTED | D48: MAHENDRA

Sheet 3.10.24
A1: CLIENTS DETAILS | B1: REMARK | C1: EMP..
A2: Name : Avinash Parwe
A3: Phone : 8149219519 | B3: NC
A4: Name : Abdul nasar
A5: Phone : 7909200000 | B5: SWITCH OFF
A6: Name : Vishu Shinde
A7: Phone : 9284220551 | B7: NPC
A8: Name : Manoj Kumar jain
A9: Phone : 9650773208 | B9: AFTER M. | C9: RISHI
A10: Name : ANUP KR GHOSH
A11: Phone : 9851156053 | B11: FT | C11: AMIT
A12: Name : SHAFIN MAHIDA
A13: Phone : 7016490230 | B13: INTERESTED | C13: RAJ
A14: Name : Nnn
A15: Phone : 9994774831 | B15: NPC
A16: Name : Vivek Rathi
A17: Phone : 7682969855 | B17: AMIT
A18: Name : Rajshekhar Patil
A19: Phone : 9743617975 | B19: NR
A20: Name : Dilip chakraborty
A21: Phone : 7278567738 | B21: NI
A22: Name : magan
A23: Phone : 9368022127 | B23: NI
A24: Name : Ravi A R
A25: Phone : 9900289231 | B25: NPC
A26: Name : Kranti
A27: Phone : 7656055500 | B27: NC
A28: Name : Avinash K
A29: Phone : 6366346002 | B29: NPC
A30: Name : Shijo george
A31: Phone : 7736023155 | B31: BUSY
A32: Name : Aditya khutwad
A33: Phone : 9226304210 | B33: CB | C33: PAWAN
A34: Name : Dattatraya Satpute
A35: Phone : 9226888232 | B35: NPC
A36: Name : Emaer
A37: Phone : 8788501061 | B37: LI
A38: Name : Gholap kishor
A39: Phone : 9579529193 | B39: NPC
A40: Name : Sanket Junghare
A41: Phone : 8407979759 | B41: FT | C41: SHRUTI
A42: S
A43: Phone : 9113292851 | B43: NPC
A44: Name : Sekhar
A45: Phone : 9989234558 | B45: NI
A46: Name : Santosh Sharma
A47: Phone : 8999895507 | B47: INTERESTED | C47: SUNITA
A48: Name : Nikhil Agarwal
A49: Phone : 8884978203 | B49: PAID | C49: RISHI

Sheet 08-10-2024
A1: CLIENTS DETAILS | B1: REMARK | C1: INVESTMENT | D1: EMP…
A2: Name : amit chouhan
A3: Phone : 7738553566 | B3: CB EVENING | D3: KAMINI
A4: Name : Sipun kumar
A5: Phone : 7008435883 | B5: NPC | D5: RISHI
A6: Name : Lalit
A7: Phone : 9930218264 | B7: CB 12 PM | D7: VOM
A8: Name : Pavan
A9: Phone : 8805682743 | B9: NPC
A10: Name : Akash3591
A11: Phone : 8073431232 | B11: CB | D11: AMIT
A12: Name : Murali
A13: Phone : 9629630807 | B13: INTERESTED | D13: KAMINI
A14: Name : Ankur
A15: Phone : 9729863010 | B15: NPC
A16: Name : Swoyamprava
A17: Phone : 8249285172 | B17: BUSY
A18: Name : adarsh
A19: Phone : 9860410411 | B19: NPC
A20: Name : Harshit chauhan
A21: Phone : 8866338831 | B21: NI
A22: Name : Shiv Shankar
A23: Phone : 6387167813 | B23: INTERESTED | D23: KAMINI
A24: Name : Haridas N
A25: Phone : 9142198228 | B25: NI
A26: Name : Palla vinod kumar
A27: Phone : 8186824781 | B27: BUSY
A28: Name : B.A Srinivasa
A29: Phone : 8553468558 | B29: BUSY
A30: Name : Saikumar
A31: Phone : 9182030324 | B31: BUSY
A32: Name : Habibi
A33: Phone : 9849662306 | B33: NI
A34: Name : Vipul
A35: Phone : 9373116657 | B35: PAYMENT DONE | D35: SUNITA
A36: Name : muzammil
A37: Phone : 9765552403 | B37: Ni
A38: Name : Arin
A39: Phone : 7028893735 | B39: FUTURE INTERESTED
A40: Name : Ashish sahani
A41: Phone : 7075794244 | B41: INTERESTED | D41: SHALINA
A42: Name : Shanthi
A43: Phone : 7411100143 | B43: FOLLOW UP | D43: YASH
A44: Name : shashank joshi
A45: Phone : 9762180765 | B45: NPC
A46: Name : Naushad Ansari | B46: FT
A47: Phone : 8928057141 | B47: FT | C47: 20K | D47: AMIT
A48: Name : Akshay Chate
A49: Phone : 8412094242 | B49: BUSY
A50: Name : Tanmay Shukla
A51: Phone : 9811614039 | B51: NPC
A52: Name : Anju bangera | B52: FT
A53: Phone : 8779973882 | B53: FT | C53: 50K | D53: SHRUTI
A54: Name : Yogesh Nathuram Ranavare
A55: Phone : 9833101981 | B55: FOLLOW UP | C55: RISHI
A56: Name : Amar Shah
A57: Phone : 8169323027 | B57: CB | C57: SHRUTI
A58: Name : Anamika Akib Khan
A59: Phone : 7765851385 | B59: NI
A60: Name : Rohith Kumar
A61: Phone : 9738733344 | B61: NPC
A62: Name : Aravind | B62: FT
A63: Phone : 9620962201 | B63: FT | C63: 30K | D63: AMIT
A64: Name : Babita Vijay bansude | B64: FT
A65: Phone : 9763730523 | B65: FT | C65: 40K | D65: AYUSH
A66: Name : Shubhamg | B66: FT
A67: Phone : 9100067399 | B67: FT | C67: 1 LAKH CAPITAL | D67: AMIT
A68: Name : Bharat
A69: Phone : 9850888486 | B69: SWITCH OFF
A70: Name : Anujna
A71: Phone : 8296507253 | B71: NPC
A72: Name : Nishanthi
A73: Phone : 9176728447 | B73: INVALID
A74: Name : robin singh | B74: FT
A75: Phone : 9711282111 | B75: FT | D75: RISHI
A76: Name : Anujna
A77: Name : Bhuvanesh
A78: Phone : 7397221838 | B78: LI
A79: Name : Amith Valluri
A80: Phone : 7382694555 | B80: NPC
A81: Name :
A82: Phone : 9025659995 | B82: NPC
A83: Name :
A84: Phone : 9043952227 | B84: INVALID
A85: Name : Aishwarya Angane
A86: Phone : 8999034982 | B86: NI
A87: Name : Sonal
A88: Phone : 9921600894 | B88: NPC
A89: Name : Bhupender Singh | B89: FT
A90: Phone : 8882420045 | B90: FT | C90: 1 LAKH CAPITAL + | D90: KAMINI
A91: Name : Anamika Akib Khan ( New Hindustan Mobile Siwan wale) l
A92: Phone : 7979971002 | B92: CB | C92: DHARMESH
A93: Name : Pandit Jagtap
A94: Phone : 9890613999 | B94: FOLLOW UP | D94: SHALINA
A95: Name : T. Viswanadham
A96: Phone : 9686600027 | B96: INTERESTED | D96: KIMINI
A97: Name : Lata ksiwart
A98: Phone : 8305002367 | B98: FT | C98: 1.5 LAC | D98: SANJAY
A99: ame : Worngayung
A100: Phone : 9003476489 | B100: FOLLOW UP | D100: SHALINA
...

Sheet 10-10-2024
A1: CLIENTS DETAILS | B1: REMARK | C1: INVESTMENT | D1: EMP…
A2: Name : Jacquiline
A3: Phone : 8848527437 | B3: CB | D3: SHRUTI
A4: Name : Kavitha G
A5: Phone : 9562547654 | B5: INVALID
A6: Name : Ashish kumar Barik
A7: Phone : 9090560560 | B7: Clinic ka number h ye uske
A8: Name : Pradeep mandal
A9: Phone : 7894516213 | B9: FOLLOW UP | C9: 12 DAYS | D9: AYUSH
A10: Name : Tushar suryawanshi
A11: Phone : 7666285848 | B11: SF
A12: Name : Tapan
A13: Phone : 9348615447 | B13: FT | C13: 25k stock intraday | D13: YASH
A14: Name : Sumeet
A15: Phone : 8178022878 | B15: FT | D15: RAJ
A16: Name : Ravi .
A17: Phone : 8217768304 | B17: INVALID
A18: Name : Shivam bhalavi
A19: Phone : 9699445516 | B19: CB TOMORROW | D19: RITU
A20: Name : Bishwa
A21: Phone : 7868553656 | B21: INVALID
A22: Name : Vasanth
A23: Phone : 9344052172 | B23: SAID DONT CALL ME
A24: Name : Ashokkumarbehera
A25: Phone : 7008048755 | B25: NPC
A26: Name : Knashswell | B26: FT
A27: Phone : 9560842105 | B27: FT | C27: 50K | D27: SHRUTI
A28: Name : Shubham gadkar
A29: Phone : 9403327202 | B29: BUYS
A30: Name : Rajesh Singh
A31: Phone : 9930099505 | B31: INTERESTED | C31: 25K | D31: YASH
A32: Name : Master
A33: Phone : 6005000591 | B33: NI
A34: Name : Srinivas Rao
A35: Phone : 7008535768 | B35: FOLLOW UP | D35: VOM
A36: Name : Vmk | B36: FT
A37: Phone : 9943282325 | B37: FT | C37: 50K | D37: AMIT
A38: Name : POORAJAN
A39: Phone : 9600770309 | B39: FOLLOW UP | C39: option/1 lakh/ expectation : 5 Lakhs | D39: RISHI
A40: Name : Jyoti Singh
A41: Phone : 9562547654 | B41: INVALID
A42: Name : MANIKANDAN G
A43: Phone : 9944251107 | B43: NPC
A44: Name : Gnkbc
A45: Phone : 8893466143 | B45: INVALID
A46: Name : Kirankunar | B46: FT
A47: Phone : 9449837995 | B47: FT | C47: 50K | D47: AMIT
A48: Name : kaju
A49: Phone : 9812045600 | B49: NC | D49: RISHI
A50: Name : Manoj Kumar swain
A51: Phone : 6361853296 | B51: INTERESTED | C51: 1 lakh capital next month se start | D51: KAMINI
A52: Name : Vinod Rawat
A53: Phone : 9013226524 | B53: CB 2 PM
A54: Name : Sanjay Narale
A55: Phone : 9307463004 | B55: NPC
A56: Name : Chiru
A57: Phone : 9611051761 | B57: NI
A58: Name : Satyajit moharana | B58: FT
A59: Phone : 7978965049 | B59: FT | C59: 30K | D59: AMIT
A60: Name : Alexander
A61: Phone : 9654366796 | B61: INTERESTED | D61: VRADDHI
A62: Name : Tdrrd
A63: Phone : 8965556785 | B63: SF
A64: Name : Jyt
A65: Phone : 6442568646 | B65: INVALID
A66: Name : Ravi Bhasamre
A67: Phone : 7666799660 | B67: INTERESTED | C67: 2 lakh capital , eqt cash | D67: KAMINI
A68: Name : ishaan
A69: Phone : 8526118298 | B69: NPC
A70: Name : dfsdfsf
A71: Phone : 6666666666 | B71: INVALID
A72: Name : Mohitt
A73: Phone : 9742957875 | B73: OUT OF SERVICE
A74: Name : Nilo shaikh
A75: Phone : 8788507821 | B75: CB AFTER 8PM | D75: AMIT
A76: Name : Sivareddy | B76: FT
A77: Phone : 9959376860 | B77: FT | C77: intrested eqt cash , 3 lakh , new in intraday | D77: KAMINI
A78: Name : prakash jadhav
A79: Phone : 8806835920 | B79: BUYS
A80: Name : Ehtesham
A81: Phone : 9886704670 | B81: CB 5PM | D81: SHRUTI
A82: Name : PM Swamy | B82: FT
A83: Phone : 9886184203 | B83: FT | C83: 30K | D83: AMIT
A84: Name : Cyril Eginus
A85: Phone : 9538480289 | B85: FOLLOW UP | D85: RISHI
A86: Name : srini
A87: Phone : 9003104190 | B87: NI
A88: Name : SUNIL N
A89: Phone : 9731914900 | B89: FOLLOW UP | D89: AYUSH
A90: Name : jayaseelan
A91: Phone : 7094316811 | B91: NI
A92: Name : satheeshkumar | B92: FT
A93: Phone : 9994144478 | B93: FT | C93: 15k capital, index option | D93: KAMINI
A94: Name : Harindra
A95: Phone : 9702485875 | B95: NI
A96: Name : rathish
A97: Phone : 9544963464 | B97: INTERESTED | D97: SHRUTI
A98: Name : Agrawal
A99: Phone : 9729171717 | B99: NI
A100: Name : T. M Raj Narendra Singh
...

Sheet 09-10-2024
A1: CLIENTS DETAILS | B1: REMARK | C1: INVESTMENT | D1: EMP…
A2: Name : Arif | B2: FT
A3: Phone : 9702858602 | B3: FT | C3: 5 LAKH | D3: RITU
A4: Name : rajappan
A5: Phone : 9847505265 | B5: SF
A6: Name : Premdas
A7: Phone : 9637098125 | B7: SF | D7: KAMINI
A8: Name : Aiman Badane | B8: FT
A9: Phone : 9373778518 | B9: FT | D9: AMIT
A10: Name : sarvesh43198@gmailcom
A11: Phone : 9769543732 | B11: NPC
A12: Name : Rappa
A13: Phone : 9000000000 | B13: invalid
A14: Name : Sandi
A15: Phone : 7982931280 | B15: NI
A16: Name : Abhay Kumar
A17: Phone : 9560165472 | B17: FOLLOW UP | D17: KAMINI
A18: Name : Akash L
A19: Phone : 8197059648 | B19: NI
A20: Name : Ayyappan
A21: Phone : 8015120392 | B21: invalid
A22: Name : Manuel M.S
A23: Phone : 9847169683 | B23: NPC
A24: Name : Manoj Gadkari
A25: Phone : 9223209996 | B25: NPC
A26: Name : Jabadurai
A27: Phone : 8668176541 | B27: NPC
A28: Name : Karthik
A29: Phone : 9790875570 | B29: SF
A30: Name : AASHISH CHATTAR
A31: Phone : 9579768205 | B31: NI
A32: Name : Sanjay Sharma
A33: Phone : 9438143002 | B33: NI
A34: Name : Bandi koteswararao
A35: Phone : 9000366247 | B35: PAID
A36: Name : Ajeetesh
A37: Phone : 8018111810 | B37: INTERESTED | D37: RAJ
A38: Name : Xy
A39: Phone : 9899967999 | B39: NI
A40: Name : Bhavik | B40: FT
A41: Phone : 9987049651 | B41: FT | C41: 2 lac investment cash 30k option | D41: AMIT
A42: Name : Bhavya Wadhwa
A43: Phone : 9811333368 | B43: INTERESTED | D43: KAMINI
A44: Name : Muna Sahoo | B44: FT
A45: Phone : 9040421070 | B45: FT | D45: AKSHAY
A46: Name : Mayur | B46: FT
A47: Phone : 9922034330 | B47: FT | D47: AYUSH
A48: Name : Samertali
A49: Phone : 6366479709 | B49: NPC
A50: Name : Kinshuk Sharma
A51: Phone : 9873160199 | B51: BUSY
A52: Name : Anushka Kashyap
A53: Phone : 8888888888 | B53: INVALID
A54: Name : Shamnad
A55: Phone : 9745724763 | B55: LI
A56: Name : Nithyananda
A57: Phone : 9497454666 | B57: PAID | D57: AMBRISH
A58: Name : Ramesh Sundaram
A59: Phone : 7418944330 | B59: FOLLOW UP | D59: VOM
A60: Name : Akbar | B60: FT
A61: Phone : 8888492311 | B61: FT | D61: SHRUTI
A62: Name : Solanki
A63: Phone : 7043177246 | B63: NI
A64: Name : Deepak Tyagi | B64: FT
A65: Phone : 8700126657 | B65: FT | D65: AKSHAY
A66: Name : Rimjhim
A67: Phone : 9986267138 | B67: PAID
A68: Name : Samir Poojary | B68: FT
A69: Phone : 9284030690 | B69: FT | D69: Investment 1Lakh
A70: Name : Sumeet Ghundiyal
A71: Phone : 9021551530 | B71: CB AFTER 5 PM | D71: VRADDHI
A72: Name : Patil rohini
A73: Phone : 9404526522 | B73: NI
A74: Name : Pradyumn kumar
A75: Phone : 7392969700 | B75: FUND ISSUE
A76: Name : Chinmay
A77: Phone : 8793869022 | B77: invalid
A78: Name : Surya rathod
A79: Phone : 8605320278 | B79: FOLLOW UP | D79: KAMINI
A80: Name : Vikas Chandraprakash Jaiswal
A81: Phone : 9588679658 | B81: NI
A82: Name : Dora
A83: Phone : 9716921349 | B83: NI
A84: Name : Ravi bora
A85: Name : Santosh mittal | B85: FT
A86: Phone : 8003244630 | B86: FT | C86: 30K | D86: AMIT
A87: Name : Panduranga Varadhan
A88: Phone : 9945472566 | B88: NPC
A89: Name : Deepak Shinde
A90: Phone : 9619237142 | B90: NC
A91: Name : Pramod Phone : 7021070412 | B91: FOLLOW UP | D91: AMBRISH
A92: Name : Gasa
A93: Phone : 9967498984 | B93: invalid
A94: Name : Chethana | B94: FT
A95: Phone : 9480614132 | B95: FT | C95: 45K | D95: KAMINI
A96: Name : Asifali | B96: FT
A97: Phone : 7892467656 | B97: FT | C97: 15K | D97: AYUSH
A98: Name : Kumaravel
A99: Phone : 7397735101
A100: Name : Prashant | B100: FT
...

Sheet 11-10-2024
A1: CLIENTS DETAIL | B1: REMARK | C1: INVESTMENT | D1: EMP…
A2: Name : Sivara
A3: Phone : 7444450022 | B3: INVALID
A4: Name : Husain devendra madiwal
A5: Phone : 7738721537 | B5: BUSY
A6: Name : Santosh
A7: Phone : 9962292567 | B7: SF
A8: Name : Karthip
A9: Phone : 9578414221 | B9: NPC
A10: Name : Ajay prataprao more
A11: Phone : 9890817689 | B11: NI
A12: Name : Ponmaniraja
A13: Phone : 9952770767 | B13: BUSY
A14: Name : Deepak kumar
A15: Phone : 9911261493 | B15: NPC
A16: Name : Nareshkumar
A17: Phone : 9962447117 | B17: NPC
A18: Name : Sandeep Rode
A19: Phone : 7276929999 | B19: INTERESTED | D19: SUNITA
A20: Name : Mangginlen Haokip
A21: Phone : 8787774316 | B21: NPC
A22: Name : srinivasa
A23: Phone : 8141382952 | B23: NI
A24: Name : Shanmuga
A25: Phone : 9524371155 | B25: CD WC
A26: Name : Sushant ananda awale
A27: Phone : 9766933620 | B27: NC
A28: Name : Varsha Seth
A29: Phone : 9163605584 | B29: FOLLOW UP | D29: VIKASH
A30: Name : Virender Singh Negi | B30: FT
A31: Phone : 9915350144 | B31: FT | C31: 10K | D31: VOM
A32: Name : Suraj rajye
A33: Phone : 8975857093 | B33: INTERESTED | D33: SUNITA
A34: Name : P L MANOJ
A35: Phone : 9746817464 | B35: NPC
A36: Name : Sandeep javare
A37: Phone : 7420838472 | B37: NPC | D37: VOM
A38: Name : Himanshu Rajbhar
A39: Phone : 7558707503 | B39: BUSY
A40: Name : Vijayakanth Rama
A41: Phone : 9618816417 | B41: INTERESTED | D41: RAJ
A42: Name : Shubham More
A43: Phone : 8830638246 | B43: FUND ISSUE
A44: Name : Mit
A45: Phone : 8899922770 | B45: INVALID
A46: Name : Jee
A47: Phone : 9962154579 | B47: FOLLOW UP | D47: VISHNU
A48: Name : Himanshu
A49: Phone : 8826058637 | B49: FOLLOW UP | D49: AYUSH
A50: Name : Balak Singh Verma
A51: Phone : 8958502001 | B51: NPC
A52: Name : Dahni
A53: Phone : 8108550707 | B53: NPC
A54: Name : Kalyan | B54: FT
A55: Phone : 8000039143 | B55: FT | D55: AMIT
A56: Name : raktate hospitak
A57: Phone : 8788507821 | B57: FOLLOW UP | D57: AMBRISH
A58: Name : Jagdish Kumar
A59: Phone : 9166945700 | B59: INVALID
A60: Name : Sss
A61: Phone : 9768661921 | B61: INVALID
A62: Name : SAJIN RAJ
A63: Phone : 8122585058 | B63: INTERESTED | D63: SUNITA
A64: Name : MARUTHI
A65: Phone : 7019122698 | B65: INDEX OPTION ALGO
A66: Name : Pooja Sharma
A67: Phone : 9899604079 | B67: NPC | D67: VIJAY
A68: Name : Nabi
A69: Phone : 9866656395 | B69: FOLLOW UP | D69: VISHNU
A70: Name : rajamurugan
A71: Phone : 8015063607 | B71: NPC | D71: VOM
A72: Name : bodapati pavan kumar | B72: FT
A73: Phone : 6309343938 | B73: FT | C73: 30K | D73: YASH
A74: Name : VHORA SHABBIRBHAI YAKUBBHAI
A75: Phone : 9574711996 | B75: NI
A76: Name : Narayanan
A77: Phone : 9940111130 | B77: NI | D77: AMIT
A78: Name : Cgg
A79: Phone : 8988766768 | B79: NC
A80: Name : Appa
A81: Phone : 9456334678 | B81: INVALID
A82: Name : Ritik
A83: Phone : 9900910406 | B83: FOLLOW UP | D83: RISHI
A84: Name : Yogesh Mohan Kashid
A85: Phone : 9561848589 | B85: FOLLOW UP | D85: VOM
A86: Name : Ramachandran | B86: FT
A87: Phone : 9500046725 | B87: FT | C87: index option, 30 LAKH LOSS | D87: KAMINI
A88: Name : Chirag lalwani
A89: Phone : 8160241275 | B89: NPC
A90: Name : Sachin Rudra
A91: Phone : 9711613512 | B91: FOLLOW UP | D91: VOM
A92: Name : Varsha Negi
A93: Phone : 9654346678 | B93: BUSY
A94: Name : Abid
A95: Phone : 7019133668 | B95: BUSY
A96: Name : Atul Kumar choudhari
A97: Phone : 8451933784 | B97: INTERESTED | D97: SHALINA
A98: Name : Mashhoor | B98: FT
A99: Phone : 8943962776 | B99: FT | D99: AMIT
A100: Name : DEVANSH GUPTA
...

Sheet 14-10-2024
A1: CLIENTS DETAILS | B1: REMARK | C1: INVESTMENT | D1: EMP…
A2: Name : Sagar naswa
A3: Phone : 9654742902 | B3: CB | D3: RISHI
A4: Name : Sumata sethi
A5: Phone : 8018575373 | B5: SF
A6: Name : Ravi Teja Pokala
A7: Phone : 9177235051 | B7: FOLLOW UP | D7: AMIT
A8: Name : prakash Ananda kandre
A9: Phone : 7028408479 | B9: NPC
A10: Name : Sunild
A11: Phone : 9423008902 | B11: NPC
A12: Name : Thyagarajan
A13: Phone : 9940693948 | B13: INTERESTED | D13: RITU
A14: Name : S.siva Sreekanth
A15: Phone : 9441030128 | B15: NI
A16: Name : dsfg
A17: Phone : 9856321456 | B17: INVALID
A18: Name : Nivash Kumar
A19: Phone : 6382223680 | B19: NPC | C19: 14/10/2024
A20: Name : Babu
A21: Phone : 6379344544 | B21: INTERESTED | C21: REPEAT | D21: SUNITA
A22: Name : ramesha
A23: Phone : 9964502012 | B23: NI
A24: Name : Hari | B24: FT
A25: Phone : 7276016008 | B25: FT | C25: 20K | D25: KAMINI
A26: Name : HIRAN
A27: Phone : 9535214870 | B27: NI | C27: 10/15/2024 MORNING | D27: VOM
A28: Name : nilo
A29: Phone : 8788507821 | B29: FOLLOW UP | C29: REPEAT NO. | D29: AMBRISH
A30: Name : sonu shaikh
A31: Phone : 7757002813 | B31: NI
A32: Name : A.VALLINAYAGAM | B32: FT
A33: Phone : 9344452106 | B33: FT | D33: Harendra
A34: Name : dfasf
A35: Phone : 9885486258 | B35: NPC
A36: Name : Vishwaja
A37: Phone : 7507937679 | B37: INTERESTED | D37: VIJAY
A38: Name : rakesh rampa
A39: Phone : 9440939824 | B39: PAID | D39: KAMINI
A40: Name : Chander Kant Sharma
A41: Phone : 8447770977 | B41: NI
A42: Name : Surekha patil
A43: Phone : 9869832999 | B43: CB | D43: VOM
A44: Name : Jayasmita Nayak
A45: Phone : 8339861674 | B45: NI | D45: RISHI
A46: Name : MERLINFREEDA
A47: Phone : 9344675238 | B47: BUSY
A48: Name : Hemapriya S A
A49: Phone : 9148779932 | B49: NI
A50: Name : Pinaki Mandal
A51: Phone : 9711971229 | B51: NPC
A52: Name : Banit
A53: Phone : 8879080468 | B53: SF
A54: Name : M tuffy
A55: Phone : 9515891814 | B55: NPC
A56: Name : Neeraj jain
A57: Phone : 9871195616 | B57: INTERESTED | D57: SUNITA
A58: Name : Sattry
A59: Phone : 7685678900 | B59: INVALID
A60: Name : Nithin Rao
A61: Phone : 9945129863 | B61: FOLLOW UP | D61: AMIT
A62: Name : Xavier
A63: Phone : 9443518285 | B63: FOLLOW UP | D63: VOM
A64: Name : Nikhil
A65: Phone : 8089385897 | B65: BUSY
A66: Name : Madhavi
A67: Phone : 8639305753 | B67: NPC
A68: Name : HARISINGH GUSAIN | B68: FT
A69: Phone : 8851002326 | B69: FT | D69: HARENDRA
A70: Name : Vaibhav Waratkar
A71: Phone : 9822224446 | B71: PAID | C71: 1LAKH | D71: VOM
A72: Name : DEEPANKAR RAY
A73: Phone : 7681803030 | B73: BUSY
A74: Name : Meghna
A75: Phone : 9845280362 | B75: NI
A76: Name : Harsh
A77: Phone : 9999999999 | B77: INVALID
A78: Name : Nilesh Paswan
A79: Phone : 7304430143 | B79: NPC
A80: Name : Hrushikesh
A81: Phone : 8446890490 | B81: NI
A82: Name : Rishabh
A83: Phone : 8696043190 | B83: CD
A84: Name : Gagandeep Singh
A85: Phone : 9990504045 | B85: NPC
A86: Name : Yuvika
A87: Phone : 9482790043 | B87: INTERESTED | D87: RAJ
A88: Name : T RAMESH CHANDRA | B88: FT
A89: Phone : 9849354222 | B89: FT | C89: 20K REPEAT NO.
A90: Name : Suneetha | B90: FT
A91: Phone : 7995681555 | B91: FT | C91: 20K | D91: R C
A92: Name : Megyna
A93: Phone : 9845280362 | B93: NI
A94: Name : subbulakshmi
D100: TOTAL LEADS - 42
D101: Date -14.10.24
D102: FT | E102: 5
D103: INTERESTED | E103: 5
D104: FOLLOWUP | E104: 4
D105: CB | E105: 3
...

Sheet 15-10-24
A1: CLIENTS DETAILS | B1: REMARK | C1: INVESTMENT | D1: EMP….
A2: Name : Abdul Qadir Ansari
A3: Phone : 8660022799 | B3: PAID | D3: VIJAY
A4: Name : Deepak talpe | I4: TOTAL LEADS - 63
A5: Phone : 9028239509 | B5: NC | I5: Date -15.10.24
A6: Name : Yash Choudhary | I6: FT | J6: 8
A7: Phone : 9990644107 | B7: NPC | I7: INTERESTED | J7: 2
A8: Name : Uc narayana | I8: FOLLOWUP | J8: 4
A9: Phone : 9959849623 | B9: NPC | I9: CB | J9: 8
A10: Name : Dd | I10: BUSY | J10: 3
A11: Phone : 9546078512 | B11: NI | I11: NI | J11: 6
A12: Name : Mukesh Ahire | I12: NPC | J12: 18
A13: Phone : 8356906595 | B13: CB 3:30 | D13: AYUSH | I13: OTHERS | J13: 16
A14: Name : Sudesh
A15: Phone : 9967361987 | B15: NI
A16: Name : Sudheer Kumar
A17: Phone : 9611723975 | B17: INTERESTED | D17: VIJAY
A18: Name : Dav
A19: Phone : 6360161965 | B19: DETAIL SEND | D19: RISHI
A20: Name : Tarkeshwar Jain
A21: Phone : 9314531886 | B21: SF
A22: Name : Santosha
A23: Phone : 8105641535 | B23: NI
A24: Name : Neee
A25: Phone : 8446227696 | B25: NPC
A26: Name : thakur
A27: Phone : 8906014544 | B27: NPC | D27: VIJAY
A28: Name : Vandana Soni
A29: Phone : 9004087575 | B29: NI
A30: Name : S PRIYA LAKSHMI
A31: Phone : 8807585539 | B31: INVALID
A32: Name : giri reddy
A33: Phone : 8438378546 | B33: INTERESTED | D33: KAMINI
A34: Name : Mukesh kumawat
A35: Phone : 7014128173 | B35: NPC
A36: Name : Chandan chakma
A37: Phone : 8277634966 | B37: INTERESTED | C37: 10K
A38: Name : Subrat patra | B38: FT
A39: Phone : 7377636347 | B39: FT | D39: SHALINA
A40: Name : Birender Govil
A41: Phone : 9910377861 | B41: INTERESTED | D41: AMAN
A42: Name : Bharath
A43: Phone : 6361584491 | B43: INTERESTED | D43: VIJAY
A44: Name : kjl
A45: Phone : 9893228176 | B45: INVALID
A46: Name : SHAIKH BISMILLAH
A47: Phone : 9860616359 | B47: BUSY
A48: Name : Ravai rajaaa
A49: Phone : 8877667767 | B49: NC
A50: Name : Prasad
A51: Phone : 9014128955 | B51: NPC
A52: Name : Ronit
A53: Phone : 9167329012 | B53: NPC
A54: Name : Emy
A55: Phone : 9159109264 | B55: NPC
A56: Name : SRINIVASALU AN
A57: Phone : 6362694068 | B57: CB 6 PM | D57: KAMINI
A58: Name : Ankush Gupta
A59: Phone : 8108934251 | B59: SF
A60: Name : Tejas Rithe
A61: Phone : 9175742001 | B61: NPC
A62: Name : Anis
A63: Phone : 9315143351 | B63: NI
A64: Name : Shriniwas
A65: Phone : 9867263183 | B65: NI
A66: Name : Girish chandrakant sakpal
A67: Phone : 8356839132 | B67: NPC
A68: Name : Abhinav Nain
A69: Phone : 9997631945 | B69: PAID | D69: VOM
A70: Name : saurabh gupta
A71: Phone : 9650995000 | B71: NA
A72: Name : Vinod Melvani
A73: Phone : 9870128000 | B73: NI
A74: Name : Devam
A75: Phone : 9173366222 | B75: NPC
A76: Name : Nagendra
A77: Phone : 9980067824 | B77: CB 1H | D77: AMIT
A78: Name : Shubham_Patil
A79: Phone : 8408079001 | B79: NC
A80: Name : S. Ramachandran | B80: FT
A81: Phone : 9500046725 | B81: FT | C81: index option, 30lakh loss | D81: KAMINI
A82: Name : Jacintha
A83: Phone : 9718453895 | B83: NC
A84: Name : Arnan
A85: Phone : 9501262340 | B85: FOLLOW UP | D85: VOM
A86: Name : Nanjundan | B86: FT
A87: Phone : 9894353464 | B87: FT | D87: SHALINA
A88: Name : VISHWAS
A89: Phone : 6363573061 | B89: NPC
A90: Name : Shubham Sonkusare
A91: Phone : 8668238988 | B91: NPC
A92: Name : Ratheesh
A93: Phone : 7907787926 | B93: NC
A94: Name : Ashu | B94: FT
A95: Phone : 9820119174 | B95: FT | D95: GAURAV
A96: Name : Ayush Mane | B96: FT
A97: Phone : 9022229404 | B97: FT | C97: 10K | D97: KAMINI
A98: Name : Zuhaib khan | B98: FT
A99: Phone : 6396521216 | B99: FT | C99: 10K | D99: AMIT
A100: Name : shaik mohammed zakeer basha
...

Sheet OLD 
A1: Name : Kuldeep Phone : | B1: 8423230016 | C1: Fund issue after Diwali start | D1: DHARMESH
A2: 1-client name_bhushan /number_/ investment- 50k | B2: 9897688442 | D2: SHRUTI
A3: 2-prajwal / 40k | B3: 7517834510
A4: Name : Yuvika
A5: Phone : 9482790043 | B5: =RIGHT(A5,10) -> 9482790043 | C5: INTERESTED | D5: RAJ
A6: Name kishore Mobile No. 9937467174 Service - Stock-Cash | C6: FOLLOW UP | D6: MAHENDRA
A7: Name : victor jayaraj S
A8: Phone : 7904773882 | C8: INTERESTED | D8: DHARMESH
A9: Name Ravi Mobile No. 9740577772 Service - Stock-Option | C9: FOLLOW UP | D9: MAHENDRA
A10: Name kishore Mobile No. 9937467174 Service - Stock-Cash | C10: FOLLOW UP | D10: MAHENDRA
A11: Name Amritha Ajaykumar Mobile No. 9747871316 Service - Stock-Cash | C11: CB | D11: MAHENDRA
A12: Name Terim Mobile No. 8529938236 Service - Stock-Cash - Stock-Option | C12: INTERESTED | D12: MAHENDRA
A13: Name Sumit Mobile No. 8669099741 Service - Stock-Cash - Stock-Future - Stock-Option -- | C13: INTERESTED | D13: MAHENDRA
A15: 15/10/2024
A17: Name Shantanu Mobile No. 9082987990 Services Option Nifty Bank Nifty | C17: TOMORROW AFT MARKET | D17: DHARMESH
A18: Name Pankaj Palariya Mobile No. 7819007059 Services Stock-Cash | C18: FT | D18: SHALINA
A19: Name Kuber Mobile No. 09611572903 Services Option Nifty Bank Nifty
A20: [ SELF TRADER , 3 MONTH , INDEX OPTION , FREE TRIAL , 2 LAKH , ] FREE TRIAL | D20: KAMINI
A21: Dear:Bhupendra Rathod Phone: 9673236770 interested \ stock only | C21: INTERESTED | D21: AMAN
A22: Name : Rahul kumbalkar Phone : 7587794750 ft | C22: FT | D22: RITU
A23: Rp 9007732825 cash 50k Kolkata FT | C23: FT | D23: RITU
A24: Arindam 7980708375 cash 1lac kolkata ft | C24: FT | D24: RITU
A25: Tabrez 9845122348 all seg. Banglore mahendra ft | C25: FT | D25: RITU
A26: Rathiranjan 9831971649 cash 50k call back 5 bje | C26: cb 5 | D26: RITU
A28: 16/10/2024
A29: 1-client name_arbaz /number_9845473520/ investment-50k
A30: 2-bijender/ 8900311480/ 50k
A31: Keerthan Mobile No. 7975307707 interested | C31: SUNITA
A33: 19/10/2024
A34: deepak MOBILE: 9588056821 | C34: KAMINI
A38: Name : Sandeep Rode
A39: Phone : 7276929999 | C39: INTERESTED | D39: SUNITA
A40: Name : Suraj rajye
A41: Phone : 8975857093 | C41: INTERESTED | E41: SUNITA
A42: Name : SAJIN RAJ
A43: Phone : 8122585058 | C43: INTERESTED | E43: SUNITA
A44: Name : bodapati pavan kumar
A45: Phone : 6309343938 | C45: FT | D45: 30K | E45: YASH
A46: Name : Santosh Sharma
A47: Phone : 8999895507 | C47: INTERESTED | D47: SUNITA
A48: Name : Lakshaya Phone : 8112235103 | C48: intrusted | D48: SUNITA
A49: Name : Amit Goel Phone : 8826004546 | C49: intrusted | D49: YASH
A50: Name : Munna Phone : 9619718047 | C50: followup | D50: AKSHAY
A51: Name : Aditya Phone : 7710877268 | C51: ft | D51: TANVI
A52: Name : Pelluri Venkatesh
A53: Phone : 9032756008 | C53: INTERESTED | D53: AKASH
A54: Name : Tejas kothawade
A55: Phone : 8856967062 | C55: CB | D55: PAWAN
A56: Name : Mangesh Phone : 8080967005 | C56: FOLLOW UP | D56: AKASH
A57: Name : Franklin
A58: Phone : 8056384237 | C58: FOLLOW UP | D58: AKASH
A59: Name : Siddharth Bose
A60: Phone : 7978826409 | C60: INTERESTED | D60: yash
A61: Name : Tanishq
A62: Phone : 9423184681 | C62: INTERESTED | D62: SUNITA

Sheet 16-10-24
A1: CLIENTS DETAILS | B1: REMARK | C1: INVESTMENT | D1: EMP….
A2: Name : nrusingh | B2: FT | G2: 14 no. mobile | H2: yadvender
A3: Phone : 8917558456 | B3: FT | C3: 2LAC | D3: AMIT
A4: CC
A5: Phone : Name : Tanish Phone : 6380237495 | B5: NI | G5: TOTAL LEADS - 74
A6: Name : Jeeva | G6: Date -16.10.24
A7: Phone : 9962154579 | B7: FOLLOW UP | D7: VISHNU | G7: FT | H7: 11
A8: Name : ABHISHEK SINGH | G8: INTERESTED | H8: 1
A9: Phone : 7007413592 | B9: INVALID | G9: FOLLOWUP | H9: 7
A10: Name : Rizwan Ali | G10: CB | H10: 6
A11: Phone : 9718562973 | B11: NI | G11: BUSY | H11: 3
A12: Name : AshokSK | G12: NI | H12: 8
A13: Phone : 8618344536 | B13: NPC | G13: NPC | H13: 13
A14: Name : Somasundaran Kulakkattu Palengara | G14: OTHERS | H14: 26
A15: Phone : 9744612643 | B15: NI
A16: Name : Suji
A17: Phone : 8328311145 | B17: NI
A18: Name : Dillibabu
A19: Phone : 9448289351 | B19: NI
A20: Name : TEJAS Hirachand Patil
A21: Phone : 9029409611 | B21: BUSY
A22: Name : Prajakta Barde | B22: FT
A23: Phone : 7796412155 | B23: FT | C23: 10K CAPITAL | D23: KAMINI
A24: Name : Kazi irfan
A25: Phone : 9820284445 | B25: INVALID
A26: Name : Ajinkya
A27: Phone : 8422993587 | B27: NI
A28: Name : Mahendran
A29: Phone : 8807174671 | B29: INVALID
A30: Name : Meghraj
A31: Phone : 9422733029 | B31: FOLLOW UP | D31: VIKASH
A32: Name : Sudharsan r
A33: Phone : 6282317769 | B33: INTERESTED | D33: SUNITA
A34: Name : Veena G R
A35: Phone : 8884980333 | B35: FOLLOW UP | D35: RISHI
A36: Name : Ctree
A37: Phone : 7755578855 | B37: INVALID
A38: Name : Sairqk
A39: Phone : 9487868621 | B39: NPC
A40: Name : Biju
A41: Phone : 9895351574 | B41: NI
A42: Name : Balkrushna Sheshrao Pakane
A43: Phone : 8888926988 | B43: NI
A44: Name : Anand
A45: Phone : 8308820014 | B45: NC
A46: Name : Ashok Sharma
A47: Phone : 9370001378 | B47: NPC
A48: Name : Rohit Gupta
A49: Phone : 9628944620 | B49: INTERESTED | D49: SHRUTI
A50: Name : VIVEK V PATIL
A51: Phone : 9960289169 | B51: FOLLOW UP | C51: AFTER DIWALI 2 LAC | D51: AMIT
A52: Name : Nandam
A53: Phone : 9372082883 | B53: NPC
A54: Name : Sandip Varnwal
A55: Phone : 8208890523 | B55: NC
A56: Name : Harsh Patil
A57: Phone : 9322235664 | B57: NI
A58: Name : Pranay Patil
A59: Phone : 9322235664 | B59: REPEAT
A60: Name : Raj Shekhar Paul
A61: Phone : 7381144737 | B61: INTERESTED | D61: MAHENDRA
A62: Name : R P SENGUPTA | B62: FT
A63: Phone : 9007732825 | B63: FT | C63: 50K | D63: SHRUTI
A64: Name : Kiran lade
A65: Phone : 8380820592 | B65: FT | D65: NARMADA | F65: 45931
A66: Name : fhzf
A67: Phone : 9834567823 | B67: NC
A68: Name : Javed Khan
A69: Phone : 8652101467 | B69: INTERESTED | D69: SHRUTI
A70: Name : ganesh jagdale
A71: Phone : 9766883669 | B71: NI | D71: VOM
A72: Name : teee
A73: Phone : 8455068828 | B73: NC
A74: Name : Nayaz Shaik
A75: Phone : 9703392462 | B75: NC
A76: Name : Shubham Srivastava | B76: FT
A77: Phone : 8750450831 | B77: FT | D77: AYUSH
A78: Name : Manish jaideorao Bhawatkar
A79: Phone : 9890936400 | B79: CB 2 PM | D79: VOM
A80: Name : Faizan
A81: Phone : 9987904990 | B81: FOLLOW UP | D81: VISHNU
A82: Name : Ramana | B82: FT
A83: Phone : 8341590979 | B83: FT | D83: RISHI
A84: Name : Shashikumar
A85: Phone : 6364435502 | B85: NI
A86: Name : Akshay M
A87: Phone : 7276721282 | B87: NI
A88: Name : Pushkar | B88: FT
A89: Phone : 8130300680 | B89: FT | D89: SHALINA
A90: Name : Sagar Kumbar
A91: Phone : 7829964539 | B91: AFTER MARKET | D91: R C
A92: Name : Urvi
A93: Phone : 9923658868 | B93: NC
A94: Name : muniappan
A95: Phone : 7695959586 | B95: LI
A96: Name : Anurag Hebballi | B96: FT
A97: Phone : 7892252023 | B97: FT | C97: 24K repeat no. | D97: AMIT
A98: Name : Saravanan D
A99: Phone : 7449214460 | B99: NI
A100: Name : Siddhes
...

Sheet 18-10-24
A1: CLIENTS DETAIL | B1: REMARK | C1: INVESTMENT | D1: REMARK
A2: Name : UJJWAL KUMAR SINGH | H2: TOTAL LEADS - 53
A3: Phone : 8130838918 | B3: FT | D3: AJAY | E3: 17/12/2024 | H3: Date -18.10.24
A4: Name : PK Rohira | B4: FT | H4: FT | I4: 6
A5: Phone : 9891337979 | B5: FT | D5: SHRUTI | H5: INTERESTED | I5: 1
A6: Name : Sreenivasarao | B6: FT | H6: FOLLOWUP | I6: 3
A7: Phone : 9705910889 | B7: FT | C7: 50K | D7: AMIT | H7: CB | I7: 0
A8: Name : Manda | H8: BUSY | I8: 12
A9: Phone : 8180876803 | B9: NI | D9: KAMINI | H9: NI | I9: 5
A10: Name : Satender Kumar Gautam | H10: NPC | I10: 4
A11: Phone : 9013401637 | B11: SF | D11: AYUSH | H11: OTHERS | I11: 23
A12: Name : Siddarth K S
A13: Phone : 7204542910 | B13: INVALID | D13: RAJ
A14: Name : Sai priya Chejarla
A15: Phone : 8179115271 | B15: NI | D15: VIJAY
A16: Name : Vaibhav
A17: Phone : 9325161891 | B17: NI | D17: KAMINI
A18: Name : Sundar n
A19: Phone : 8610974253 | B19: LI | D19: AMIT
A20: Name : Sanjayk
A21: Phone : 7008040769 | B21: NPC | D21: RISHI
A22: Name : Naveena Kumara M
A23: Phone : 6382294922 | B23: PAID | D23: VOM
A24: Name : Raj1
A25: Phone : 9494949494 | B25: INVALID | D25: AYUSH
A26: Name : Lalitvijay kumar | B26: FT
A27: Phone : 8448621522 | B27: FT | C27: 25K | D27: VISHNU
A28: Name : BHAVIN VADHAR | B28: FT
A29: Phone : 9819100370 | B29: FT | C29: 50K | D29: KAMINI
A30: Name : शुभापुजरी
A31: Phone : 8263909574 | B31: BUSY | D31: VISHNU | J31: F
A32: Name : Rohini Mahadik
A33: Phone : 9082409412 | B33: PAID | D33: RISHI
A34: Name : Raghunathan R
A35: Phone : 9940674865 | B35: PAYMENT DONE | D35: AMIT
A36: Name : Ravi Ranjan Sinha
A37: Phone : 8303739070 | B37: NI | D37: RAJ
A38: Name : Vigneshladda
A39: Phone : 9840988999 | B39: BUSY | D39: AMIT
A40: Name : Aarti jadhav
A41: Phone : 9834451823 | B41: NI | D41: AMIT
A42: Name : Pgrthwl
A43: Phone : 9398647784 | B43: BUSY | D43: RISHI
A44: Name : Mona
A45: Phone : 9398647784 | B45: BUSY | C45: REPEAT | D45: RISHI
A46: Name : Telugy
A47: Phone : 9398647784 | B47: NPC | C47: REPEAT | D47: VOM
A48: Name : Prasad satao
A49: Phone : 9175335991 | B49: PAYMENT DONE | D49: VIJAY
A50: Name : Manju
A51: Phone : 9810211310 | B51: BUSY | D51: MAHENDRA
A52: Name : Gopall
A53: Phone : 9823308760 | B53: WRONG | D53: AMIT
A54: Name : Gopall rao
A55: Phone : 8087587042 | B55: NPC | D55: AMBRISH
A56: Name : Sudip Roy
A57: Phone : 9831662164 | B57: NI | D57: VOM
A58: Name : Balakrishnan Kv
A59: Phone : 8825944705 | B59: NI | D59: AMIT
A60: Name : anguri didi
A61: Phone : 8788507821 | B61: BUSY | D61: RISHI
A62: Name : Vigneshpaonu
A63: Phone : 9840988999 | B63: BUSY | D63: AMIT
A64: ame : Neel | M64: S
A65: Phone : 9850943524 | B65: NPC | D65: SOURABH
A66: Name : Kevin Warjri
A67: Phone : 8119823678 | B67: FOLLOW UP | D67: VOM
A68: Name : Ishwar
A69: Phone : 7738369013 | B69: BUSY | D69: JITENDAR
A70: Name : vinod mittal
A71: Phone : 9898989898 | B71: OF | C71: REPEAT | D71: AMIT
A72: Name : vinod mittal mmm
A73: Phone : 6766767664 | B73: INVALID | D73: JITENDAR
A74: Name : Navneet Nigam
A75: Phone : 9898989890 | B75: SF | D75: KAMINI
A76: Name : Phanikumar | B76: FT
A77: Phone : 9494900106 | B77: FT | C77: 1 LAC | D77: AMIT
A78: Name : Vallabh vaity | B78: FT
A79: Phone : 9324161015 | B79: FT | D79: KAMINI
A80: Name : COET
A81: Phone : 9039971400 | B81: NI | C81: INTRADAY | D81: JITENDAR
A82: Name : Vignesh
A83: Phone : 9840988999 | B83: BUSY | D83: KAMINI
A84: Name : shrinivasulu E
A85: Phone : 8884676974 | B85: FOLLOW UP | D85: VOM
A86: Name : Mohamed Hajha Ali Mohamed Ibrahim
A87: Phone : 7200712654 | B87: SF | D87: KAMINI
A88: Name : DILEEP BHAT
A89: Phone : 9108849174 | B89: FOLLOW UP | D89: VOM
A90: Name : surekha
A91: Phone : 8291491718 | B91: ALREADY PAID | C91: REPEAT | D91: VISHNU
A92: Name : Rakesh aramalla
A93: Phone : 9959524185 | B93: LI | D93: VISHNU
A94: Name : Bhagyashree samala
A95: Phone : 7738314612 | B95: NI | D95: VISHNU
A96: Name : Aviiraaj Dhere
A97: Phone : 8432752903 | B97: NI | D97: RAJ
A98: Name : Suraj Mili
A99: Phone : 9365510437 | B99: SF | D99: RC
A100: Name : Jitendra Behera
...

Sheet 17-10-24
A1: CLIENTS DETAILS | B1: REMARK | C1: INVESTMENT | D1: EMP…
A2: Name : Vinod | H2: TOTAL LEADS - 82
A3: Phone : 9632106156 | B3: BUSY | D3: RISHI | H3: Date -17.10.24
A4: Name : Venkataraju | H4: FT | I4: 11
A5: Phone : 8105930977 | B5: NPC | D5: RAJ | H5: INTERESTED | I5: 5
A6: Name : Rajath R | H6: FOLLOWUP | I6: 8
A7: Phone : 8123393957 | B7: PAID | D7: VISHNU | H7: CB | I7: 5
A8: Name : Maruthi J | H8: BUSY | I8: 14
A9: Phone : 6360061216 | B9: BUSY | D9: AMIT | H9: NI | I9: 9
A10: Name : Barundeep Singh | H10: NPC | I10: 14
A11: Phone : 9459622663 | B11: FOLLOW UP | D11: AYUSH | H11: OTHERS | I11: 18
A12: Name : Dharmesh
A13: Phone : 9773292801 | B13: NI | D13: KAMINI
A14: Name : Godwin joseph
A15: Phone : 8108026556 | B15: NI | D15: SHALINA
A16: Name : Manoj H L
A17: Phone : 8050221701 | B17: FOLLOW UP | C17: 50K | D17: RC
A18: Name : Raj bhalkar
A19: Phone : 7887875544 | B19: CB | D19: KAMINI
A20: Name : Prajwal Sharma
A21: Phone : 9036105632 | B21: FOLLOW UP | D21: KAMINI
A22: Name : Pradip Balasaheb pawar
A23: Phone : 7447565730 | B23: NPC | D23: VISHNU
A24: Name : Arul
A25: Phone : 9095947066 | B25: SF | D25: VISHNU
A26: Name : Vedant
A27: Phone : 9922229343 | B27: NI | D27: SHALINA
A28: Name : Akash Mayandibharathi
A29: Phone : 9655541772 | B29: BUSY | C29: REPEAT NO. | D29: RISHI
A30: Name : Arhaan
A31: Phone : 9964932290 | B31: NPC | D31: KAMINI
A32: Name : Mayur kharat
A33: Phone : 9158003389 | B33: SF | D33: VIJAY
A34: Name : HARDIK KOTHARI
A35: Phone : 7666999669 | B35: PAYMENT DONE | D35: VIKASH
A36: Name : Arjun Thorat
A37: Phone : 9309785511 | B37: BUSY | D37: RAJ
A38: Name : jameer
A39: Phone : 9000488900 | B39: NI | D39: MAHENDAR
A40: Name : Lakshmikanth
A41: Phone : 9986450185 | B41: BUSY | D41: AMIT
A42: Name : Raskar Govind
A43: Phone : 8208928034 | B43: FT | D43: KIRTI | F43: 45901
A44: Name : Praveen V
A45: Phone : 8660095977 | B45: FOLLOW UP | D45: VISHNU
A46: Name : Manoj G R | B46: FT
A47: Phone : 9900091355 | B47: FT | C47: 15 to 20k capital | D47: KAMINI
A48: Name : Praveen Pankaj
A49: Phone : 9811600009 | B49: NPC | D49: AYUSH
A50: Name : Arul
A51: Phone : 9095947066 | B51: SF | D51: VISHNU
A52: Name : Praveena
A53: Phone : 9940168668 | B53: FOLLOW UP | D53: AYUSH/VOM
A54: Name : Raju
A55: Phone : 9150855298 | B55: NI | D55: KAMINI
A56: Name : Thangapandian
A57: Phone : 7006792165 | B57: NPC | D57: AYUSH
A58: Name : Vebu
A59: Phone : 9444099710 | B59: INVALID | D59: VISHNU
A60: Name : Arun Ramesh | B60: FT
A61: Phone : 8940024139 | B61: FOLLOW UP | D61: NARMADA
A62: Name : Subhasis khuntia
A63: Phone : 7873266820 | B63: NI | D63: KAMINI
A64: Name : ANILKUMAR
A65: Phone : 6300040737 | B65: BUSY | D65: KAMINI
A66: Name : Beem
A67: Phone : 8558221168 | B67: INVALID | D67: KAMINI
A68: Name : Dr Ash
A69: Phone : 8762002430 | B69: CB 1:30 PM | D69: AYUSH
A70: Name : Prem Chand Arora
A71: Phone : 9811678729 | B71: BUSY | D71: KAMINI
A72: Name : Basavaraj Chinchakhandi
A73: Phone : 7019184726 | B73: INTERESTED | D73: KAMINI
A74: Name : Devaraja
A75: Phone : 9481048236 | B75: BUSY | D75: AMIT
A76: Name : Amit maan
A77: Phone : 9212651331 | B77: INTERESTED | D77: SUNITA
A78: Name : Hemanth gowda
A79: Phone : 7892784322 | B79: NPC | D79: AYUSH
A80: Name : R.Ganesh
A81: Phone : 9310431904 | B81: NI | D81: KAMINI
A82: Name : Akshay Pawar | B82: FT
A83: Phone : 9284820013 | B83: FT | C83: 20K | D83: AMIT
A84: Name : neeraj gupta
A85: Phone : 9999400558 | B85: FOLLOW UP | D85: VOM
A86: Name : AkashShewale
A87: Phone : 8007350702 | B87: NI | D87: RC
A88: Name : Name
A89: Phone : 8976545267 | B89: INVALID | D89: KAMINI
A90: Name : Jessy Binoy
A91: Phone : 9768226205 | B91: CB | D91: VOM
A92: Name : Aditya Kumar ray
A93: Phone : 9149870266 | B93: NI | D93: VOM
A94: Name : Prashant Chaturvedi
A95: Phone : 9717188966 | B95: BUSY | D95: RISHI
A96: Name : Senthil Kumar R M | B96: FT
A97: Phone : 9176666507 | B97: FT | D97: AMIT
A98: Name : Res
A99: Phone : 6756454324 | B99: INVALID | D99: VISHNU
A100: Name : rs18bhat | B100: FT
...

Sheet 19-10-24
A1: CLIENTS DETAILS | B1: REMARK | C1: INVESTMENT | D1: EMP…
A2: Name : KPS KUMAR | H2: TOTAL LEADS - 33
A3: Phone : 9344406219 | B3: PAID | D3: RISHI | H3: Date -19.10.24
A4: Name : samar jyoti patar | B4: FT | H4: FT | I4: 6
A5: Phone : 7569415264 | B5: FT | C5: 30K | D5: AMIT | H5: INTERESTED | I5: 3
A6: Name : Dr. Rahul Kathariya | H6: FOLLOWUP | I6: 1
A7: Phone : 8983370741 | B7: FOLLOW UP | D7: VOM | H7: CB | I7: 2
A8: Phone : Name : samar jyoti patar | B8: FT | H8: BUSY | I8: 3
A9: Phone : 7569415264 | B9: FT | C9: 30K | D9: AMIT | H9: NI | I9: 1
A10: Name : Kuppusamy | B10: FT | H10: NPC | I10: 9
A11: Phone : 9944611537 | B11: FT | D11: RISHI | H11: OTHERS
A12: Name : Amol pawar
A13: Phone : 8668453535 | B13: CB | D13: VOM
A14: Name : Manja
A15: Phone : 9398647784 | B15: NPC | C15: REPEAT | D15: VISHNU
A16: Name : Gokul Krishna
A17: Phone : 7736785886 | B17: CD | D17: AMIT
A18: Name : Vijay singh
A19: Phone : 9650471000 | B19: NI | D19: KAMINI
A20: Name : Gokul Krishna
A21: Phone : 7736785886 | B21: BUSY | D21: AMIT
A22: Name : Titus Dsouza
A23: Phone : 9167193636 | B23: NPC | D23: VISHNU
A24: Name : Tanish
A25: Phone : 6380237495 | B25: NPC | D25: AMBRISH
A26: Name : Aditya Nanda
A27: Phone : 8439956966 | B27: NC | D27: KAMINI
A28: Name : Chandra Mohan
A29: Phone : 7989567987 | B29: BUSY | D29: AMIT
A30: Name : Kg ykxx vvjc
A31: Phone : 6655544565 | B31: INVALID | D31: VISHNU
A32: Name : Abhishek m b | B32: FT
A33: Phone : 8762314350 | B33: FT | C33: 1LAC | D33: AMIT
A34: Name : Manpreet Kaur
A35: Phone : 9717518277 | B35: INTERESTED | C35: NEXT MOUNTH | D35: KAMINI
A36: Name : chandru
A37: Phone : 9353414891 | B37: CB 4PM | D37: VOM
A38: Name : Rajesh Kumar panda
A39: Phone : 8917445849 | B39: FOLLOW UP | D39: VISHNU
A40: Name : Dharmendra
A41: Phone : 9039971400 | B41: NI | D41: VISHNU
A42: Name : ramki
A43: Phone : 9700038333 | B43: NI | D43: AYUSH
A44: Name : Girish Kulkarani | B44: FT
A45: Phone : 9960047053 | B45: FT | C45: 50K | D45: AMIT
A46: Name : LAKSHMANAN | B46: FT
A47: Phone : 9566593741 | B47: FT | C47: 50K+ | D47: KAMINI
A48: Name : Satish Kumar
A49: Phone : 9492742078 | B49: NI | D49: AMIT
A50: Name : Nazmunnisha Khan
A51: Phone : 9821947860 | B51: FOUND ISSUE | C51: 2K | D51: AYUSH
A52: Name : Madhuri Sadalage
A53: Phone : 7040655924 | B53: FOLLOW UP | D53: KIRTI
A54: Name : Anas
A55: Phone : 9961759291 | B55: FOLLOW UP | D55: VOM
A56: Name : Radhey Sham Aggarwal | B56: FT
A57: Phone : 9910036611 | B57: FT | C57: 1LAC | D57: AMIT
A58: Name : Narawade
A59: Phone : 9767723939 | B59: NC | D59: ARUN
A60: Name : Priyanshu Doshi
A61: Phone : 8763248100 | B61: INTERESTED | D61: KAMINI
A62: Name : Gkg
A63: Phone : 8357828284 | B63: INVALID | D63: VOM
A64: Name : Srishti Koshija
A65: Phone : 9899872928 | B65: NI | D65: AYUSH
A66: Name : Purushoth
A67: Phone : 7010268158 | B67: NPC | D67: RISHI
A68: Name : Amruta | B68: FT
A69: Phone : 7259103700 | B69: FT | C69: 1K | D69: AMIT

Sheet TODAY 21-10-24
A1: CLIENTS DETAILS | B1: REMARK | C1: INVESTMENT | D1: EMP… | G1: TOTAL LEADS - 59
A2: Name : Mahima Bisen 21 | G2: Date -21.10.24
A3: Phone : 8770310812 | B3: NI | D3: KAMINI | G3: FT | H3: 8
A4: Name : Chinmay Sethiya | G4: INTERESTED | H4: 1
A5: Phone : 8122051870 | B5: NI | D5: KAMINI | G5: FOLLOWUP | H5: 3
A6: Name : Baskar7982 | G6: CB | H6: 6
A7: Phone : 9994875586 | B7: NI | D7: AYUSH | G7: BUSY | H7: 4
A8: Name : Parmeshwar Shinde | G8: CD | H8: 5
A9: Phone : 9850866243 | B9: BUSY | D9: JITENDRA | G9: NI | H9: 9
A10: Name : Gaurav Upadhyay | G10: NPC | H10: 17
A11: Phone : 9873983990 | B11: CB EVENING | D11: RISHI | G11: OTHERS | H11: 6
A12: Name : Atri
A13: Phone : 9538162322 | B13: NI | C13: REPEAT | D13: VIJAY
A14: Name : Ishwar Chaudhari
A15: Phone : 8956752696 | B15: FT | C15: 45K | D15: KAMINI
A16: Name : Ranjan
A17: Phone : 7978184161 | B17: NPC | D17: AMIT
A18: Name : RK Venkatesh
A19: Phone : 8463959107 | B19: CD | D19: KAMINI
A20: Name : Nawaz
A21: Phone : 8864036651 | B21: NC | D21: VIJAY
A22: Name : Shanmugasunderam
A23: Phone : 9884876096 | B23: CB | D23: VIKASH
A24: Name : Rajeshvijayan m
A25: Phone : 9840220404 | B25: NI | D25: SHIVANI
A26: Name : Jaydeep
A27: Phone : 7030131383 | B27: FOLLOW UP | D27: VOM
A28: Name : Phamdom Prince Singh
A29: Phone : 9910396513 | B29: BUSY | D29: RITU
A30: Name : Boopathi
A31: Phone : 6380239291 | B31: NI | D31: VIKASH
A32: Name : TEJAS SHASTRI
A33: Phone : 9986813658 | B33: BUSY | D33: KAMINI
A34: Name : Guna
A35: Phone : 9066066096 | B35: NI | D35: AMIT
A36: Name : Udayakumar
A37: Phone : 8903386001 | B37: NI | D37: VIKASH
A38: Name : bharti
A39: Phone : 9600399985 | B39: CD | D39: VIKASH
A40: Name : Mohd samim
A41: Phone : 8081558827 | B41: FT | C41: 10K | D41: KAMINI
A42: Name : Shreya
A43: Phone : 8421282434 | B43: NI | D43: VOM
A44: Name : Manjeet Singh
A45: Phone : 7980369924 | B45: FT | D45: AYUSH
A46: Name : Ravi Kumar
A47: Phone : 9654859957 | B47: NI | D47: AMIT
A48: Name : John guite
A49: Phone : 9862299587 | B49: BUSY | D49: VOM
A50: Name : Pallavi Naik
A51: Phone : 8971975347 | B51: CD | D51: KAMINI
A52: Name : Shalini
A53: Phone : 9628095793 | B53: NPC | D53: VOM
A54: Name : Pankaj Tiwary
A55: Phone : 9234567890 | B55: SF | C55: REPEAT | D55: KAMINI
A56: Name : Yugi
A57: Phone : 8123268700 | B57: NI | D57: VOM
A58: Name : RAMCHARAM MEGASATR
A59: Phone : 9575644344 | B59: WRONG | D59: VOM
A60: Name : King
A61: Phone : 8868547557 | B61: INVALID | D61: AMIT
A62: Name : Amruta
A63: Phone : 7259103700 | B63: FT | C63: 1K | D63: AMIT
A64: Name : Shital Ajay Kadam
A65: Phone : 9130234170 | B65: FT | C65: 50K | D65: AMIT
A66: Name : Sathvik
A67: Phone : 9448232609 | B67: NPC | D67: VOM
A68: Name : Jampa mahesh rao
A69: Phone : 7377098021 | B69: FT | C69: 1K | D69: AMIT
A70: Name : Kasthuri
A71: Phone : 9092252101 | B71: FOLLOW UP | D71: AMIT
A72: Name : Rohan Harulage
A73: Phone : 9762369675 | B73: FT | D73: KAMINI
A74: Name : Deepak badgujar
A75: Phone : 9325967010 | B75: BUSY | D75: AMIT
A76: Name : SHASHIDAR sopper
A77: Phone : 9535706470 | B77: NPC | D77: VOM
A78: Name : Poonam anchan
A79: Phone : 7506221264 | B79: FT | C79: 50K | D79: AMIT
A80: Name : puviyarasu
A81: Phone : 8825519670 | B81: NPC | D81: VOM
A82: Name : Ashwini pudale
A83: Phone : 7757987675 | B83: NPC | D83: VOM
A84: Name : Ameen
A85: Phone : 9908703876 | B85: CD | D85: AYUSH
A86: Name : ajinkyaa
A87: Phone : 9028666676 | B87: FT | C87: 50k | D87: VISHNU
A88: Name : Dharmaraj .P
A89: Phone : 9087687657 | B89: INVALID | D89: VISHNU
A90: Name : Saleem khan
A91: Phone : 8700719519 | B91: FOLLOW UP | D91: VISHNU
A92: Name : Senthil Kumar
A93: Phone : 7358727191 | B93: NPC | D93: AMIT
A94: Name : samar raj
A95: Phone : 7250975297 | B95: FT | C95: 10K | D95: VOM
A96: Name : SUMEET AGRAWAL
A97: Phone : 9953452855 | B97: INVALID | D97: VISHNU
A98: Name : Prakash Avasank
A99: Phone : 9892530736 | B99: NI | C99: REPEAT NO | D99: KAMINI
A100: Name : Abilas
...

Sheet 21-10-24
A1: CLIENTS DETAILS | B1: REMARK | C1: INVESTMENT | D1: EMP…
A2: Name : sabyasachi barik | H2: TOTAL LEADS - 112
A3: Phone : 9668688811 | B3: NPC | D3: KAMINI | H3: Date -21.10.24
A4: Name : Roy | H4: FT | I4: 8
A5: Phone : 8262038635 | B5: NI | D5: VOM | H5: INTERESTED | I5: 1
A6: Name : Bhupendra Meher | H6: FOLLOWUP | I6: 5
A7: Phone : 8446487990 | B7: NI | D7: RISHI | H7: CB | I7: 9
A8: Name : Krishuu | H8: BUSY | I8: 8
A9: Phone : 7057323657 | B9: NI | D9: AMIT | H9: CD | I9: 6
A10: Name : Vamsi | H10: NI | I10: 21
A11: Phone : 9753041979 | B11: SF | D11: VISHNU | H11: NPC | I11: 35
A12: Name : Rajat panigrahy | H12: OTHERS | I12: 20
A13: Phone : 9438293909 | B13: BUSY | D13: RITU
A14: Name : Sunakar Rout
A15: Phone : 9861106424 | B15: FUND ISSUE | D15: AYUSH
A16: Name : Dilip Desai
A17: Phone : 7710928635 | B17: INTERESTED | D17: RAJ
A18: Name : Liju
A19: Phone : 9072792516 | B19: NI | D19: RAJ
A20: Name : Dhanesh chikhale
A21: Phone : 8208804996 | B21: CB | D21: VINAY
A22: Name : Ra i
A23: Phone : 7090583628 | B23: NPC | D23: JITENDRA
A24: Name : Spp
A25: Phone : 8118059130 | B25: NI | C25: ` | D25: SHIVANI
A26: Name : Ganesh hambir
A27: Phone : 9702104757 | B27: NI | D27: VIJAY
A28: Name : Raviraj Chopdar
A29: Phone : 7447692443 | B29: NI | C29: AFTER MARKET | D29: KAMINI
A30: Name : Harshithaa. M
A31: Phone : 6362958657 | B31: NPC | D31: AMBRISH
A32: Name : Patakamuri
A33: Phone : 9545015356 | B33: NPC | D33: RISHI
A34: Name : NITIN JAIN
A35: Phone : 9810371278 | B35: NI | D35: VISHNU
A36: Name : Lakshminarayana
A37: Phone : 9343735842 | B37: NC | D37: KAMINI
A38: Name : APIUTH
A39: Phone : 9884582101 | B39: NI | D39: RAJ
A40: Name : R Muthukumar
A41: Phone : 9150789764 | B41: NI | D41: RISHI
A42: Name : pratham
A43: Phone : 8890829004 | B43: NI | D43: AMAR
A44: Name : vamsikrishnan
A45: Phone : 9884433193 | B45: NC | D45: VOM
A46: Name : K v k swamy
A47: Phone : 9677278913 | B47: NPC | D47: SHIVANI
A48: Name : Sukanya
A49: Phone : 8884388853 | B49: FORWORD | D49: RAJ
A50: Name : Jayaraman
A51: Phone : 9443855722 | B51: NI | D51: VIJAY
A52: Name : Dhupam Raju
A53: Phone : 9490244275 | B53: NPC | D53: AYUSH
A54: Name : Yogesh
A55: Phone : 7066769919 | B55: NI | D55: NANDINI
A56: Name : md bilaladdin
A57: Phone : 8210014558 | B57: FOLLOW UP | D57: AMBRISH
A58: Name : Aarti patil
A59: Phone : 9209911833 | B59: NC | D59: VOM
A60: Name : Bishal sil
A61: Phone : 8618173688 | B61: CB | D61: RITU
A62: Name : Prakash Mullur
A63: Phone : 9986118961 | B63: NI | D63: AYUSH
A64: Name : Biplab Chowdhury
A65: Phone : 6290625567 | B65: NI | D65: RISHI
A66: Name : Shiv Mohan Papneja
A67: Phone : 8882225445 | B67: NPC | D67: VOM
A68: Name : Johnson Prakash Lobo
A69: Phone : 7349429841 | B69: NI | D69: VIKASH
A70: Name : Jafser Abdulla
A71: Phone : 9605859120 | B71: INTERESTED | C71: eqt cash , in loss 50k | D71: KAMINI
A72: Name : Anjan
A73: Phone : 9880850380 | B73: NPC | C73: REPEAT | D73: SHIVANI
A74: Name : BHARAT CHANDRA DAS
A75: Phone : 7735838058 | B75: NI | D75: AYUSH
A76: Name : Nasir
A77: Phone : 9986418913 | B77: CB TOMORROW | D77: RAJ
A78: Name : Anoop kumar adhikari
A79: Phone : 9479523022 | B79: NI | D79: RISHI
A80: Name : Veeresh
A81: Phone : 8722325258 | B81: INVALID | D81: JITENDRA
A82: Name : Satyajeet Kumar singh
A83: Phone : 8271638050 | B83: NI | D83: NANDINI
A84: Name : Priyanka
A85: Phone : 9990888790 | B85: NPC | D85: AYUSH
A86: Name : Anisha S
A87: Phone : 9897567533 | B87: NPC | D87: RAJ
A88: Name : Kona srinu
A89: Phone : 9912252443 | B89: BUSY | C89: REPEAT | D89: RISHI
A90: Name : Sharad
A91: Phone : 9623419008 | B91: NI | D91: KAMINI
A92: Name : Praveen Kumar
A93: Phone : 9365234667 | B93: FOLLOW UP | D93: AMBRISH
A94: Name : AshokSharma
A95: Phone : 9230303334 | B95: NI | D95: ARUN
A96: Name : Harshit
A97: Phone : 8692927060 | B97: NI | D97: NANDINI
A98: Name : Archi
A99: Phone : 9945407979 | B99: INVALID | D99: RITU
A100: Name : Rsk
...

Sheet Sheet1
A1: TOTAL LEADS -
A2: Date -
A3: FT
A4: INTERESTED
A5: FOLLOWUP
A6: CB
A7: BUSY
A8: CD
A9: NI
A10: NPC
A11: OTHERS

Sheet Sheet7
A1: TOTAL LEADS -
A2: Date -
A3: FT
A4: INTERESTED
A5: FOLLOWUP
A6: CB
A7: BUSY
A8: CD
A9: NI
A10: NPC
A11: OTHERS

Sheet 22-10-2024
A1: CLIENTS DETAILS | B1: REMARK | C1: INVESTMENT | D1: EMP… | G1: TOTAL LEADS - 43
A2: Name : Sohan K | G2: Date -22.10.24
A3: Phone : 8767192253 | B3: PAYMENT DONE | D3: KAMINI | G3: FT | H3: 4
A4: Name : Rohittttttttttt | G4: INTERESTED | H4: 3
A5: Phone : 9968114181 | B5: SF | D5: RAJ | G5: FOLLOWUP | H5: 3
A6: Name : MANOJ BASUTKAR | G6: CB | H6: 5
A7: Phone : 9930161763 | B7: BUSY | C7: REPEAT NO…. | D7: AMIT | G7: BUSY | H7: 2
A8: Name : Ruksar | G8: CD | H8: 1
A9: Phone : 9967894851 | B9: NPC | D9: VISHNU | G9: NI | H9: 1
A10: Name : RAMALLA JOSEPH | G10: NPC | H10: 10
A11: Phone : 9182230137 | B11: LI | D11: AYUSH | G11: OTHERS | H11: 13
A12: Name : Joseph
A13: Phone : 9182230127 | B13: WRONG NO….. | D13: VOM
A14: Name : SHAIKH Ali
A15: Phone : 8010836792 | B15: CAPITAL ISSUE | D15: VOM
A16: Name : Deborshe Dutta
A17: Phone : 6370416011 | B17: DETAIL SEND | D17: RISHI
A18: Name : Amol Raut | B18: FT
A19: Phone : 9021986751 | B19: FT | C19: 50K LOSS ,7K | D19: KAMINI
A20: Name : Shaikh hunain
A21: Phone : 9175747938 | B21: NI | D21: VOM
A22: Name : Janesh
A23: Phone : 8169098400 | B23: PAYMENT DONE | D23: KAMINI
A24: Name : Swati
A25: Phone : 7709848649 | B25: FT | D25: RANJANA | F25: 45931
A26: Name : Telepu lanja
A27: Phone : 8712326390 | B27: LI | D27: AMIT
A28: Name : Sundar n
A29: Phone : 8610974253 | B29: CD | C29: REPEAT NO…. | D29: KAMINI
A30: Name : Eru halyapnor
A31: Phone : 8668490175 | B31: NI | D31: VISHNU
A32: Name : Mahesh Mhatre
A33: Phone : 9975033909 | B33: CB | D33: AMAR
A34: Name : Sanjay Bora
A35: Phone : 9322267596 | B35: NI | D35: SHIVANI
A36: Name : Omappa
A37: Phone : 9731408234 | B37: NI | D37: VOM
A38: Name : Irfan Maner
A39: Phone : 8237621054 | B39: FOLLOW UP | C39: 5K | D39: AMIT
A40: Name : Mohanlal
A41: Phone : 9840062460 | B41: INTERESTED | C41: 1 LAC + | D41: KAMINI
A42: Name : T Vishnu vardhan
A43: Phone : 8897678078 | B43: NPC | D43: KAMINI
A44: Name : fernando .G
A45: Phone : 7639929708 | B45: LI | D45: RISHI
A46: Name : Myran
A47: Phone : 9744130201 | B47: SF | D47: AMIT
A48: Name : Pariyan
A49: Phone : 8129730666 | B49: CB EVENING | D49: VISHNU
A50: Name : J.SENTHIL KUMAR
A51: Phone : 9487861303 | B51: SF | D51: KAMINI
A52: Name : Rishit Garg
A53: Phone : 8595646344 | B53: FOLLOW UP | D53: VOM
A54: Name : Pieya gogawale
A55: Phone : 9175905008 | B55: INTERESTED | D55: MAHENDRA
A56: Name : Aahan Devadiga
A57: Phone : 9834845931 | B57: NI | D57: VOM
A58: Name : Pramesh
A59: Phone : 9010443341 | B59: WTSP | D59: KAMINI
A60: Name : Ganpat Pandey
A61: Phone : 8505969524 | B61: NI | D61: HARIOM
A62: Name : Rajesh riya
A63: Phone : 6380711701 | B63: CAPITAL ISSUE | D63: KAMINI
A64: Name : N MANJUNATH
A65: Phone : 9845665585 | B65: DETAIL SEND | D65: RISHI
A66: Name : gousri
A67: Phone : 9075020925 | B67: NI | D67: VOM
A68: Name : Dayaram Bhanushali
A69: Phone : 9664344206 | B69: NPC | D69: VOM
A70: Name : Anil Paul
A71: Phone : 8281542411 | B71: FOLLOW UP | D71: RISHI
A72: Name : Swetha
A73: Phone : 8618176583 | B73: FOLLOW UP | D73: VOM
A74: Name : Nagaraj B | B74: FT
A75: Phone : 8496841234 | B75: FT | D75: VIJAY
A76: Name : Md Tarique Alam | B76: FT
A77: Phone : 6299221854 | B77: FT | C77: 20K | D77: VOM
A78: Name : Samrut Sukte
A79: Phone : 9921785035 | B79: INTERESTED | D79: MAHENDRA
A80: Name : Dhairyashil deshmukh
A81: Phone : 9130704457 | B81: NC | D81: RC
A82: Name : vinod ydadv
A83: Phone : 7887863475 | B83: FOLLOW UP | D83: VOM
A84: Name : Ayubkhan
A85: Phone : 9744744777 | B85: PAYMENT DONE | C85: 50LAC CAPITAL | D85: KAMINI
A86: Name : Parveen Kumar
A87: Phone : 8708497214 | B87: NI | D87: RC
A88: Name : Pieya gogawale
A89: Phone : 9175905008 | B89: FOLLOW UP | D89: SNEHA

Sheet 23-10-24
A1: CLIENTS DETAILS | B1: REMARK | C1: INVESTMENT | D1: EMP…
A2: Name : Kathiravan | F2: TOTAL LEADS - 50
A3: Phone : 9626618105 | B3: NI | D3: KAMINI | F3: Date -23.10.24
A4: name:sunil kumar mahala | B4: FT | F4: FT | G4: 4 | H4: 2
A5: Phone : 9938515326 | B5: FT | C5: 50K | D5: MANSING | E5: 28/12/2024 | F5: INTERESTED | G5: 7
A6: Name : Nagarathinam | F6: FOLLOWUP | G6: 5 | H6: 1
A7: Phone : 9840301101 | B7: NPC | D7: VOM | F7: CB | G7: 4
A8: Name : Vidya | F8: BUSY | G8: 2
A9: Phone : 9900378642 | B9: PAYMENT DONE | D9: ABHAY | F9: CD | G9: 2
A10: Name : Pranav | F10: NI | G10: 6
A11: Phone : 7757006362 | B11: NI | D11: VIKASH | F11: NPC | G11: 13
A12: Name : Pradeep kumar | F12: OTHERS | G12: 7
A13: Phone : 8490032346 | B13: CB 4PM | D13: RISHI
A14: Name : Juned
A15: Phone : 9284157540 | B15: INTERESTED | D15: MAHENDRA
A16: Name : Kalyan Karande
A17: Phone : 7263956744 | B17: CD | D17: VISHNU
A18: Name : Debajyoti
A19: Phone : 9632248586 | B19: PAYMENT DONE | D19: VOM
A20: Name : Swati
A21: Phone : 7709848649 | B21: FOLLOW UP | D21: VOM
A22: Name : M srinibas Rao
A23: Phone : 9437305754 | B23: FOLLOW UP | C23: REPEAT | D23: AYUSH
A24: Name : Keerthi vasan
A25: Phone : 6369695012 | B25: CD | D25: RAJ
A26: Name : Abh
A27: Phone : 9172515944 | B27: INTERESTED | D27: MAHENDRA
A28: Name : Sweety Chauhan
A29: Phone : 8999789611 | B29: FUND ISSUE | C29: 6K | D29: RAJ
A30: Name : Shiv
A31: Phone : 9899883414 | B31: INTERESTED | D31: JITENDRA
A32: Name : Chandrahasa
A33: Phone : 9480116680 | B33: CAPITAL ISSUE | D33: VIKASH
A34: Name : Manikandan | B34: FT
A35: Phone : 9841338829 | B35: FT | C35: 30K-40K | D35: AYUSH
A36: Name : S M BIRADAR
A37: Phone : 9740625189 | B37: INTERESTED | C37: DETAIL SEND | D37: VIKASH
A38: Name : Tushar kadam
A39: Phone : 8779839655 | B39: NC | D39: RAJ
A40: Name : Babu c
A41: Phone : 9043262224 | B41: INTERESTED | D41: MAHENDRA
A42: Name : Shimit Singh
A43: Phone : 9044371493 | B43: NI | D43: MAHENDRA
A44: Name : Kapil
A45: Phone : 9764978664 | B45: FOLLOW UP | D45: VIKASH
A46: Name : ajeet456 | B46: FT
A47: Phone : 9777762166 | B47: FT | C47: 25K | D47: KAMINI
A48: Name : Prajakta
A49: Phone : 9561308831 | B49: FOLLOW UP | D49: KAMINI
A50: Name : Ehh
A51: Phone : 8288281828 | B51: SW | D51: VOM
A52: Name : Ajitkumar Dash
A53: Phone : 8249845708 | B53: FOLLOW UP | D53: ABHAY
A54: Name : uwaiz Qureshi
A55: Phone : 8217576126 | B55: NI | D55: VIKASH
A56: Name : Vardan | B56: FT
A57: Phone : 9897047799 | B57: FT | C57: 20K | D57: AMIT
A58: Name : Vysakh
A59: Phone : 7066285451 | B59: FOLLOW UP | D59: VIKASH
A60: Name : vidhal
A61: Phone : 9692564727 | B61: NPC | D61: VOM
A62: Name : Balamurali Jeganathan
A63: Phone : 9842472798 | B63: NI | D63: VIKASH
A64: Name : Collection
A65: Phone : 9511854567 | B65: NPC | D65: VIJAY
A66: Name : apps
A67: Phone : 9890189438 | B67: INTERESTED | D67: JITENDRA
A68: Name : ruchita
A69: Phone : 9768051261 | B69: NI | D69: VIJAY
A70: Name : Nisam
A71: Phone : 9645650002 | B71: FOLLOW UP | D71: VOM
A72: Name : Jakir hussain
A73: Phone : 9940722486 | B73: NI | D73: RAJ
A74: Name : kjjl
A75: Phone : 6976697697 | B75: INVALID | D75: AMIT
A76: Name : Chahat Aggrawal
A77: Phone : 9250197283 | B77: ADVISOR | D77: VIJAY
A78: Name : Arunesh
A79: Phone : 9430349677 | B79: BUSY | D79: KAMINI
A80: Name : Rashmi
A81: Phone : 8197932935 | B81: NPC | D81: VOM
A82: Name : sailendran.D
A83: Phone : 9840666122 | B83: INTERESTED | D83: RAJ
A84: Name : v k
A85: Phone : 6765678763 | B85: INVALID | D85: VISHNU
A86: Name : satyanarayana | B86: FT
A87: Phone : 7013306282 | B87: FT | C87: 30K | D87: VISHNU
A88: Name : Tanvid
A89: Phone : 7777087256 | B89: NPC | D89: VIKASH
A90: Name : jagadesh
A91: Phone : 9148475022 | B91: NPC | D91: AYUSH
A92: Name : Chitra
A93: Phone : 8123217004 | B93: ONLY LEARNING | D93: AMIT
A94: Name : Subhashree pradhan
A95: Phone : 9348172937 | B95: NI | D95: AMIT
A96: Name : Jainty T
A97: Phone : 7303425678 | B97: PAYMENT DONE | D97: VYOM
A98: Name : Abhijit amde
A99: Phone : 8149174072 | B99: INTERESTED | D99: MAHENDRA
A100: Name : Suvam behera
...

Sheet 24-10-24
A1: CLIENTS DETAILS | B1: REMARK | C1: INVESTMENT | D1: EMP…
A2: Name : I am sakaham | G2: TOTAL LEADS -52
A3: Phone : 7821055529 | B3: SF | D3: AMIT | G3: Date -24.10.24
A4: Name : Bagtavar | G4: FT | H4: 7
A5: Phone : 9145615006 | B5: CD | D5: KAMINI | G5: INTERESTED | H5: 4
A6: Name : Vinod sultane | G6: FOLLOWUP | H6: 6
A7: Phone : 9604020588 | B7: 2K CAPITAL | D7: RITU | G7: CB | H7: 0
A8: Name : Depu | G8: BUSY | H8: 2
A9: Phone : 9028553001 | B9: INVALID | D9: RAJ | G9: CD | H9: 6 | L9: 36
A10: Name : Naresh | G10: NI | H10: 6 | L10: =49-39 -> 10
A11: Phone : 9060465599 | B11: NPC | D11: MAHENDRA | G11: NPC | H11: 9
A12: Name : Ritesh patil | G12: OTHERS | H12: 10
A13: Phone : 9272105354 | B13: BLOCK | D13: VIKASH
A14: Name : K suganya
A15: Phone : 7550055114 | B15: LI | D15: RISHI
A16: Name : laxman rathod
A17: Phone : 7721025407 | B17: NI | D17: VIKASH
A18: Name : Billal
A19: Phone : 8939807890 | B19: BUSY | D19: AMIT
A20: Name : Manju reddy
A21: Phone : 8197687847 | B21: LI WTSP | D21: AMIT
A22: Name : ayush
A23: Phone : 7852454545 | B23: INVALID | D23: VIJAY
A24: Name : sadananda
A25: Phone : 9480869369 | B25: SF | D25: VYOM
A26: Name : Abbas Dhinojwala
A27: Phone : 9380105448 | B27: FOLLOW UP | D27: VYOM
A28: Name : Purna
A29: Phone : 9848833355 | B29: LI | D29: VIKASH
A30: Name : Hhh
A31: Phone : 9362626252 | B31: NI | D31: RAJ
A32: Name : bride name
A33: Phone : 9676547463 | B33: SF | D33: MAHENDRA
A34: Name : Ghu
A35: Phone : 9340299468 | B35: INVALID | D35: AMIT
A36: Name : MATTADODDI SURENDRA
A37: Phone : 8522073560 | B37: FOLLOW UP | D37: VISHNU
A38: Name : Rakhi | B38: FT
A39: Phone : 8169440012 | B39: FT | C39: 2 TO 5 LAC | D39: KAMINI
A40: Name : dfsdfsdfsdf
A41: Phone : 8745963210 | B41: INVALID | D41: VYOM
A42: Name : Mohanraj Chinraj | B42: FT
A43: Phone : 9578504573 | B43: FT | C43: 30K | D43: AMIT
A44: Name : loudesh
A45: Phone : 9845792786 | B45: NPC | D45: MAHENDRA
A46: Name : Darshan Jain
A47: Phone : 9096960206 | B47: INTERESTED | D47: MAHENDRA
A48: Name : swarup Patil
A49: Phone : 6363561808 | B49: NPC | D49: RISHI
A50: Name : Mohammed Askar
A51: Phone : 6383756165 | B51: NI | D51: KAMINI
A52: Name : Ankush Yadav Thange
A53: Phone : 9869772554 | B53: INTERESTED | D53: RAJ
A54: Name : Paresh Chaudhari | B54: FT
A55: Phone : 7030199010 | B55: FT | C55: 10K | D55: AMIT
A56: Name : Kjj
A57: Phone : 6788568877 | B57: INVALID | D57: RAJ
A58: Name : H
A59: Phone : 8765567778 | B59: WRONG NO.. | D59: VISHNU
A60: Name : Uday jangid
A61: Phone : 9561047547 | B61: NC | D61: VISHNU
A62: Name : Jay Prakash Sah
A63: Phone : 9938032985 | B63: CB | D63: KAMINI
A64: Name : radhika patil
A65: Phone : 8792039218 | B65: NPC | D65: R C
A66: Name : Yesbank
A67: Phone : 7897383887 | B67: NI | D67: RAJ
A68: Name : Rahulsam
A69: Phone : 9167160096 | B69: NPC | D69: AMIT
A70: Name : Girish Jayantrao Patil
A71: Phone : 8149453953 | B71: INTERESTED | D71: AYUSH
A72: Name : Nithya Manjunath
A73: Phone : 9618988484 | B73: NPC | D73: AMIT
A74: Name : Piuli Dey
A75: Phone : 8904681801 | B75: FOLLOW UP | D75: VYOM
A76: Name : Chitra vanam
A77: Phone : 9372475973 | B77: INTERESTED | D77: VIJAY
A78: Name : Ghj
A79: Phone : 9145789531 | B79: NC | D79: RISHI
A80: Name : fairooshamv
A81: Phone : 9544573733 | B81: NI | D81: VIKASH
A82: Name : Yuvraj4070
A83: Phone : 9529105594 | B83: NPC | D83: MAHENDRA
A84: Name : Gopinath S
A85: Phone : 7358707398 | B85: PAYMENT DONE | D85: RISHI
A86: Name : Sam
A87: Phone : 9874576234 | B87: INVALID | C87: S | D87: AYUSH
A88: Name : Shafeeq Ahmed
A89: Phone : 8825599063 | B89: FOLLOW UP | D89: VYOM
A90: Name : Pushpakpatil
A91: Phone : 9860117030 | B91: NI | D91: VYOM
A92: Name : adil jhatam | B92: FT
A93: Phone : 8008578314 | B93: FT | C93: 1 LAC | D93: AMIT
A94: Name : vishalkokil
A95: Phone : 9096769651 | B95: NI | D95: KAMINI
A96: Name : Krishna Gopi challa
A97: Phone : 8686443648 | B97: FOLLOW UP | D97: VYOM
A98: Name : Lawrence Peter | B98: FT
A99: Phone : 9845244551 | B99: FT | C99: 25K | D99: KAMINI
A100: Name : Dsrao | B100: FT
...

Sheet 25-10-24
A1: CLIENTS DETAILS | B1: REMARK | C1: INVESTMENT | D1: EMP…
A2: Name : vijaya krishnakumar iyer | B2: FT | G2: TOTAL LEADS - 40
A3: Phone : 9322226307 | B3: FT | D3: KAMINI | G3: Date -25.10.24
A4: Name : Chandrashekhar | G4: FT | H4: 7
A5: Phone : 8468996680 | B5: SF | D5: MAHENDRA | G5: INTERESTED | H5: 2
A6: Name : Malli | G6: FOLLOWUP | H6: 2
A7: Phone : 7674943527 | B7: NPC | D7: RAJ | G7: CB | H7: 1
A8: Name : Prathamesh | G8: BUSY | H8: 1
A9: Phone : 9422603334 | B9: FT | C9: 50K | D9: KAMINI | E9: 45536 | G9: CD | H9: 0
A10: Name : MANOJ BASUTKAR | G10: NI | H10: 8
A11: Phone : 9930161763 | B11: INTERESTED | C11: REPEAT | D11: VIKASH | G11: NPC | H11: 8
A12: Name : Vanita | G12: OTHERS | H12: 11
A13: Phone : 9538538407 | B13: INTERESTED
A14: Name : Bharath gundappa
A15: Phone : 8970537616 | B15: PAYMENT DONE | D15: VISHNU
A16: Name : Neha salvi
A17: Phone : 9833662189 | B17: NPC | D17: VIJAY
A18: Name : Suganya
A19: Phone : 7010533203 | B19: NPC | D19: KAMINI
A20: Name : Harsh padave
A21: Phone : 9137886014 | B21: NPC | D21: VYOM
A22: Name : Rakshitha
A23: Phone : 8904399534 | B23: FOLLOW UP | D23: VISHNU
A24: Name : Rakesh Tiwari | B24: FT
A25: Phone : 9932072182 | B25: FT | C25: 1 LAC | D25: VIKASH
A26: Name : Nithya
A27: Phone : 9618988424 | B27: SF | D27: RISHI
A28: Name : kanika arora
A29: Phone : 6284210159 | B29: NI | D29: RAJ
A30: Name : k.p.chinnaswmy
A31: Phone : 9244804550 | B31: PAYMENT DONE | D31: AYUSH
A32: Name : Ankita
A33: Phone : 6361450872 | B33: FOLLOW UP | C33: AFTR DIWALI | D33: KAMINI
A34: Name : Bunty
A35: Phone : 7798319595 | B35: NC | D35: KAMINI
A36: Name : Pawan
A37: Phone : 8178939277 | B37: NI | D37: VOM
A38: Name : Sharif | B38: FT
A39: Phone : 9819589537 | B39: FT | C39: 30K | D39: AMIT
A40: Name : Mangi Lal Sharma
A41: Phone : 9352222083 | B41: BUSY | D41: KAMINI
A42: Name : Basic Package
A43: Phone : 7808798890 | B43: SF | D43: AMIT
A44: Name : amar
A45: Phone : 7488325689 | B45: NI | D45: RAJ
A46: Name : sdfdf
A47: Phone : 9004900107 | B47: NC | D47: KAMINI
A48: Name : Dusmanta Kumar Sahoo
A49: Phone : 7682817455 | B49: NPC | D49: RITU
A50: Name : Krishnan m
A51: Phone : 9343425715 | B51: NPC | D51: VIJAY
A52: Name : Subharamyee
A53: Phone : 7894759124 | B53: NI | D53: RISHI
A54: Name : Puja
A55: Phone : 9437928942 | B55: NI | D55: VISHNU
A56: Name : Dash
A57: Phone : 8260578434 | B57: FOLLOW UP | D57: AYUSH
A58: Name : Archana Mishra | B58: FT
A59: Phone : 8169101158 | B59: FT | C59: 20K | D59: AMIT
A60: Name : Taha Hafiz Kazi
A61: Phone : 8291321321 | B61: INTERESTED | D61: RAJ
A62: Name : Rrdhhddhbdbdejn
A63: Phone : 7338838687 | B63: CB 8 PM | D63: VIKASH
A64: Name : dgs
A65: Phone : 9822345345 | B65: LI | D65: VIKASH
A66: Name : chetan
A67: Phone : 9920031748 | B67: FOLLOW UP | D67: VYOM
A68: Name : krishnavel
A69: Phone : 9600239366 | B69: NI | D69: MAHENDRA
A70: Name : Jhatu Kuldeep Badwe
A71: Phone : 9116057800 | B71: NI | D71: VISHNU
A72: Name : Raj n
A73: Phone : 7875716151 | B73: INTERESTED | D73: MAHENDRA
A74: Name : BOYKA Jackson
A75: Phone : 9899111686 | B75: SF | D75: KAMINI
A76: Name : Laxman saud | B76: FT
A77: Phone : 8660295897 | B77: FT | C77: 10K | D77: VISHNU
A78: Name : Sandip mane | B78: FT
A79: Phone : 9890766348 | B79: FT | C79: 30K | D79: AMIT
A80: Name : wajid
A81: Phone : 8368225543 | B81: NPC | D81: AYUSH

Sheet 29-10-24
A1: CLIENTS DETAILS | B1: REMARK | C1: INVESTMENT | D1: EMP…
A2: Name : Faisal Khan
A3: Phone : 9004131045 | B3: NI | D3: KAMINI
A4: Name : Devesh shayam trader
A5: Phone : 8975157053 | B5: NI | C5: REPEAT NO.. | D5: AMIT
A6: Name : Rajendra Yawalkar
A7: Phone : 9422717118 | B7: NI | D7: AYUSH
A8: Name : Amol Jijore
A9: Phone : 7038399379 | B9: NI | D9: VISHNU
A10: Name : Amol Kumbhare
A11: Phone : 9763364601 | B11: NI | D11: RAJ
A12: Name : Aniket Katenge
A13: Phone : 8805913933 | B13: NI | D13: VIKASH
A14: Name : Arvind Tembhurne
A15: Phone : 9860066752 | B15: NC | D15: VYOM
A16: Name : Atul Admane
A17: Phone : 8010325208 | B17: CD | D17: VISHNU
A18: Name : Bhavna Neware
A19: Phone : 9145262213 | B19: NC | D19: AMIT
A20: Name : Bhupesh Donode
A21: Phone : 7666678124 | B21: NI | C21: REPEAT NO.. | D21: SHIVANI
A22: Name : Chhatrapati Kursunge
A23: Phone : 8766925750 | B23: CB 4 PM | D23: KAMINI
A24: Name : Divakar Urkude
A25: Phone : 9922699637 | B25: NI | D25: AMIT
A26: Name : Chunnilala Karpate
A27: Phone : 7057810643 | B27: NPC | D27: AKSHAY
A28: Name : Gahane
A29: Phone : 9420277095 | B29: NI | D29: RAJ
A30: Name : Lokesh Donede
A31: Phone : 9623662605 | B31: NI | D31: RITU
A32: Name : Lokesh Shahare
A33: Phone : 7507902795 | B33: NC | D33: KAMINI
A34: Name : Mauli Gayakwad
A35: Phone : 9767337366 | B35: SF | D35: RAJ
A36: Name : Parmanand gahane
A37: Phone : 9359720026 | B37: NI | D37: AYUSH
A38: Name : Supriya Bisen Con.
A39: Phone : 7972179831 | B39: SF | C39: REPEAT NO.. | D39: KAMINI
A40: Name : Sagar Pardhi
A41: Phone : 7083807368 | B41: NC | D41: KAMINI
A42: Name : Rahul Faye
A43: Phone : 9422981806 | B43: NC | D43: VYOM
A44: Name : Vikesh Naik
A45: Phone : 9545483465 | B45: NPC | D45: AKSHAY
A47: Name : Raghunathan R | B47: 30/10/2024
A48: Phone : 9940674865 | B48: PAYMENT DONE | D48: AMIT

Sheet 04-11-24
A1: CLIENTS DETAILS | B1: REMARK | C1: INVESTMENT | D1: EMP… | H1: TOTAL LEADS - 48
A2: Name : sdfsd | H2: Date -04.11.24
A3: Phone : 9755441254 | B3: NC | D3: VIKASH | H3: FT | I3: 8
A4: Name : Abrar Syed | H4: INTERESTED | I4: 3
A5: Phone : 9619266195 | B5: FT | C5: 1 LAC CAPITAL | D5: KAMINI | H5: FOLLOWUP | I5: 0
A6: Name : Shriram Balasaheb | H6: CB | I6: 6
A7: Phone : 7083619009 | B7: NC | D7: VISHNU | H7: BUSY | I7: 2
A8: Name : Prathamesh Nalawade | H8: CD | I8: 0
A9: Phone : 9422603334 | B9: FT | C9: 50K REPEAT NO. | D9: VISHNU | H9: NI | I9: 7
A10: Name : VIJAYAKUMAR M | H10: NPC | I10: 10
A11: Phone : 9944345472 | B11: TRADE WATCH | D11: VIKASH | H11: OTHERS | I11: 12
A12: Name : EDISON
A13: Phone : 8012262960 | B13: NI | D13: AYUSH
A14: Name : Sreeramamurthy | B14: FT
A15: Phone : 9989491349 | B15: FT | D15: SHALINA
A16: Name : Abdul Kadim
A17: Phone : 7873578673 | B17: NPC | D17: MAHENDRA
A18: Name : K.sathishkumar
A19: Phone : 9959644425 | B19: NPC | D19: RAJ
A20: Name : YUVARAJ P
A21: Phone : 9597350684 | B21: NI | D21: AMIT
A22: Name : Santosh g
A23: Phone : 9620333331 | B23: NI | D23: VYOM
A24: Name : Jithin g das
A25: Phone : 8129091937 | B25: NI | C25: REPEAT NO.. | D25: VYOM
A26: Name : Vishnuraj
A27: Phone : 9567638541 | B27: SF | D27: MAHENDRA
A28: Name : Govind soni
A29: Phone : 9861523083 | B29: FOLLOW UP | D29: VIKASH
A30: Name : Arth Aggarwal
A31: Phone : 9871976270 | B31: FOLLOW UP | D31: SANJAY
A32: Name : Bassam
A33: Phone : 9082413837 | B33: NI | D33: VYOM
A34: Name : Prakash P V
A35: Phone : 9976968466 | B35: FT | C35: 10K | D35: VYOM
A36: Name : Ramkumar s
A37: Phone : 9994062625 | B37: NI | D37: VISHNU
A38: Name : Naresh Chavan
A39: Phone : 9823053587 | B39: PAYMENT DONE | D39: VIKASH
A40: Name : Sikha Agrawal
A41: Phone : 9438069958 | B41: FT | D41: MAHENDRA | F41: 21/1/2025
A42: Name : Chethana B G
A43: Phone : 9663101013 | B43: CB TOMORROW | D43: VISHNU
A44: Name : Sunil Shankarrao Ramteke
A45: Phone : 8888741314 | B45: FOLLOW UP | D45: KIRTI
A46: Name : Pravin
A47: Phone : 9922338201 | B47: PAYMENT DONE | D47: AMIT
A48: Name : Naresh a Chavan
A49: Phone : 7020304257 | B49: WN | D49: RISHI
A50: Name : Vellingiri
A51: Phone : 6380994954 | B51: LI | D51: R C
A52: Name : Prajyesh
A53: Phone : 7288814648 | B53: NPC | D53: R C
A54: Name : Karthi
A55: Phone : 9003893784 | B55: NC | D55: VYOM
A56: Name : rakesh bhat
A57: Phone : 7057163224 | B57: CAPITAL ISSUE | D57: KAMINI
A58: Name : Puneet
A59: Phone : 9717172875 | B59: FT | D59: PRIYA | F59: 21/1/2025
A60: Name : Thota Ganesh Raja
A61: Phone : 9100554656 | B61: NPC | D61: R C
A62: Name : assa
A63: Phone : 9876543210 | B63: SF | C63: REPEAT NO
A64: Name : Rajit Rana
A65: Phone : 6280372212 | B65: FT | C65: 20K | D65: KAMINI
A66: Name : Dhruv
A67: Phone : 8169771677 | B67: NPC | D67: RISHI
A68: Name : Ahamed
A69: Phone : 9845256380 | B69: PAYMENT DONE | D69: RAJ
A70: Name : pradhum
A71: Phone : 7249495649 | B71: CB | D71: VYOM
A72: Name : Hari Kamal K
A73: Phone : 9008570646 | B73: NI | D73: MANSING
A74: Name : Durgaparameshwara
A75: Phone : 9663826972 | B75: NPC | D75: RISHI
A76: Name : Santha Kumar
A77: Phone : 9944162074 | B77: PAYMENT DONE | D77: KAMINI
A78: Name : Siddharth Gurav
A79: Phone : 9819223019 | B79: NPC | D79: RAJ
A80: Name : Basavaraj dk
A81: Phone : 8970268621 | B81: FT | C81: 50K | D81: KAMINI
A82: Name : S Prasada Rao
A83: Phone : 9704911455 | B83: NC | D83: VYOM
A84: Name : Yogeesha
A85: Phone : 9480821880 | B85: CB | D85: VYOM
A86: Name : Venkatesh V
A87: Phone : 9035963121 | B87: FOLLOW UP | D87: KIRTI
A88: Name : Sivakumar R
A89: Phone : 7411139593 | B89: NC | D89: RISHI
A90: Name : Mahendra vishwakarma
A91: Phone : 6266634933 | B91: CB | D91: RISHI
A92: Name : Ishpreet
A93: Phone : 9028018292 | B93: FT | C93: 3LAC | D93: KAMINI
A94: Name : Saurabh Gala
A95: Phone : 8087217753 | B95: NI | D95: VYOM
A96: Name : Shrishashank S K
A97: Phone : 9845112523 | B97: NI | D97: VYOM
A98: Name : Sikha Agrawal
A99: Phone : 9438069958 | B99: PAYMENT DONE | D99: VYOM
A101: Name Hari Mobile No. 00919207417040 | B101: PAYMENT DONE | C101: 4K | D101: HARIOM

Sheet 05-11-24
A1: CLIENTS DETAILS | B1: REMARK | C1: INVESTMENT | D1: EMP…
A2: Name : dinesh pawar | H2: TOTAL LEADS - 28 | N2: RITU | O2: MOBILE NO.. 30
A3: Phone : 9821306309 | B3: BUSY | D3: KAMINI | H3: Date -05.11.24
A4: Name : Moidu tmv | H4: FT | I4: 0
A5: Phone : 8606448226 | B5: CB | D5: NIKITA | H5: INTERESTED | I5: 3
A6: Name : SHAIK HAFIZULLA | H6: FOLLOWUP | I6: 0
A7: Phone : 9885122789 | B7: INTERESTED | D7: MAHENDRA | H7: CB | I7: 3
A8: Name : Afreen Salim Sayyed | H8: BUSY | I8: 1
A9: Phone : 9892579554 | B9: INTERESTED | D9: AAYUSH | H9: CD | I9: 2
A10: Name : Nag | H10: NI | I10: 2
A11: Phone : 7675052490 | B11: NC | D11: AMIT | H11: NPC | I11: 8
A12: Name : Yukta | H12: OTHERS | I12: 9
A13: Phone : 8551961280 | B13: NPC | D13: NIKITA
A14: Name : A
A15: Phone : 9898989899 | B15: INVALID | D15: AMIT
A16: Name : TANIYA SAXENA
A17: Phone : 9812368725 | B17: FT | D17: AMIT
A18: Name : Rkmishra
A19: Phone : 9828897666 | B19: NC | D19: VISHNU
A20: Name : Mohammad' Afridi
A21: Phone : 8867556992 | B21: INTERESTED | D21: MAHENDRA
A22: Name : guberan
A23: Phone : 9600881342 | B23: SF | D23: AMIT
A24: Name : Shaikh Ejaz Ahmed
A25: Phone : 9766415026 | B25: CD | D25: JITENDRA
A26: Name : Suganyaraju
A27: Phone : 9361162935 | B27: NPC | D27: AAYUSH
A28: Name : Sahil Gawade
A29: Phone : 7208127893 | B29: SF | D29: AMIT
A30: Name : Veerendra
A31: Phone : 9110420087 | B31: NPC | D31: AMIT
A32: Name : Saurabh Bothikar
A33: Phone : 8087868319 | B33: INTERESTED | D33: ABHAY
A34: Name : Prasadjnvd
A35: Phone : 7799993210 | B35: NPC | D35: NIKITA
A36: Name : G.Hemalatha
A37: Phone : 9025526351 | B37: NPC | D37: VYOM
A38: Name : Meena
A39: Phone : 9788687810 | B39: SF | D39: KAMINI
A40: Name : Rajesh shukla
A41: Phone : 9892737229 | B41: NPC | D41: VYOM
A42: Name : Khushi
A43: Phone : 7020031843 | B43: NPC | D43: AMIT
A44: Name : M nageswararao
A45: Phone : 9182023216 | B45: LI | D45: JITENDRA
A46: Name : Abhi kumar
A47: Phone : 9624156292 | B47: NPC | D47: VISHNU
A48: Name : Jasbir Singh
A49: Phone : 9320216111 | B49: NC | D49: AAYUSH
A50: Name : Karthikeyan
A51: Phone : 8778439758 | B51: WHATSAPP | D51: KAMINI
A52: Name : Dhanaraj
A53: Phone : 8088118343 | B53: NI | D53: AMIT
A54: Name : Shounak Roy
A55: Phone : 9620684138 | B55: INVALID
A56: Name : Muruganantham
A57: Phone : 7845629702 | B57: WHATSAPP | D57: KAMINI
A58: Name : Veeramani
A59: Phone : 7094566388 | B59: DC | D59: NIKITA
A60: Kamal | C60: 76700 | D60: ABHAY
A61: Phone :+918420320025 | B61: PAYMENT DONE

Sheet 06-11-24
A1: CLIENTS DETAILS | B1: REMARK | C1: INVESTMENT | D1: EMP…
A2: Name : hghg | D2: MAHENDRA | G2: TOTAL LEADS - 34
A3: Phone : 9654851212 | B3: NPC | D3: MAHENDRA | G3: Date -06.11.24
A4: Name : jflk | D4: KAMINI | G4: FT | H4: 7
A5: Phone : 9852512512 | B5: CD | D5: KAMINI | G5: INTERESTED | H5: 3
A6: Name : Shiva kumar | D6: VYOM | G6: FOLLOWUP | H6: 1 | I6: 1
A7: Phone : 8105726643 | B7: FOLLOW UP | D7: VYOM | G7: CB | H7: 1
A8: Name : B. Sai ratnakar | D8: KAMINI | G8: BUSY | H8: 1
A9: Phone : 9703123969 | B9: CAPITAL ISSUE | D9: KAMINI | G9: CD | H9: 2
A10: Name : Bilal | D10: AMIT | G10: NI | H10: 0
A11: Phone : 9607775628 | B11: FT | C11: 30K | D11: AMIT | G11: NPC | H11: 13
A12: Name : Alex | D12: VISHNU | G12: OTHERS | H12: 6
A13: Phone : 8344203065 | B13: NPC | D13: VISHNU
A14: Name : PHULARAM
A15: Phone : 9116373771 | B15: PAYMENT DONE | D15: VISHNU
A16: Name : Dupuguntla Y Krishna | D16: VYOM
A17: Phone : 9966596143 | B17: NPC | D17: VYOM
A18: Name : Ganga | D18: RAJ
A19: Phone : 8618683773 | B19: FOLLOW UP | D19: SANGEETA VAMANKAR | E19: 17/12/2024
A20: Name : Rajendra nandurkar | D20: KAMINI
A21: Phone : 9823116405 | B21: INTERESTED | D21: KAMINI
A22: Name : S M Shariff | D22: AMIT
A23: Phone : 8341186786 | B23: FT | C23: 50K | D23: AMIT
A24: Name : Vgvbh | D24: MAHENDRA
A25: Phone : 9447889644 | B25: NPC | D25: MAHENDRA
A26: Name : D. K Sethi | D26: VIKASH
A27: Phone : 9438437300 | B27: PAYMENT DONE | D27: VIKASH
A28: Name : Vinod shinde | D28: JITENDRA
A29: Phone : 9923373473 | B29: PAYMENT DONE | D29: JITENDRA
A30: Name : Jay 1206 | D30: MAHENDRA
A31: Phone : 9182370207 | B31: NPC | D31: MAHENDRA
A32: Name : Zaman | D32: VISHNU
A33: Phone : 9740467669 | B33: PAYMENT DONE | D33: VISHNU
A34: Name : K BHAALASUBRAMANIYAM | D34: VYOM
A35: Phone : 9445005122 | B35: NPC | C35: REPEAT NO | D35: VYOM
A36: Name : shijoy | D36: ABHAY
A37: Phone : 9847888042 | B37: LI | D37: ABHAY
A38: Name : Shiva kumar s | D38: MAHENDRA
A39: Phone : 9886157554 | B39: INTERESTED | D39: MAHENDRA
A40: Name : Sahil | D40: RAJ
A41: Phone : 7079363636 | B41: NPC | D41: RAJ
A42: Name : kailash Joshi | D42: KAMINI
A43: Phone : 9650295198 | B43: FT | C43: 5K | D43: KAMINI
A44: Name : MANIKANDAN M V | D44: ABHAY
A45: Phone : 9995962217 | B45: LI | D45: ABHAY
A46: Name : Prasad | D46: RAJ
A47: Phone : 7745037667 | B47: TRADE WATCH | D47: RAJ
A48: Name : Govind soni | D48: VIKASH
A49: Phone : 9861523083 | B49: FT | D49: VIKASH
A50: Name : Babu Salamni | D50: VYOM
A51: Phone : 9650227946 | B51: FT | D51: VYOM
A52: Name : Shankar s | D52: AMIT
A53: Phone : 8884195586 | B53: CD | D53: AMIT
A54: Name : Ravi Shankar | D54: VIJAY
A55: Phone : 8374091475 | B55: NPC | D55: VIJAY
A56: Name : Siddharth Sapru | D56: AMBRISH
A57: Phone : 8750591434 | B57: INTERESTED | D57: AMBRISH
A58: Name : Mahesh jain | D58: NIKITA
A59: Phone : 9867291111 | B59: CD | C59: REPEAT NO.. | D59: NIKITA
A60: Name : Sks
A61: Phone : 9437212452 | B61: FT | D61: RISHI
A62: Name : gjffg
A63: Phone : 9456856595 | B63: SF | D63: MAHENDRA
A64: Name : jhjh
A65: Phone : 8595457545 | B65: FOLLOW UP | D65: VISHNU
A66: Name : Harsh shinde
A67: Phone : 9067487605 | B67: NR | D67: VYOM
A68: Name : Alan J. L Jose
A69: Phone : 8056689730 | B69: FOLLOW UP | D69: VYOM
A70: Name : Francis
A71: Phone : 7972736538 | B71: NI | D71: VYOM
A72: Name : Vinayak bagalkot
A73: Phone : 6361469716 | B73: FT | D73: SHALINA
A74: Name : Shaheb
A75: Phone : 7408140611 | B75: NC | D75: KAMINI

Sheet fb
A1: Phone : 8105726643 | B1: FOLLOW UP | D1: VYOM | E1: BAAT CHAL RAHI H
A2: Phone : 9607775628 | B2: FT | C2: 30K | D2: AMIT | E2: Payment ki bat chl rhi h ise bhi
A3: Phone : 9823116405 | B3: INTERESTED | D3: KAMINI | E3: WORK NAHI KARWAYA
A4: Phone : 8341186786 | B4: FT | C4: 50K | D4: AMIT | E4: Monday se start karega
A5: Phone : 9438437300 | B5: FT | C5: 20K | D5: VIKASH | F5: ft yesterday ka clint h profit de diya h and 6 bje baat krenga PAYMENT MODE
A6: Phone : 9923373473 | B6: FOLLOW UP | D6: JITENDRA
A7: Phone : 9740467669 | B7: FT | C7: 40K | D7: VISHNU | E7: BLOCK KAR DIYA
A8: Phone : 9886157554 | B8: INTERESTED | D8: MAHENDRA | E8: Demat open ne hai abhi
A9: Phone : 9650295198 | B9: FT | C9: 5K | D9: KAMINI | E9: WORK NAHI KARWAYA
A10: Phone : 9861523083 | B10: FT | D10: VIKASH | F10: follow up me clint ye
A11: Phone : 9650227946 | B11: FT | D11: VYOM
A12: Phone : 8750591434 | B12: INTERESTED | D12: AMBRISH | E12: SENSEX MEIN LOSS Esko kal trade provide kar ke payment dega
A13: Phone : 8056689730 | B13: FOLLOW UP | D13: VYOM | E13: BAAT CHAL RAHI H
A14: Phone : 6361469716 | B14: FT | D14: SHALINA | E14: SOCH KAR BTAYEGA PARSO TAK
A15: Phone : 9717172875 | B15: INTERESTED | D15: MAHENDRA | E15: LOSS HO GAYA
A20: 45484
A22: Name : Nilam Kumar Patel | B22: FT
A23: Phone : 7978598372 | B23: FT | D23: AMIT | E23: LOSS HO GAYA
A24: Name : Radhey | B24: FT
A25: Phone : 7769099690 | B25: FT | C25: 50K | D25: VIKASH | E25: NOT RESPONSE
A26: Name : JITENDER THAKUR | B26: FT
A27: Phone : 9891526822 | B27: FT | D27: AMIT | E27: LOSS HO GAYA
A28: Name : joy biswas | B28: FT
A29: Phone : 9818166085 | B29: FT | D29: AMIT | E29: LOSS
A30: Name : Thulaseedharan | B30: FT
A31: Phone : 8547157583 | B31: FT | C31: 1 LAC | D31: AMIT | E31: LOSS
A32: Name : vanishree | B32: FT
A33: Phone : 9841009838 | B33: FT | C33: 15 LAC | D33: KAMINI | E33: START MONDAY
A34: Name : Shubham | B34: FT
A35: Phone : 9096438578 | B35: FT | D35: SHALINA | E35: AAJ BAAT NAHI HUI H
A36: Name : Hussain | B36: FT
A37: Phone : 8667466923 | B37: FT | D37: VIKASH TODAY
A39: Lalji Bhai Joshi- 7600854856
A41: Update- Aaj Demo ke liye Available nhi the.
A43: Current Status- Monday ko Demo Trade Watch krege...!!! (Mere Followup me hai)
A45: Samarth- 9108529922
A47: Update- SL hit On Demo Trade
A49: Current Status- Monday ko Again Positive krege... (Mere Followup me hai)
A51: Abhay- 8793593581
A53: Update- Demo Trade Failed...
A55: Current Status- Monday ko Registration charge Lena hai... Ek Demo ke baad

Sheet 07-11-24
A1: CLIENTS DETAILS | B1: REMARK | C1: INVESTMENT | D1: EMP…
A2: Name : Shiva kumar | B2: FT | G2: TOTAL LEADS - 49
A3: Phone : 8105726643 | B3: FT | D3: AMIT | G3: Date -07.11.24
A4: Name : B. Sai ratnakar | G4: FT | H4: 6 | I4: 2
A5: Name : Bilal | B5: INVALID | G5: INTERESTED | H5: 1 | I5: 0
A6: Name : Alex | G6: FOLLOWUP | H6: 1 | I6: 1
A7: Name : PHULARAM | B7: NI | D7: RAJ | G7: CB | H7: 4
A8: Phone : 9116373771 | G8: BUSY | H8: 4
A9: Name : Dupuguntla Y Krishna | B9: INVALID | D9: VIKASH | G9: CD | H9: 3
A10: Name : Ganga | G10: NI | H10: 8
A11: Phone : 8618683773 | B11: NI | D11: ABHAY | G11: NPC | H11: 8
A12: Name : Rajendra nandurkar | G12: OTHERS | H12: 14
A13: Phone : 9823116405 | B13: NI | D13: VIKASH
A14: Name : S M Shariff
A15: Name : Vgvbh | B15: NI | D15: VISHNU
A16: Name : D. K Sethi
A17: Phone : 9438437300 | B17: NI | D17: SHALINA
A18: Name : Vinod shinde
A19: Phone : 9923373473 | B19: CD | D19: AMIT
A20: Name : Jay 1206
A21: Name : Zaman | B21: NC | D21: NIKITA
A22: Phone : 9740467669
A23: Name : K BHAALASUBRAMANIYAM | B23: BUSY | D23: JITENDRA
A24: Name : shijoy
A25: Name : Shiva kumar s | B25: LI | D25: RAJ
A26: Phone : 9886157554
A27: Name : Sahil | B27: NI | D27: VIKASH
A28: Name : kailash Joshi
A29: Name : MANIKANDAN M V | B29: NI | D29: AMIT
A30: Name : Prasad
A31: Name : Govind soni | B31: INTERESTED | D31: VIJAY
A32: Name : Babu Salamni
A33: Name : Shankar s | B33: NPC | D33: VIJAY
A34: Name : Ravi Shankar
A35: Name : Siddharth Sapru | B35: NI | D35: AMIT
A36: Phone : 8750591434
A37: Name : Mahesh jain | B37: NI | D37: VISHNU
A38: Name : Sks
A39: Name : gjffg | B39: SF | D39: VIJAY
A40: Name : jhjh
A41: Phone : 8595457545 | B41: NI | D41: ABHAY
A42: Name : Harsh shinde
A43: Name : Alan J. L Jose | B43: BUSY | D43: VISHNU
A44: Phone : 8056689730
A45: Name : Francis | B45: NC | D45: AMBRISH
A46: Name : Vinayak bagalkot
A47: Name : Shaheb | B47: NI | D47: VISHNU
A48: Name : Radhey | B48: FT
A49: Phone : 7769099690 | B49: FT | C49: 50K | D49: VIKASH
A50: Name : shrawan
A51: Phone : 9958109135 | B51: NPC | D51: ABHAY
A52: Name : Bhaskar Reddy
A53: Phone : 7204886897 | B53: CAPITAL ISSUE | D53: AMIT
A54: Name : Pankaj kumar singh
A55: Phone : 6201862026 | B55: NPC | D55: AMIT
A56: Name : Jiya
A57: Phone : 7977048520 | B57: NI | D57: VISHNU
A58: Name : JITENDER THAKUR | B58: FT
A59: Phone : 9891526822 | B59: FT | D59: AMIT
A60: Name : RENGANATHAN
A61: Phone : 7010089061 | B61: LI | D61: KAMINI
A62: Name : Vasu thota
A63: Phone : 6301088872 | B63: NI | D63: KAMINI
A64: Name : prabir khuntia
A65: Phone : 7978330412 | B65: NPC | D65: VIKASH
A66: Name : Rohitkumar s. tripathi
A67: Phone : 9136051016 | B67: SF | D67: KAMINI
A68: Name : Shruti Patel
A69: Phone : 9442615671 | B69: CB | D69: VISHNU
A70: Name : Abhay
A71: Phone : 8793593581 | B71: FT | D71: SANGEETA | E71: 45901
A72: Name : Ajinkya
A73: Phone : 8888607045 | B73: NI | D73: KAMINI
A74: Name : joy biswas | B74: FT
A75: Phone : 9818166085 | B75: FT | D75: AMIT
A76: Name : Kaka Watchman
A77: Phone : 8655458936 | B77: CD | D77: KAMINI
A78: Name : Akshay jain
A79: Phone : 7026251712 | B79: CB | D79: VIKASH
A80: Name : Manoj Mahamulkar
A81: Phone : 8655500380 | B81: FOLLOW UP | D81: VYOM
A82: Name : Thulaseedharan | B82: FT
A83: Phone : 8547157583 | B83: FT | C83: 1 LAC | D83: AMIT
A84: Name : Jiya Kacholiya
A85: Phone : 8505098639 | B85: FOLLOW UP | D85: VISHNU
A86: Name : R kumar
A87: Phone : 7008980354 | B87: NPC | D87: VYOM
A88: Name : Fhhf
A89: Phone : 9876567656 | B89: BUSY | C89: REPEAT NO.. | D89: KAMINI
A90: Name : vanishree
A91: Phone : 9841009838 | B91: PAYMENT DONE | D91: KAMINI
A92: Name : Shubham | B92: FT
A93: Phone : 9096438578 | B93: FT | D93: SHALINA
A94: Name : Sarthak Mahadev palkar
A95: Phone : 8928863713 | B95: BUSY | D95: KAMINI
A96: Name : Hussain | B96: FT
A97: Phone : 8667466923 | B97: FT | D97: VIKASH
A98: Name : Subhadeep Bhattacharyya
A99: Phone : 9930421623 | B99: WTSP | D99: KAMINI
A100: Name : Sandhya mandiwala
...

Sheet 08-11-24
A1: CLIENTS DETAILS | B1: REMARK | C1: INVESTMENT | D1: EMP…
A2: Name : KAJA MOHIDEEN | G2: TOTAL LEADS - 22
A3: Phone : 9894013445 | B3: FT | D3: RAJ | G3: Date -08.11.24
A4: Name : Aniket gawai | G4: FT | H4: 6 | I4: 1
A5: Phone : 9209217981 | B5: INTERESTED | D5: SHALINA | G5: INTERESTED | H5: 1
A6: Name : Risab | G6: FOLLOWUP | H6: 2
A7: Phone : 7676223489 | B7: NI | D7: VYOM | G7: CB | H7: 0
A8: Name : Ayush Singh Parihar | G8: BUSY | H8: 1
A9: Phone : 6268304586 | B9: FT | C9: 50K | D9: AMIT | G9: CD | H9: 0
A10: Name : Sharmi | G10: NI | H10: 4
A11: Phone : 8688941540 | B11: SF | D11: VYOM | G11: NPC | H11: 3
A12: Name : Mehul Bhuva | G12: OTHERS | H12: 5
A13: Phone : 8411006073 | B13: NC | D13: VYOM
A14: Name : Divyatiwari
A15: Phone : 7065572339 | B15: PAYMENT DONE | D15: SHALINA
A16: Name : Abhiraj Vp
A17: Phone : 9847194456 | B17: NPC | D17: VYOM
A18: Name : Ratnaa Umesh Togari
A19: Phone : 9011359119 | B19: NC | D19: AMBRISH
A20: Name : ganesh tate
A21: Phone : 9784499699 | B21: FT | C21: 4 LAC , 5 LAC LOSS | D21: KAMINI
A22: Name : Anuj
A23: Phone : 9891443654 | B23: FT | C23: 50K | D23: AMIT
A24: Name : Pradeep j
A25: Phone : 9003231642 | B25: FT | D25: NARMADA | F25: 45901
A26: Name : Arun Prabhu
A27: Phone : 9345578566 | B27: NC | D27: AMIT
A28: Name : Shawn A Backer
A29: Phone : 7012564575 | B29: FT | D29: VIJAY
A30: Name : Arun murti
A31: Phone : 9082265160 | B31: DC | D31: VYOM
A32: Name : Jay Kotian
A33: Phone : 9538812902 | B33: FT | D33: VIKAS | F33: 21/1/2025
A34: Name : Naveen
A35: Phone : 7330728399 | B35: NI | D35: KAMINI
A36: Name : Rasik
A37: Phone : 9995483399 | B37: FOLLOW UP | D37: VYOM
A38: Name : Nikita
A39: Phone : 9650958404 | B39: NI | D39: VYOM
A40: Name : Sudhakar ramachandran
A41: Phone : 9362441679 | B41: FT | D41: KAMINI
A42: Name : Ibrahim
A43: Phone : 7671925728 | B43: NI | D43: VYOM
A44: Name : Rohit Sarjerao Pande
A45: Phone : 8605516368 | B45: NI | D45: VYOM
A46: Name : Nazir
A47: Phone : 9372137739 | B47: NI | D47: VYOM
A48: Name : Miraj khadim
A49: Phone : 7584881270 | B49: NPC | D49: AMIT
A53: VINOD SHINDE +91 99233 73473 | B53: PAYMENT DONE | C53: HARIOM

Sheet 13-11-24  OLD DATA
A2: EMPLOYEE | B2: FT | C2: INVESTMENT
A3: VIKASH | B3: 2
F57: PURANA DATA SE

Sheet 09-11-24
A1: CLIENTS DETAILS | B1: REMARK | C1: INVESTMENT | D1: EMP…
A2: Name : Swapnil | G2: TOTAL LEADS - 18
A3: Phone : 9552892849 | B3: CB ,NPC | D3: VYOM | G3: Date -09.11.24
A4: Name : Miraj khadim | G4: FT | I4: 2
A5: Phone : 7584881270 | B5: CB, AFTR 1 WEEK | D5: SHALINA | G5: INTERESTED | I5: 1
A6: Name : Sandip jamdade | G6: FOLLOWUP | I6: 2
A7: Phone : 9511233464 | B7: CD | D7: VISHNU | G7: CB | I7: 4
A8: Name : JOY K G | G8: BUSY | I8: 1
A9: Phone : 8281332567 | B9: NI | D9: KAMINI | G9: CD | I9: 1
A10: Name : Sheetalkumar | G10: NI | I10: 1
A11: Phone : 8861257536 | B11: FOLLOW UP | D11: VYOM | G11: NPC | I11: 4
A12: Name : Mandar kulkarni | G12: OTHERS | I12: 4
A13: Phone : 7710874649 | B13: INTERESTED | D13: ABHAY
A14: Name : Rahul S
A15: Phone : 8667536684 | B15: FT | C15: 1 LAC + | D15: KAMINI
A16: Name : ADITYA KALE
A17: Phone : 7775919456 | B17: NI | D17: AMIT
A18: Name : Najiullah khan
A19: Phone : 9167728553 | B19: NI | D19: MAHENDRA
A20: Name : Jjjkkk
A21: Phone : 9778767788 | B21: INVALID | D21: VISHNU
A22: Name : Arvind278463
A23: Phone : 8660284892 | B23: BUSY | D23: KAMINI
A24: Name : Janardhan dhau mokal
A25: Phone : 9890124200 | B25: NI | D25: MAHENDRA
A26: Name : Sagadvean
A27: Phone : 9597275226 | B27: WTSP | D27: KAMINI
A28: Name : Rudra m
A29: Phone : 7019945155 | B29: NPC | D29: VYOM
A30: Name : Nandan
A31: Phone : 9845270402 | B31: FOLLOW UP | D31: VYOM
A32: Name : Ran
A33: Phone : 8608844165 | B33: NPC | D33: VYOM
A34: Name : SATHEESH Kumar S J
A35: Phone : 9020217007 | B35: INVALID | D35: KAMINI
A36: Name : Shivam Gupta
A37: Phone : 7065367767 | B37: FT | C37: 50K | D37: RC
A38: Name : Swapnil
A39: Phone : 9552892849 | B39: NI | D39: VYOM

Sheet Sheet8
A1: TOTAL LEADS - 18
A2: Date -09.11.24
A3: FT | C3: 2
A4: INTERESTED | C4: 0
A5: FOLLOWUP | C5: 2
A6: CB | C6: 3
A7: BUSY | C7: 1
A8: CD | C8: 1
A9: NI | C9: 1
A10: SF
A11: INVALID
A12: NPC | C12: 4
A13: OTHERS | C13: 5

Sheet 11-11-24
A1: CLIENTS DETAILS | B1: REMARK | C1: INVESTMENT | D1: EMP…
A2: Name : Nijam Hasmi | F2: TOTAL LEADS - 74
A3: Phone : 6297784509 | B3: NPC | D3: AMIT | F3: Date -11.11.24
A4: Name : Jitendra Sain | F4: FT | G4: 3
A5: Phone : 8306243198 | B5: NPC | D5: VYOM | F5: INTERESTED | G5: 5
A6: Name : Pankaj | F6: FOLLOWUP | G6: 3
A7: Phone : 9820945360 | B7: BUSY | D7: SHALINA | F7: CB | G7: 4
A8: Name : Mohd Junaid | F8: BUSY | G8: 6
A9: Phone : 8627030392 | B9: NC | D9: VIKASH | F9: CD | G9: 11
A10: Name : Shankari | F10: NI | G10: 9
A11: Phone : 8867658316 | B11: NPC | D11: ABHAY | F11: SF | G11: 3
A12: Name : Shankari ly | F12: INVALID | G12: 0
A13: Phone : 8867658317 | B13: CD | D13: VIJAY | F13: NPC | G13: 25
A14: Name : Pavandip | F14: OTHERS | G14: 9
A15: Phone : 9021691971 | B15: NI | D15: MAHENDRA
A16: Name : Onkar Gaysamudre
A17: Phone : 8668970987 | B17: SF | D17: RAJ
A18: Name : Mahesh Katkar
A19: Phone : 8329377944 | B19: NPC | D19: AMIT
A20: Name : Santa
A21: Phone : 9740584789 | B21: NPC | D21: VIJAY
A22: Name : SPOORTHI.M.M
A23: Phone : 8123673675 | B23: NC | D23: VIKASH
A24: Name : Sourabh
A25: Phone : 9845345051 | B25: CD | D25: JITENDRA
A26: Name : Manj
A27: Phone : 8884233058 | B27: NI | D27: MAHENDRA
A28: Name : Debasish Dash
A29: Phone : 8018286645 | B29: BUSY | D29: RAJ
A30: Name : Sunil Salunke
A31: Phone : 9923889957 | B31: NPC | D31: AMIT
A32: Name : Chandra Prabha
A33: Phone : 9243526036 | B33: NI | D33: AMIT
A34: Name : Rakesh Kaushik
A35: Phone : 8287073064 | B35: NI | D35: MAHENDRA
A36: Name : Rishaf
A37: Phone : 8072047425 | B37: NI | D37: RAJ
A38: Name : Deepa
A39: Phone : 9940659275 | B39: LI | D39: RAJ
A40: Name : mohammed khaiser
A41: Phone : 7795355609 | B41: CB | C41: DEMATE ISSUE | D41: VIJAY
A42: Name : Mahendra Kumar Juneja
A43: Phone : 9259941771 | B43: NI | D43: SHALINA
A44: Name : King ..k
A45: Phone : 6397239312 | B45: NPC | D45: JITENDRA
A46: Name : Sharath
A47: Phone : 9141003366 | B47: NPC | D47: JITENDRA
A48: Name : UDAY RAMNATH WAGH
A49: Phone : 8806661008 | B49: BUSY | D49: MAHENDRA
A50: Name : Mohit jain
A51: Phone : 7826090375 | B51: NPC | D51: RISHI
A52: Name : Chakali washer
A53: Phone : 8008707104 | B53: NI | D53: VIJAY
A54: Name : Vikash
A55: Phone : 9971748478 | B55: CB | D55: VYOM
A56: Name : Mahesh Chatkar
A57: Phone : 8329377944 | B57: NPC | D57: AMIT
A58: Name : Jain
A59: Phone : 7506391355 | B59: CD | D59: VIKASH
A60: Name : Tammisetti Sagar babu
A61: Phone : 6305718088 | B61: NPC | D61: JITENDRA
A62: Name : Padam
A63: Phone : 8949627317 | B63: NI | D63: SHALINA
A64: Name : Madhav
A65: Phone : 9769576925 | B65: CB | D65: VYOM
A66: Name : Dipesh Shrimali
A67: Phone : 7976011048 | B67: CD | D67: AMIT
A68: Name : Mahmood
A69: Phone : 8971174746 | B69: INTERESTED | C69: STRT MONDAY | D69: AMIT
A70: Name : Debra Dennis Furtado
A71: Phone : 8452885667 | B71: NI | D71: RISHI
A72: Name : Abhinav gupta
A73: Phone : 7892178880 | B73: NPC | D73: AMIT
A74: Name : VenkataSiva
A75: Phone : 7416386661 | B75: INTERESTED | D75: VIJAY
A76: Name : Rigve
A77: Phone : 8226877305 | B77: SF | D77: JITENDRA
A78: Name : Pranay salunke
A79: Phone : 7208877246 | B79: NR | D79: SHALINA
A80: Name : K Lakshmi Suresh
A81: Phone : 9347733696 | B81: NPC | D81: RAJ
A82: Name : Janani
A83: Phone : 7806914765 | B83: LI | D83: ABHAY
A84: Name : Amol Waghmode
A85: Phone : 8805566307 | B85: CD | D85: VIKASH
A86: Name : Virender Singh Negi
A87: Phone : 9915350144 | B87: FT | C87: repeat no.. | D87: VYOM
A88: Name : ELIAZER I
A89: Phone : 9677137733 | B89: NPC | D89: VIKASH
A90: Name : Nehal 11/11/2024
A91: Phone : 9555574815 | B91: NI | D91: MAHENDRA
A92: Name : Muruganandan t
A93: Phone : 9443428555 | B93: CD | D93: AMIT
A94: Name : Tusharkanti dash
A95: Phone : 8249198558 | B95: BUSY | D95: RAJ
A96: Name : Krishna chandran
A97: Phone : 9496816018 | B97: NI | D97: VYOM
A98: Name : Raju dake
A99: Phone : 9860431020 | B99: INTERESTED | D99: JITENDRA
A100: Name : Sumit Bhosale
...

Sheet 12-11-24 
A1: CLIENTS DETAILS | B1: REMARK | C1: INVESTMENT | D1: EMP…
A2: Name : Deepak Upadhyay | F2: TOTAL LEADS - 21
A3: Phone : 9619669042 | B3: NPC | D3: VIKAS | F3: Date -12.11.24
A4: Name : Gajendra Sangame | F4: FT | G4: 4
A5: Phone : 9686703856 | B5: FT | C5: 20K | D5: AMIT | F5: INTERESTED
A6: Name : sakthi p | F6: FOLLOWUP | G6: 2
A7: Phone : 9952423240 | B7: FOLLOWUP | D7: VIKASH | F7: CB | G7: 1
A8: Name : Anwer SADATH | F8: BUSY | G8: 1
A9: Phone : 8310537490 | B9: CALL BACK | D9: KAMINI | F9: CD
A10: Name : Taufiq Alam Khan | F10: NI | G10: 3
A11: Phone : 9606741533 | B11: NPC | D11: VYOM | F11: SF
A12: Name : Bhavesh | F12: INVALID | G12: 1
A13: Phone : 9509414198 | B13: FT | C13: 10K | D13: VISHNU | F13: NPC | G13: 9
A14: Name : hsiwb | F14: OTHERS
A15: Phone : 7393638208 | B15: NPC | D15: VYOM
A16: Name : Ashish
A17: Phone : 8793255648 | B17: NPC | D17: ABHAY
A18: Name : Sibram
A19: Phone : 9366394848 | B19: NPC | D19: KAMINI
A20: Name : Sadhana
A21: Phone : 9005488096 | B21: FOLLOWUP | D21: RISHI
A22: Name : Sagar patil
A23: Phone : 9881334647 | B23: NPC | D23: VYOM
A24: Name : Ashish Nilesh Darji
A25: Phone : 8793255648 | B25: FT | C25: 30K | D25: AMIT
A26: Name : Darji Phone : 9226392639 | B26: NI | D26: KAMINI
A27: Name : Ram raj
A28: Phone : 7518549344 | B28: NPC | D28: VYOM
A29: Name : Akhil
A30: Phone : 7907929572 | B30: BUSY | D30: KAMINI
A31: Name : Roopesh Nallapeta
A32: Phone : 9886003380 | B32: NPC | D32: SHALINA
A33: Name : Bhjvn
A34: Phone : 9865655699 | B34: INVALID | D34: AMIT
A35: Name : Passpathi
A36: Phone : 9445683241 | B36: FT | C36: 50K STOCK | D36: RISHI
A37: Name : Azeem
A38: Phone : 8600001245 | B38: FOLLOWUP | D38: VYOM
A39: Name : Ghhjhh
A40: Phone : 8050409876 | B40: NI | D40: AMIT
A41: Name : Akiraa
A42: Phone : 7093827464 | B42: NI | D42: KAMINI

Sheet 13-11-24 
A1: CLIENTS DETAILS | B1: REMARK | C1: INVESTMENT | D1: EMP…
A2: Name : BOBBY | F2: TOTAL LEADS - 36
A3: Phone : 9392772906 | B3: FOLLOWUP | D3: VYOM | F3: Date -13.11.24
A4: Name : Sonu Prajapati | F4: FT | G4: 9
A5: Phone : 8630351183 | B5: CAPITAL ISSUE | D5: KAMINI | F5: INTERESTED | G5: 1
A6: Name : Ahmed Nameer | F6: FOLLOWUP | G6: 7
A7: Phone : 7907596405 | B7: NI | D7: AMIT | F7: CB | G7: 1
A8: Name : Savitha Sethuram | F8: BUSY | G8: 1
A9: Phone : 7899927478 | B9: FT | C9: 1.50L Holding | D9: RISHI | F9: CD | G9: 1
A10: Name : Vansh | F10: NI | G10: 3
A11: Phone : 8178288643 | B11: NI | D11: SHALINA | F11: SF
A12: Name : Vaibhav Bhagwat | F12: INVALID | G12: 2
A13: Phone : 8329765295 | B13: IN | D13: HARIOM | F13: NPC | G13: 8
A14: Name : SHRADDHA N | F14: OTHERS
A15: Phone : 8281421385 | B15: NPC | D15: VYOM
A16: Name : Vaibhav
A17: Phone : 8380980262 | B17: FT | C17: 2.85 LAKH | D17: KAMINI
A18: Name : ajay dalavi
A19: Phone : 8999894889 | B19: NI | D19: VYOM
A20: Name : Lkg
A21: Phone : 9036083720 | B21: INVALID | D21: ABHAY
A22: Name : Purushothaman B
A23: Phone : 9962769013 | B23: NPC | D23: VYOM
A24: Name : MDIMRAN
A25: Phone : 7744970032 | B25: FOLLOWUP | D25: KAMINI
A26: Name : Harshal
A27: Phone : 9561552265 | B27: FT | C27: 50K | D27: AMIT
A28: Name : Kashish
A29: Phone : 9599307074 | B29: FT | D29: SHALINA
A30: Name : Netranand Gupta
A31: Phone : 7558310153 | B31: CB | D31: HARIOM
A32: Name : Veena
A33: Phone : 8547491560 | B33: FOLLOWUP | D33: RISHI
A34: Name : Hanuman
A35: Phone : 7498323974 | B35: FOLLOWUP | D35: VYOM
A36: Name : G Rahamthulla
A37: Phone : 9133823003 | B37: FOLLOWUP | D37: VYOM
A38: Name : Dharmendra
A39: Phone : 9867811306 | B39: BUSY | D39: KAMINI
A40: Name : vinayak s
A41: Phone : 8123551197 | B41: NI | D41: ABHAY
A42: Name : Akasha R
A43: Phone : 7483415833 | B43: NI | D43: AMIT
A44: Name : T G Paul
A45: Phone : 7982205615 | B45: FT | C45: 2 LAKH | D45: RISHI
A46: Name : Dhanush
A47: Phone : 7019794103 | B47: NPC | D47: SHALINA
A48: Name : Sumit Khandare
A49: Phone : 8830057206 | B49: NPC | D49: KAMINI
A50: Name : Rachita Pathare
A51: Phone : 7776845855 | B51: FOLLOWUP | D51: VYOM
A52: Name : Babaji
A53: Phone : 9751432890 | B53: NPC | D53: ABHAY
A54: Name : A kumaraswamy
A55: Phone : 9591412524 | B55: FT | C55: 2 LAKH | D55: KAMINI
A56: Name : Sheetalkumar
A57: Phone : 8861257536 | B57: FT | C57: 1 LAKH | D57: RISHI | F57: PURANA DATA SE
A58: Name : Munjaji jamdhade
A59: Phone : 7498323974 | B59: FT | C59: 5K | D59: AMIT
A60: Name : S venkata Naidu
A61: Phone : 8790431728 | B61: NPC | D61: VYOM
A62: Name : ANIL MEHTA
A63: Phone : 9724347064 | B63: FT | D63: SHALINA
A64: Name : Md farid
A65: Phone : 9987209581 | B65: NI | D65: KAMINI
A66: Name : Amit kumar
A67: Phone : 9879467202 | B67: INVLID | D67: RISHI
A68: Name : Saji
A69: Phone : 9744403666 | B69: FOLLOWUP | D69: VYOM
A70: Name : Abhinav kk
A71: Phone : 9624156292 | B71: NI | D71: AMIT
A72: Name : Tharchius
A73: Phone : 9159309017 | B73: CB | D73: VYOM

Sheet 14-11-24 
A1: CLIENTS DETAILS | B1: REMARK | C1: INVESTMENT | D1: EMP…
A2: Name : Sanju | F2: TOTAL LEADS - 63
A3: Phone : 7418759874 | B3: CD | D3: KAMINI | F3: Date -14.11.24
A4: Name : Badal das | F4: FT | G4: 4
A5: Phone : 7854080374 | B5: NI | D5: VYOM | F5: INTERESTED | G5: 3
A6: Name : Nilan garnaik | F6: FOLLOWUP | G6: 4
A7: Phone : 8018338770 | B7: BUSY | D7: AMIT | F7: CB | G7: 6
A8: Name : R yadav | F8: BUSY | G8: 4
A9: Phone : 9124973650 | B9: CD | D9: RISHI | F9: CD | G9: 6
A10: Name : Jaisankar | F10: NI | G10: 12
A11: Phone : 9786514619 | B11: LI | D11: VISHNU | F11: SF
A12: Name : Suraj P | F12: INVALID | G12: 3
A13: Phone : 9902323527 | B13: CB | D13: SHALINA | F13: NPC | G13: 16
A14: Name : Krittika Joshi | F14: OTHERS
A15: Phone : 8553021655 | B15: FOLLOWUP | D15: ABHAY
A16: Name : Rushikesh Ravindra Kamble
A17: Phone : 7218489921 | B17: FT | D17: AJAY | E17: 16/12/2024
A18: Name : Venkataraman
A19: Phone : 9884864562 | B19: CB | D19: KAMINI
A20: Name : Mathankumar D
A21: Phone : 6382384021 | B21: NI | D21: VYOM
A22: Name : Shivam
A23: Phone : 9368142670 | B23: NI | D23: AMIT
A24: Name : Tino
A25: Phone : 7561810918 | B25: NPC | D25: RISHI
A26: Name : SHEHEER
A27: Phone : 9447073826 | B27: LI | D27: VISHNU
A28: Name : Muthu
A29: Phone : 6383623375 | B29: NI | D29: SHALINA
A30: Name : Kalaimagal.a
A31: Phone : 9176168433 | B31: NPC | D31: ABHAY
A32: Name : Praneeth
A33: Phone : 8074477804 | B33: NI | D33: RAJ
A34: Name : Karthikeyan N
A35: Phone : 7200567333 | B35: BUSY | D35: KAMINI
A36: Name : Sujata Owhal
A37: Phone : 9060658647 | B37: INVALID | D37: VISHNU
A38: Name : Mohammad Abdul kashif
A39: Phone : 9380147171 | B39: CD | D39: AMIT
A40: Name : Sohail
A41: Phone : 8108894499 | B41: CB | D41: RISHI
A42: Name : Kanhu behera
A43: Phone : 8144268348 | B43: NI | D43: ABHAY
A44: Name : Cartoon Videos Bundle
A45: Phone : 9708987090 | B45: INVALID | D45: SHALINA
A46: Name : Harshrana
A47: Phone : 9911844310 | B47: CD | D47: SANJAY
A48: Name : Pritam Mohanty
A49: Phone : 8368807833 | B49: INTERESTED | C49: 50K | D49: KAMINI
A50: Name : Sakshi Jire
A51: Phone : 8855951859 | B51: FOLLOWUP | D51: AMIT
A52: Name : Sudeep HOSMANI
A53: Phone : 6366176818 | B53: BUSY | D53: RISHI
A54: Name : Tabasum
A55: Phone : 8431265798 | B55: FT | D55: SHALINA
A56: Name : Rohit Madhorao Meshram
A57: Phone : 7378682309 | B57: NI | D57: ABHAY
A58: Name : Saurabh
A59: Phone : 8075309252 | B59: PAYMENT DONE | D59: VYOM
A60: Name : Sudahar
A61: Phone : 9698789308 | B61: FOLLOWUP | D61: VYOM
A62: Name : Suresh kumar p
A63: Phone : 9962215987 | B63: FT | C63: 1 LAKH | D63: KAMINI
A64: Name : Malathiarun
A65: Phone : 8247686948 | B65: FOLLOWUP | D65: AMIT
A66: Name : Vidya jadhav
A67: Phone : 7057174815 | B67: NI | D67: RISHI
A68: Name : Karuna
A69: Phone : 8867648296 | B69: FT | D69: SHALINA
A70: Name : M Dinesh Babu
A71: Phone : 9344731806 | B71: INTERESTED | D71: RAJ
A72: Name : Mai Din
A73: Phone : 9042532390 | B73: NPC | D73: VYOM
A74: Name : Chethan s
A75: Phone : 9945622008 | B75: FOLLOWUP | D75: VIKASH
A76: Name : Aravindh R
A77: Phone : 9944212116 | B77: FOLLOWUP | D77: SHALINA
A78: Name : Ayaan 786
A79: Phone : 9148469010 | B79: NI | D79: VYOM
A80: Name : Mamali das
A81: Phone : 6371573903 | B81: NI | D81: KAMINI
A82: Name : Ritesh Kumar
A83: Phone : 8920572159 | B83: INVALID | D83: RISHI
A84: Name : आर्यन राजू पवार
A85: Phone : 9028936692 | B85: CB | D85: KAMINI
A86: Name : Yash hiware
A87: Phone : 9175918040 | B87: NI | D87: AMIT
A88: Name : govind
A89: Phone : 8384082002 | B89: NPC | D89: KAMINI
A90: Name : jude lazarus
A91: Phone : 8888020020 | B91: INTERESTED | D91: VINAY
A92: Name : Tabreez
A93: Phone : 8050686042 | B93: PAYMENT DONE | C93: 3 LAKH | D93: AMIT
A94: Name : Laxmi jadhav
A95: Phone : 8838540648 | B95: SW | D95: RISHI
A96: Name : Rakesh Yadav
A97: Phone : 9354052885 | B97: NI | D97: SHALINA
A98: Name : Laxmigaikwad
A99: Phone : 8838540648 | B99: NI | D99: KAMINI
A100: Name : Jagannath bhatta
...

Sheet 15-11-24
A1: CLIENTS DETAILS | B1: REMARK | C1: INVESTMENT | D1: EMP…
A2: Name : Sugandh kumar | F2: TOTAL LEADS - 112
A3: Phone : 8538965151 | B3: FOLLOWUP | D3: VYOM | F3: Date -15.11.24
A4: Name : Basavaraj Tukkappanavar | F4: FT | G4: 4
A5: Phone : 9535022096 | B5: NPC | D5: KAMINI | F5: INTERESTED | G5: 2
A6: Name : Kavyashree simhan | F6: FOLLOWUP | G6: 7
A7: Phone : 9035020455 | B7: NI | D7: ABHAY | F7: CB | G7: 5
A8: Name : RAKESH G PATIL | F8: BUSY | G8: 4
A9: Phone : 9960510482 | B9: FOLLOWUP | C9: 10K | D9: RISHI | F9: CD | G9: 2
A10: Name : pradeep kumar patel | F10: NI | G10: 29
A11: Phone : 9938537197 | B11: FOLLOWUP | D11: POONAM | F11: SF
A12: Name : Tarik khan | F12: INVALID | G12: 7
A13: Phone : 8273990471 | B13: NI | D13: SHALINA | F13: NPC | G13: 20
A14: Name : Vijay Ghadekar | F14: OTHERS
A15: Phone : 8888320049 | B15: NI | D15: RAJ
A16: Name : prashik
A17: Phone : 7776875356 | B17: FOLLOWUP | D17: KAMINI
A18: Name : Rahul Kumar
A19: Phone : 9310796065 | B19: CB | D19: VISHNU
A20: Name : Ujjwal
A21: Phone : 8178011821 | B21: NI | D21: SANJAY
A22: Name : Kiran gandhe
A23: Phone : 8796454619 | B23: NETWORK ISSUE | D23: KAMINI
A24: Name : Anis Tadvi
A25: Phone : 9579060543 | B25: NI | D25: ABHAY
A26: Name : Sarfaraj khan
A27: Phone : 9820683942 | B27: NI | D27: AMIT
A28: Name : Karan kadam
A29: Phone : 8080091958 | B29: NI | D29: RISHI
A30: Name : Jose
A31: Phone : 9745840728 | B31: NI | D31: VYOM
A32: Name : Momin
A33: Phone : 7679120478 | B33: NPC | D33: SHALINA
A34: Name : Manoj kv
A35: Phone : 9447736020 | B35: FT | C35: 50K | D35: VISHNU
A36: Name : It's umar 86
A37: Phone : 7482971683 | B37: NI | D37: RAJ
A38: Name : Rahul roy
A39: Phone : 7845877417 | B39: NI | D39: SANJAY
A40: Name : Sarathi
A41: Phone : 9655438234 | B41: NI | D41: HARIOM
A42: Name : Ayan
A43: Phone : 9709639986 | B43: NI | D43: VYOM
A44: Name : Saiathi
A45: Phone : 9655438234 | B45: NPC | D45: KAMINI
A46: Name : Mohamed
A47: Phone : 9446170545 | B47: NI | D47: ABHAY
A48: Name : Chandrapal Singh
A49: Phone : 9773702638 | B49: NI | D49: SHALINA
A50: Name : Arpit kujur
A51: Phone : 9972944127 | D51: RAJ
A52: Name : Rjanmjan
A53: Phone : 9902726186 | B53: NI | D53: VYOM
A54: Name : Arshad
A55: Phone : 8591186084 | B55: SCHOOL BOY | D55: RISHI
A56: Name : Kingmudarak
A57: Phone : 9902726186 | B57: NI | D57: VYOM
A58: Name : Lalan babu Raj
A59: Phone : 8051012549 | B59: NPC | D59: AMIT
A60: Name : Hindi
A61: Phone : 9292925292 | B61: NPC | D61: KAMINI
A62: Name : Yogish cn
A63: Phone : 8618306466 | B63: NPC | D63: SANJAY
A64: Name : Salman
A65: Phone : 7564385169 | B65: INVALID | D65: VISHNU
A66: Name : Hashimakhtar
A67: Phone : 9065072241 | B67: NI | D67: VYOM
A68: Name : Aniket
A69: Phone : 9536103213 | B69: FOLLOWUP | D69: SANGEETA
A70: Name : Mohanapriya
A71: Phone : 9787249595 | B71: NPC | D71: SHALINA
A72: Name : Vishu
A73: Phone : 9423579533 | B73: FOLLOWUP | D73: PRIYA
A74: Name : Wartica shivhare
A75: Phone : 9078052199 | B75: NPC | D75: VYOM
A76: Name : Manjunathsai Sai
A77: Phone : 7892735710 | B77: FOLLOWUP | D77: VYOM
A78: Name : Frahad
A79: Phone : 7465078561 | B79: INVALID | D79: RAJ
A80: Name : Sunil dagdu sakpal
A81: Phone : 9819598212 | B81: FT | D81: KAMINI
A82: Name : Chitransh
A83: Phone : 9236502041 | B83: NI | D83: HARIOM
A84: Name : Rajendra Behera
A85: Phone : 9853174794 | B85: CD | D85: AMIT
A86: Name : O P Gupta
A87: Phone : 8591368359 | B87: NI | D87: KAMINI
A88: Name : Durvesh
A89: Phone : 8724007154 | B89: NI | D89: RISHI
A90: Name : Tunne Khan
A91: Phone : 9792437688 | B91: BUSY | D91: SHALINA
A92: Name : Ganesh jadhav
A93: Phone : 8007792530 | B93: NI | D93: ABHAY
A94: Name : Shaikh aaftab
A95: Phone : 7620352385 | B95: NI | D95: VYOM
A96: Name : Bharat
A97: Phone : 9821224297 | B97: NI | D97: MAHENDRA
A98: Name : Lokanath tripathy
A99: Phone : 8249555365 | B99: NPC | D99: KAMINI
A100: Name : Syed Alluaddin
...

Sheet 16-11-24 
A1: CLIENTS DETAILS | B1: REMARK | C1: INVESTMENT | D1: EMP…
A2: Name : Raghavendra | F2: TOTAL LEADS - 110
A3: Phone : 9741354795 | B3: FOLLOWUP | D3: VIKASH | F3: Date -16.11.24
A4: Name : Sreejish | F4: FT
A5: Phone : 8086925636 | B5: NI | D5: KAMINI | F5: INTERESTED
A6: Name : k d hrn | F6: FOLLOWUP | G6: 5
A7: Phone : 9890909090 | B7: BUSY | D7: RAJ | F7: CB | G7: 1
A8: Name : kdh | F8: BUSY | G8: 6
A9: Phone : 9890989099 | B9: BUSY | D9: AMIT | F9: CD
A10: Name : Monis ali rana | F10: NI | G10: 42
A11: Phone : 8595900893 | B11: FOLLOWUP | D11: VISHNU | F11: SF
A12: Name : Aniket ghodge | F12: INVALID | G12: 10
A13: Phone : 7820844997 | B13: NI | D13: SHALINA | F13: NPC | G13: 24
A14: Name : Samir Pandey | F14: OTHERS
A15: Phone : 6370038591 | B15: NPC | D15: ABHAY
A16: Name : Joshva
A17: Phone : 9531660484 | B17: NI | D17: VIKASH
A18: Name : Lingesh .A
A19: Phone : 8939508049 | B19: INVALID | D19: VYOM
A20: Name : indra@123.cim
A21: Phone : 9529204903 | B21: NPC | D21: SANJAY
A22: Name : NEMINATH TAPAKEERE
A23: Phone : 9008771277 | B23: INVALID | D23: KAMINI
A24: Name : Sunil Tirupati Naik
A25: Phone : 9483208007 | B25: FOLLOWUP | D25: VISHNU
A26: Name : Surjaram
A27: Phone : 8669434405 | B27: NI | D27: SHALINA
A28: Name : Hari bele
A29: Phone : 9834810625 | B29: NI | D29: RAJ
A30: Name : Himanshu Kumar
A31: Phone : 7417419527 | B31: BUSY | D31: MAHENDRA
A32: Name : Mohammed ibrahim
A33: Phone : 9620972423 | B33: FT | D33: AMIT | F33: FT 30K | H33: AMIT
A34: Name : abc test
A35: Phone : 9988112233 | B35: NI | D35: VYOM
A36: Name : Kader Marakkar
A37: Phone : 8921723542 | B37: CD | D37: AMIT
A38: Name : Sharda Prasad
A39: Phone : 8178432902 | B39: FOLLOWUP | D39: SANJAY | F39: 26/12/2024
A40: Name : Ajay Kumar Mohanta
A41: Phone : 8117086997 | B41: NI | D41: HARIOM
A42: Name : Sachin vk
A43: Phone : 8954690266 | B43: SW | D43: ABHAY
A44: Name : Juber
A45: Phone : 9307344271 | B45: NI | D45: VYOM
A46: Name : Dhananjaya N
A47: Phone : 9964502003 | B47: NI | D47: KAMINI
A48: Name : Ashutosh done
A49: Phone : 9738474545 | B49: NI | D49: SHALINA
A50: Name : Shantabai hanmantrao kendre
A51: Phone : 7020059051 | B51: NI | D51: RAJ
A52: Name : Bispa majhi
A53: Phone : 9827876384 | B53: CD | D53: AMIT
A54: Name : ranjandevi9856@gamil.com
A55: Phone : 9971159915 | B55: NI | D55: ABHAY
A56: Name : RANA HOSSAIN
A57: Phone : 7019113128 | B57: NI | D57: VISHNU
A58: Name : Rajneeshpal
A59: Phone : 8756988963 | B59: NI | D59: VYOM
A60: Name : King
A61: Phone : 7066417777 | B61: BUSY | D61: SANJAY
A62: Name : 9731684144
A63: Phone : 9731684144 | B63: NPC | D63: KAMINI
A64: Name : Tanya
A65: Phone : 9960655224 | B65: FOLLOWUP | C65: 10K | D65: AMIT
A66: Name : Abhishek Kumar
A67: Phone : 9341276244 | B67: NI | D67: VYOM
A68: Name : amma_s_r_m_
A69: Phone : 6374435400 | B69: NI | D69: ABHAY
A70: Name : Ali kolekar
A71: Phone : 8857025576 | B71: NI | D71: SHALINA
A72: Name : Virendra madavi
A73: Phone : 9226514553 | B73: NI | D73: RAJ
A74: Name : Malathi
A75: Phone : 8870784634 | B75: NPC | D75: VYOM
A76: Name : .hiren
A77: Phone : 9876106978 | B77: INVALID | D77: KAMINI
A78: Name : Chandan Barman
A79: Phone : 8011251687 | B79: FOLLOWUP | D79: SANJAY
A80: Name : Pratap
A81: Phone : 9845368543 | B81: NPC | D81: ABHAY
A82: Name : Ilove you
A83: Phone : 9074176595 | B83: NI | D83: SHALINA
A84: Name : Mustakim
A85: Phone : 8600586596 | B85: NI | D85: RAJ
A86: Name : Fazal vk
A87: Phone : 6453873537 | B87: INVALID | D87: VISHNU
A88: Name : Sahil khan
A89: Phone : 9822678451 | B89: FOLLOWUP | D89: VYOM
A90: Name : Shre
A91: Phone : 9740397764 | B91: NI | D91: ABHAY
A92: Name : Ajhar max
A93: Phone : 8076874235 | B93: NI | D93: KAMINI
A94: Name : Noor mohammed
A95: Phone : 9845369229 | B95: NI | D95: SHALINA
A96: Name : Ishwar panchal
A97: Phone : 9359008140 | B97: NPC | D97: ABHAY
A98: Name : Aayush tiwari
A99: Phone : 9696224781 | B99: NI | D99: VYOM
A100: Name : Bhumraj Choubhari
...

Sheet 18-11-24
A1: CLIENTS DETAILS | B1: REMARK | C1: INVESTMENT | D1: EMP…
A2: Name : Nazrana | G2: TOTAL LEADS - 227
A3: Phone : 9354632449 | B3: NPC | D3: KAMINI | G3: Date -18.11.24
A4: Name : Rahul sada | G4: FT | H4: 0
A5: Phone : 7209528506 | B5: CB | D5: MAHENDRA | G5: INTERESTED | H5: 1
A6: Name : Ghuyt | G6: FOLLOWUP | H6: 1
A7: Phone : 6540921809 | B7: INVALID | G7: CB | H7: 12
A8: Name : Shahidking | G8: BUSY | H8: 8
A9: Phone : 7541957721 | B9: NPC | D9: RAJ | G9: CD | H9: 17
A10: Name : Manasmita | G10: NI | H10: 89
A11: Phone : 7008591677 | B11: NI | D11: AMIT | G11: SF | H11: 12
A12: Name : Velmalai | G12: INVALID | H12: 8
A13: Phone : 9344527923 | B13: NPC | D13: VISHNU | G13: NPC | H13: 53
A14: Name : TOSEEF OP | G14: OTHERS | H14: 26
A15: Phone : 8237228205 | B15: NI | D15: VIKASH
A16: Name : Abduldfc
A17: Phone : 9363876339 | B17: NI | D17: SANJAY
A18: Name : Anjaney Naykar
A19: Phone : 6362775274 | B19: NI | D19: DHEERAJ
A20: Name : Vinod yadav
A21: Phone : 9019506966 | B21: CD | D21: MAHENDRA
A22: Name : Vivek jaiswar
A23: Phone : 9987007989 | B23: NI | D23: ABHAY
A24: Name : Asif
A25: Phone : 8591617546 | B25: NI | D25: NIKITA
A26: Name : Aaradhy Dambhare
A27: Phone : 8010559551 | B27: NI | D27: KAMINI
A28: Name : Udayakanta parida
A29: Phone : 9777924710 | B29: NPC | D29: HARIOM
A30: Name : Aasifroyals4
A31: Phone : 7042065890 | B31: NPC | D31: RAJ
A32: Name : LX,,,, jaydulislam
A33: Phone : 7896876008 | B33: NI | D33: TANMESH
A34: Name : Sakthivel.R
A35: Phone : 8778605524 | B35: NI | D35: MAHENDRA
A36: Name : Biju nayak
A37: Phone : 9692725662 | B37: CB | D37: KAMINI
A38: Name : Apu
A39: Phone : 7384295861 | B39: NPC | D39: NIKITA
A40: Name : tf._.sanna
A41: Phone : 9742894623 | B41: NI | D41: HARIOM
A42: Name : Ankitshakya
A43: Phone : 9917865267 | B43: NI | D43: RISHI
A44: Name : Liladhar
A45: Phone : 9104536615 | B45: BUSY | D45: KAMINI
A46: Name : Sanjit Kumar Pandey
A47: Phone : 6203157386 | B47: NI | D47: RAJ
A48: Name : Rayyan
A49: Phone : 9137540561 | B49: FOLLOWUP | D49: ABHAY
A50: Name : Vishal prjapat
A51: Phone : 8828011530 | B51: NI | D51: HARIOM
A52: Name : Alok Pradhan 1234
A53: Phone : 6372198591 | B53: NI | D53: RISHI
A54: Name : Jypthika
A55: Phone : 9971872298 | B55: NI | D55: SHALINA
A56: Name : Shourya
A57: Phone : 8087174185 | B57: NPC | D57: SANJAY
A58: Name : RahulReddy
A59: Phone : 9963698480 | B59: INTERESTD | D59: MAHENDRA
A60: Name : Nikiljeevan
A61: Phone : 9972634282 | B61: SF | D61: HARIOM
A62: Name : Mano
A63: Phone : 9626151078 | B63: NI | D63: SHALINA
A64: Name : Shri
A65: Phone : 9945226497 | B65: NPC | D65: AMIT
A66: Name : Ruman
A67: Phone : 9845136950 | B67: NPC | D67: AMIT
A68: Name : Gobinda
A69: Phone : 6370534096 | B69: NI | D69: KAMINI
A70: Name : Shiva verma
A71: Phone : 7743830929 | B71: NI | D71: RAJ
A72: Name : Faisal
A73: Phone : 9053315576 | B73: NI | D73: SANJAY
A74: Name : Sambu
A75: Phone : 8249907442 | B75: NI | D75: AYUSHI
A76: Name : Sahbaj
A77: Phone : 9608810269 | B77: NI | D77: MAHENDRA
A78: Name : ISARAR
A79: Phone : 6353588224 | B79: NI | D79: HARIOM
A80: Name : Drx,gamer,yt
A81: Phone : 8144992770 | B81: SF | D81: RAJ
A82: Name : Laxmansundhi
A83: Phone : 7846816212 | B83: FOLLOWUP | D83: NARMADA
A84: Name : Sudhir yadav
A85: Phone : 9235367270 | B85: CD | D85: RISHI
A86: Name : Harshl
A87: Phone : 9021776021 | B87: NPC | D87: RAJ
A88: Name : Raj Kumar
A89: Phone : 7632022113 | B89: NI | D89: SANJAY
A90: Name : Jagathesh
A91: Phone : 7806822504 | B91: NPC | D91: AYUSHI
A92: Name : Laxman
A93: Phone : 9945665054 | B93: BUSY | D93: MAHENDRA
A94: Name : Padma payeng
A95: Phone : 9518318756 | B95: NI | D95: HARIOM
A96: Name : Rihan
A97: Phone : 9368024559 | B97: NPC | D97: KAMINI
A98: Name : Soune
A99: Phone : 9628924817 | B99: NI | D99: SHALINA
A100: Name : Riotff3021
...

Sheet 25-11-24 
A1: CLIENTS DETAILS | B1: REMARK | C1: INVESTMENT | D1: EMP… | G1: TOTAL LEADS - 31
A2: Name : Shashidhar | G2: Date -25.11.24
A3: Phone : 9036272331 | B3: NPC | D3: VYOM | G3: FT | H3: 2 | J3: PAYMENT DONE 1 FT
A4: Name : T E Badri Narayanan | G4: INTERESTED | H4: 1
A5: Phone : 9080094955 | B5: NPC | D5: VYOM | G5: FOLLOWUP | H5: 3
A6: Name : Pravin pandey | G6: CB | H6: 4
A7: Phone : 9210580390 | B7: PAYMENT DONE | D7: VISHNU | G7: BUSY | H7: 2
A8: Name : RajeshSanqwan | G8: CD | H8: 1
A9: Phone : 8307278017 | B9: FT | D9: ABHAY | G9: NI | H9: 3
A10: Name : Jayakumar kaliannan | G10: SF
A11: Phone : 9566718765 | B11: BUSY | D11: KAMINI | G11: INVALID | H11: 5
A12: Name : Sharan | G12: NPC | H12: 10
A13: Phone : 8248574848 | B13: INVALID | D13: RAJ | G13: OTHERS | H13: 1
A14: Name : Satyam jha
A15: Phone : 8920686302 | B15: FOLLOWUP | D15: VYOM
A16: Name : Shanmuga Sundharam K
A17: Phone : 6381295095 | B17: NI | D17: VISHNU
A18: Name : Santosh Biradar
A19: Phone : 7483541534 | B19: FOLLOWUP | D19: ABHAY
A20: Name : Praveenkumar b
A21: Phone : 9535660499 | B21: CB | D21: KAMINI
A22: Name : Paresh
A23: Phone : 9873096124 | B23: INVALID | D23: RAJ
A24: Name : Muthu Chennai
A25: Phone : 8667338669 | B25: FOLLOWUP | D25: VYOM
A26: Name : Nishad N
A27: Phone : 9645520189 | B27: NPC | D27: AJAY
A28: Name : Bharath DR
A29: Phone : 7022597540 | B29: NI | D29: VISHNU
A30: Name : Fernandes
A31: Phone : 8722476209 | B31: NPC | D31: VYOM
A32: Name : rajubai
A33: Phone : 9943927257 | B33: NPC | D33: KAMINI
A34: Name : Sujay
A35: Phone : 9975781622 | B35: NI | D35: ABHAY
A36: Name : m logaprabu
A37: Phone : 9282145598 | B37: INVALID | D37: VYOM
A38: Name : vinayak sadul
A39: Phone : 9860052828 | B39: NPC | D39: AJAY
A40: Name : Sunil arde
A41: Phone : 8668814079 | B41: INTERSTED | D41: VISHNU
A42: Name : Atul kumar Mishra
A43: Phone : 9776518057 | B43: CB | D43: ARUN
A44: Name : Fhvc
A45: Phone : 9886448855 | B45: INVALID | D45: VYOM
A46: Name : Kavita Yadav
A47: Phone : 9953254065 | B47: BUSY | D47: RAJ
A48: Name : cdvx
A49: Phone : 9554251562 | B49: NPC | D49: AJAY
A50: Name : Imran Shaikh
A51: Phone : 7796652505 | B51: FOLLOWUP | D51: ABHAY
A52: Name : Dnyaneshwar kundlik bagade
A53: Phone : 7738420119 | B53: CB | D53: VYOM
A54: Name : Gourab
A55: Phone : 9124081554 | B55: CD | D55: KAMINI
A56: Name : Lal yadav
A57: Phone : 8491816649 | B57: NPC | D57: AJAY
A58: Name : SUDIN E CHANDRAN
A59: Phone : 9633847729 | B59: NPC | D59: VYOM
A60: Name : Rohitkumar Deshmukh
A61: Phone : 9130060019 | B61: NI | D61: VISHNU
A62: Name : X
A63: Phone : 8556655358 | B63: INVALID | D63: RAJ

Sheet 18 TODAY  
A1: CLIENTS DETAILS | B1: REMARK | C1: INVESTMENT | D1: EMP…
A2: Name : Chitaranjan Mohanty | G2: TOTAL LEADS - 47
A3: Phone : 9124921775 | B3: NPC | D3: RC | G3: Date -18.11.24
A4: Name : V Sangeetha Rao | G4: FT | H4: 4
A5: Phone : 7032771051 | B5: FOLLOW UP | D5: NIKITA | G5: INTERESTED | H5: 4
A6: Name : Robin | G6: FOLLOWUP | H6: 1
A7: Phone : 8883830388 | B7: INVALID | D7: RC | G7: CB | H7: 2
A8: Name : SUBRAMANIAN N | G8: BUSY | H8: 6
A9: Phone : 8925845885 | B9: FOLLOW UP | D9: NIKITA | G9: CD | H9: 0
A10: Name : asd456 546546 | G10: NI | H10: 6
A11: Phone : 9897656746 | B11: INVALID | D11: RC | G11: SF | H11: 2
A12: Name : Rohan kapse | G12: INVALID | H12: 2
A13: Phone : 9022556559 | B13: NI | D13: RC | G13: NPC | H13: 13
A14: Name : jitesh khurana | G14: OTHERS | H14: 7
A15: Phone : 9966716344 | B15: NPC | D15: RC
A16: Name : Rama
A17: Phone : 7416386661 | B17: FOLLOW UP | D17: RC
A18: Name : Naushad Idrisi
A19: Phone : 9321412626 | B19: CB | D19: VYOM
A20: Name : sagar parmar
A21: Phone : 8830509166 | B21: FT | C21: 25K | D21: RC
A22: Name : nst
A23: Phone : 9443458061 | B23: NPC | D23: RC
A24: Name : Sharma
A25: Phone : 9360166994 | B25: NI | D25: AMIT
A26: Name : Alin Kumar Das
A27: Phone : 9853423130 | B27: NC | D27: KAMINI
A28: Name : Sid
A29: Phone : 8750591434 | B29: DEMO | C29: REPEAT NO. | D29: AMBRISH
A30: Name : Zeba
A31: Phone : 9625462901 | B31: INTERESTED | D31: RAJ
A32: Name : Niraj
A33: Phone : 9853625060 | B33: FT | C33: 8K LOSS | D33: KAMINI
A34: Name : lingaswaran gurusamy
A35: Phone : 9443354915 | B35: FOLLOW UP | D35: ABHAY
A36: Name : Susmitha
A37: Phone : 8807708412 | B37: BUSY | D37: HARIOM
A38: Name : Pranay
A39: Phone : 9394959496 | B39: WTSP CHAT FOLLOW UP | D39: NIKITA
A40: Name : Ravivarma
A41: Phone : 8309830413 | B41: CB | D41: NIDHI
A42: Name : Salman farish
A43: Phone : 8086418540 | B43: INTRESTED | D43: MAHENDRA
A44: Name : Tharan
A45: Phone : 9043866536 | B45: NI | D45: RC
A46: Name : Swapnil Choudhari
A47: Phone : 7875217619 | B47: NI | D47: VIKASH
A48: Name : Vithesh
A49: Phone : 8073926276 | B49: FOLLOW UP | D49: POONAM
A50: Name : Noushad
A51: Phone : 9995824100 | B51: CB | D51: RAJ
A52: Name : Banavath.Hariprasad Naik
A53: Phone : 8096569946 | B53: FT | C53: 50K CAPITAL | D53: KAMINI
A54: Name : Vithesh
A55: Phone : 8073926276 | B55: NPC | D55: DHEERAJ
A56: Name : Bapu Jadhav
A57: Phone : 9922444776 | B57: NI | D57: KAMINI
A58: Name : rk k
A59: Phone : 9958835979 | B59: FOLLOW UP | D59: VIKASH
A60: Name : Shub
A61: Phone : 9696919999 | B61: INTERESTED | D61: KAMINI
A62: Name : piyush bhosale
A63: Phone : 7972921150 | B63: FT | D63: KAMINI
A64: Name : Vibin varghese
A65: Phone : 7994481081 | B65: CB | D65: KAMINI
A66: Name : Jeevan
A67: Phone : 9869277821 | B67: BUSY | D67: MAHENDRA
A68: Name : yash pal
A69: Phone : 9650696622 | B69: NI | D69: AMIT
A70: Name : kehsava
A71: Phone : 7204868191 | B71: INTERESTED | D71: SANJAY
A72: Name : Balasubramaniam S
A73: Phone : 8419938747 | B73: NI | D73: RAJ
A74: Name : Manish Prajapati
A75: Phone : 8976742101 | B75: FT | D75: DHEERAJ
A76: Name : Munjaji Prabhauraj Mane
A77: Phone : 9890766348 | B77: FT | C77: REPEAT NO. | D77: AMIT
A78: Name : Shreyas Ramesh
A79: Phone : 8861256165 | B79: NI | D79: MAHENDRA
A80: Name : Khaja mohsinuddin
A81: Phone : 9886815161 | B81: NI | D81: SHALINA
A82: Name : Maaz
A83: Phone : 7353842788 | B83: SF | D83: MAHENDRA
A84: Name : Krishna kumar prasad
A85: Phone : 8112374024 | B85: BUSY | D85: KAMINI
A86: Name : Asha Baiju
A87: Phone : 8921873673 | B87: BUSY | D87: KAMINI
A88: Name : Akash Sagre
A89: Phone : 8446505034 | B89: NPC | D89: SHLINA
A90: Name : Krishna kumar prasad
A91: Phone : 8112374024 | B91: BUSY | D91: KAMINI
A92: Name : Premalatha S
A93: Phone : 6380212188 | B93: CB | D93: MAHENDRA
A94: Name : Ankit toppo
A95: Phone : 6266339713 | B95: NI | D95: SHALINA
A96: Name : John Thomas
A97: Phone : 9345033965 | B97: FOLLOW UP | D97: SHALINA
A98: Name : Thomas
A99: Phone : 9345276850 | B99: NI
A100: Name : Hum
...

Sheet 19-11-24
A1: CLIENTS DETAILS | B1: REMARK | C1: INVESTMENT | D1: EMP…
A2: Name : Anand | G2: TOTAL LEADS - 85
A3: Phone : 8075669723 | B3: BUSY | D3: KAMINI | G3: Date -19.11.24
A4: Name : Srinivas Raju | G4: FT | H4: 6
A5: Phone : 9900151617 | B5: FOLLOW UP | C5: REPEAT | D5: VIKASH | G5: INTERESTED | H5: 5
A6: Name : Ajith | G6: FOLLOWUP | H6: 7
A7: Phone : 7025767340 | B7: INTERESTED | D7: MAHENDRA | G7: CB | H7: 5
A8: Name : Anitha K V | G8: BUSY | H8: 9
A9: Phone : 8317353532 | B9: NI | D9: DHEERAJ | G9: CD | H9: 5
A10: Name : Manjunath | G10: NI | H10: 9
A11: Phone : 9632780417 | B11: NPC | D11: KAMINI | G11: SF | H11: 4
A12: Name : SHEIK BASIL J | G12: INVALID | H12: 4
A13: Phone : 9042449591 | B13: NI | D13: AMIT | G13: NPC | H13: 26
A14: Name : Akshay Kapoor | G14: OTHERS | H14: 4
A15: Phone : 7891199779 | B15: WRONG NO..
A16: Name : Udaya arun kumar
A17: Phone : 9952757230 | B17: NPC | D17: RAJ
A18: Name : Vedant sawant
A19: Phone : 8097813482 | B19: NPC | D19: TANMESH
A20: Name : Rahul. Nil
A21: Phone : 7896543278 | B21: INVALID | D21: ABHAY
A22: Name : Rahib Vayilassery
A23: Phone : 9567615982 | B23: FOLLOW UP | D23: VIKASH
A24: Name : Yogesh kumar saini
A25: Phone : 8766342947 | B25: NI | D25: NIKITA
A26: Name : Vinod khanna
A27: Phone : 7382114116 | B27: FOLLOW UP | D27: VYOM
A28: Name : no name
A29: Phone : 9988998899 | B29: SF | D29: DHEERAJ
A30: Name : Anup Gupta
A31: Phone : 8356056821 | B31: CB | D31: VIKAS
A32: Name : Rajdeep singh gill
A33: Phone : 7030510520 | B33: CB | D33: KAMINI
A34: Name : Bharathiraja
A35: Phone : 9741641222 | B35: INVALID
A36: Name : Rahul kumar singh
A37: Phone : 9162430836 | B37: NPC | D37: TANMESH
A38: Name : Rameshwar Telote
A39: Phone : 9579432665 | B39: CB | D39: NIDHI
A40: Name : Pankaj Pandey
A41: Phone : 7304873038 | B41: FT | C41: 50K | D41: VISHNU
A42: Name : Nandha
A43: Phone : 9791918893 | B43: PAYMENT DONE | D43: TANMESH
A44: Name : J Mallik
A45: Phone : 9437452215 | B45: NI | D45: SANJAY
A46: Name : Prakash Hatkar
A47: Phone : 9860258960 | B47: NPC | D47: VIKASH
A48: Name : GUNASHEKAR REDDY
A49: Phone : 9632180967 | B49: NI | D49: VYOM
A50: Name : Sp
A51: Phone : 9765698429 | B51: NI | D51: RISHI
A52: Name : Ananth kumar
A53: Phone : 9886149003 | B53: NI | D53: HARIOM
A54: Name : Devansh
A55: Phone : 9654845149 | B55: NI | D55: AMIT
A56: Name : Ajith krishnan
A57: Phone : 7025767340 | B57: INTERESTED | D57: MAHENDRA
A58: Name : Dheeraj k
A59: Phone : 7899684950 | B59: NPC | D59: NIKITA
A60: Name : Vijay kumar
A61: Phone : 7983258163 | B61: NPC | D61: TANMESH
A62: Name : Farook
A63: Phone : 9900124247 | B63: CB | D63: HARIOM
A64: Name : Emmanuel Samson A
A65: Phone : 7411762959 | B65: NPC | D65: RAJ
A66: Name : Ginu
A67: Phone : 9495491350 | B67: FT | D67: NARMADA | G67: FT | I67: NARMADA
A68: Name : Rajpal
A69: Phone : 9848012345 | B69: TOLL FREE NO | D69: RAJ
A70: Name : GOUSE PEERA PATAN
A71: Phone : 9652031661 | B71: NI | D71: AMIT
A72: Name : Ashoj
A73: Phone : 8606346042 | B73: BUSY | D73: NIKITA
A74: Name : Kaushal Kumar
A75: Phone : 7400152462 | B75: NI | D75: MAHENDRA
A76: Name : Rajesh Kumar bhola Shukla
A77: Phone : 9702697825 | B77: NI | D77: SANJAY
A78: Name : GIRISH BUGADE
A79: Phone : 9834665773 | B79: NI | D79: RAJ
A80: Name : Sobesh
A81: Phone : 8281434010 | B81: BUSY | D81: MAHENDRA
A82: Name : Baba
A83: Phone : 9900486368 | B83: FT | D83: AMAR
A84: Name : Tanmay Malik
A85: Phone : 6370286839 | B85: SF | D85: DHEERAJ
A86: Name : shahina
A87: Phone : 9970821810 | B87: NI | D87: SALINA
A88: Name : Ak
A89: Phone : 8698639751 | B89: NI | D89: AMIT
A90: Name : AMOL KAMBLE
A91: Phone : 7083084073 | B91: NI | D91: RAJ
A92: Name : Vujay
A93: Phone : 8056743475 | B93: CB | D93: VYOM
A94: Name : Ramesh T
A95: Phone : 8282821566 | B95: FT | D95: DEERAJ
A96: Name : Aayan Ansari
A97: Phone : 7385931433 | B97: NPC | D97: KAMINI
A98: Name : Manjunath
A99: Phone : 9632780417 | B99: NPC | D99: KAMINI
A100: Name : Harsh
...

Sheet Sheet6
A1: Name : Hari bele
A2: Phone : 9834810625 | B2: FOLLOW UP | D2: KAMINI
A3: Name : Noor mohammed
A4: Phone : 9845369229 | B4: FOLLOW UP | D4: VYOM
A5: Name : Sunil dagdu sakpal | B5: ft/1 lakh/fresher
A6: Phone : 9819598212 | D6: RISHI
A7: Name : Yogish cn
A8: Phone : 8618306466 | B8: tomorrow morning | D8: RISHI
A9: Name : Akash Sagre
A10: Phone : 8446505034 | B10: FOLLOW UP | D10: VYOM
A11: Name : Sid
A12: Phone : 8750591434 | B12: FT | D12: DHEERAJ

Sheet 20-11-24
A1: CLIENTS DETAILS | B1: REMARK | C1: INVESTMENT | D1: EMP… | G1: TOTAL LEADS - 41
A2: Name : Sandeep Kumar S | G2: Date -20.11.24
A3: Phone : 8270759383 | B3: NPC | D3: KAMINI | G3: FT | H3: 3
A4: Name : Vijay babu | G4: INTERESTED
A5: Phone : 8686255555 | B5: NPC | D5: RAJ | G5: FOLLOWUP | H5: 5
A6: Name : Dev s | G6: CB | H6: 3
A7: Phone : 9320613967 | B7: NPC | D7: AMIT | G7: BUSY | H7: 3
A8: Name : Pooja Pramod | G8: CD | H8: 1
A9: Phone : 8197699860 | B9: FOLLOWUP | D9: VIKASH | G9: NI | H9: 4
A10: Name : Anuj Kumar | G10: SF
A11: Phone : 9891692313 | B11: FOLLOWUP | D11: VYOM | G11: INVALID | H11: 2
A12: Name : Jayesh Tiwari | G12: NPC | H12: 16
A13: Phone : 7000269458 | B13: FOLLOWUP | C13: 45634 | D13: ABHAY | G13: OTHERS
A14: Name : Saim
A15: Phone : 9354041614 | B15: NI | D15: RISHI
A16: Name : Faijal
A17: Phone : 6284882713 | B17: NI | D17: SANJAY
A18: Name : Karthik Ponnusamy
A19: Phone : 9980088056 | B19: BUSY | D19: KAMINI
A20: Name : Eshan
A21: Phone : 6362505539 | B21: BUSY | D21: MAHENDRA
A22: Name : Murugesh
A23: Phone : 9965328395 | B23: NPC | D23: VYOM
A24: Name : Ashok Chakradhar
A25: Phone : 8639967636 | B25: NPC | D25: NIKITA
A26: Name : Vijay babu
A27: Phone : 8686255555 | B27: NPC | D27: AYUSHI
A28: Name : KAMLESH THAKUR
A29: Phone : 8368711243 | B29: FT | C29: 20K | D29: AMIT
A30: Name : Yathish
A31: Phone : 8971282225 | B31: NI | D31: RISHI
A32: Name : Tabrez
A33: Phone : 8802222889 | B33: NI | D33: RAJ
A34: Name : Vijey
A35: Phone : 9902732835 | B35: NI | D35: VIKASH
A36: Name : Navlesh
A37: Phone : 9582695456 | B37: CB | D37: NIDHI
A38: Name : Rushi
A39: Phone : 9823345634 | B39: NI | D39: VYOM
A40: Name : Thiagarajan Rathinavel
A41: Phone : 9150034500 | B41: NI | D41: VYOM
A42: Name : Akshay upre
A43: Phone : 9960115007 | B43: NPC | D43: SANJAY
A44: Name : SHABARISH
A45: Phone : 7795963036 | B45: NI | D45: NIKITA
A46: Name : Shambhu Sharma
A47: Phone : 9582675533 | B47: FOLLOWUP | D47: KAMINI
A48: Name : Sheela singh
A49: Phone : 9987367516 | B49: NI | D49: VYOM
A50: Name : leo
A51: Phone : 7418034500 | B51: NPC | D51: AMIT
A52: Name : Vijay S
A53: Phone : 6381624741 | B53: NPC | D53: VYOM
A54: Name : Praneshwar
A55: Phone : 9944912665 | B55: PAYMENT DONE | D55: AJAY
A56: Name : Jagannath
A57: Phone : 9078768073 | B57: FOLLOWUP | D57: NARMADA
A58: Name : pandian
A59: Phone : 9094992745 | B59: CB | D59: VYOM
A60: Name : Jitender kumar tamta
A61: Phone : 9911247450 | B61: NPC | D61: RISHI
A62: Name : Vivek zambre
A63: Phone : 8600632218 | B63: NI | D63: KAMINI
A64: Name : Surjeet
A65: Phone : 9717417063 | B65: FOLLOWUP | D65: VYOM
A66: Name : ELANGO
A67: Phone : 9659551762 | B67: NPC | D67: VYOM
A68: Name : Keshab
A69: Phone : 7057644615 | B69: INVALID | D69: MAHENDRA
A70: Name : Lakshminarayan
A71: Phone : 9865940041 | B71: NI | D71: MAHENDRA
A72: Name : Shikha
A73: Phone : 6485731698 | B73: INVALID | D73: RAJ
A74: Name : Sonu Kumar Patwa
A75: Phone : 7021006791 | B75: FT | C75: 50K+ | D75: AMIT
A76: Name : Damodar Mudaliar
A77: Phone : 9820082589 | B77: BUSY | D77: KAMINI
A78: Name : rajashekar
A79: Phone : 6303433054 | D79: KAMINI
A80: Name : FAHEEM DANISH
A81: Phone : 8484860990 | B81: FT | D81: MAHENDRA
A82: Name : Sanjay Shinde
A83: Phone : 9028439202 | B83: FT | C83: 2 LAKH | D83: KAMINI

Sheet 21-11-24
A1: CLIENTS DETAILS | B1: REMARK | C1: INVESTMENT | D1: EMP… | G1: TOTAL LEADS - 66
A2: Name : Rakesh jangid | G2: Date -21.11.24
A3: Phone : 8007784333 | B3: BUSY | D3: KAMINI | G3: FT | H3: 2
A4: Name : Anish | G4: INTERESTED | H4: 1
A5: Phone : 7070955203 | B5: NPC | D5: VYOM | G5: FOLLOWUP | H5: 3
A6: Name : Vishnu | G6: CB | H6: 7
A7: Phone : 7010236449 | B7: NPC | D7: HARIOM | G7: BUSY | H7: 1
A8: Name : Iamkhan | G8: CD | H8: 2
A9: Phone : 8840137682 | B9: NI | D9: AMIT | G9: NI | H9: 6
A10: Name : Dilshad khan | G10: SF
A11: Phone : 8840137682 | B11: NPC | D11: SANJAY | G11: INVALID | H11: 6
A12: Name : Firdos | G12: NPC | H12: 23
A13: Phone : 7977506748 | B13: FOLLOWUP | C13: 15K FRESHER | D13: RISHI | G13: OTHERS | H13: 25
A14: Name : Aarti Deshmukh
A15: Phone : 9004235845 | B15: INVALID | D15: MAHENDRA
A16: Name : Mahesh
A17: Phone : 8465034343 | B17: OUT OF NETWORK | D17: SHALINA
A18: Name : Kaito
A19: Phone : 9003200400 | B19: NI | D19: NIKITA
A20: Name : Rego
A21: Phone : 9626939584 | B21: NI | D21: VYOM
A22: Name : Syed
A23: Phone : 9113898880 | B23: FT | D23: AYUSHI | E23: 45870
A24: Name : Amit rathod
A25: Phone : 8779923416 | B25: CB | D25: LAXMI
A26: Name : Uppara Chandra mohan
A27: Phone : 8179391761 | B27: NI | D27: AYUSHI
A28: Name : Vivek tripathi
A29: Phone : 7977261243 | B29: NI | D29: DHIRAJ
A30: Name : Somasundaran Kulakkattu Palengara
A31: Phone : 9744612643 | B31: NI | D31: VYOM
A32: Name : Ilyas
A33: Phone : 9606592102 | B33: INVALID | D33: SHALINA
A34: Name : Mohammad feroz abdul sattar
A35: Phone : 8087062668 | B35: NI | D35: RAJ
A36: Name : Samiksha
A37: Phone : 9819303077 | B37: NI | D37: KAMINI
A38: Name : Mahendra Tayade
A39: Phone : 8149030881 | B39: NI | D39: KAMINI
A40: Name : Srinivas R.
A41: Phone : 9845355911 | B41: NI | D41: MAHENDRA
A42: Name : Shlok Molak
A43: Phone : 8429090707 | B43: NPC | D43: AMIT
A44: Name : Mohan Reddy
A45: Phone : 6301383571 | B45: NI | D45: KAMINI
A46: Name : Uday
A47: Phone : 7638064168 | B47: NI | D47: NARMADA
A48: Name : Ravichandran
A49: Phone : 9363251521 | B49: NI | D49: TANMESH
A50: Name : Dharmveer
A51: Phone : 9009681328 | B51: CB | D51: KAMINI
A52: Name : Shrilaxmi Bidarhalli
A53: Phone : 9886719214 | B53: FOLLOWUP | D53: VYOM
A54: Name : Kunal Sharma
A55: Phone : 9766619905 | B55: WHATSAPP CHAT | D55: AYUSHI
A56: Name : Kirty
A57: Phone : 9892548017 | B57: FT | C57: 50K | D57: AMIT
A58: Name : Nakka vineel babu
A59: Phone : 9299253592 | B59: NI | D59: VYOM
A60: Name : Hvyug
A61: Phone : 9946588668 | B61: INVALID | D61: AMIT
A62: Name : Vishal Trivedi
A63: Phone : 9821786010 | B63: NPC | D63: RAJ
A64: Name : Anjali
A65: Phone : 8976268564 | B65: NPC | D65: KAMINI
A66: Name : Darshan talikoti
A67: Phone : 9741287887 | B67: CB | D67: RAJ
A68: Name : Srinivasulu Reddy D
A69: Phone : 9866679900 | B69: NPC | D69: VYOM
A70: Name : Behj
A71: Phone : 8800505959 | B71: NI | D71: KAMINI
A72: Name : Aksay
A73: Phone : 9141039236 | B73: NPC | D73: NARMADA
A74: Name : Bdbdhdhd
A75: Phone : 8188871772 | B75: INVALID | D75: AMIT
A76: Name : Prasad g
A77: Phone : 8970086743 | B77: WHATSAPP CHAT | D77: NIKITA
A78: Name : Raj kashyap
A79: Phone : 7523981260 | B79: CD | D79: MAHENDRA
A80: Name : Muthu Kumar
A81: Phone : 8778504817 | B81: CB | D81: VYOM
A82: Name : suguna
A83: Phone : 9538692609 | B83: FT | D83: AYUSHI | F83: 25/12/2024
A84: Name : bibekananda pujhari
A85: Phone : 8114314613 | B85: CD | D85: RAJ
A86: Name : Sinan
A87: Phone : 9645684571 | B87: INVALID | D87: SHALINA
A88: Name : Kiranmaye
A89: Phone : 9994229349 | B89: NI | D89: KAMINI
A90: Name : Shahid c
A91: Phone : 9961838168 | D91: GOURAV
A92: Name : Hina Meshram
A93: Phone : 8308407038 | B93: FT | D93: RANJANA | F93: 45870
A94: Name : Nick
A95: Phone : 7982592641 | D95: GOURAV
A96: Name : MuraliA
A97: Phone : 7892505058 | B97: NI | D97: GOURAV
A98: Name : Dev Sharma
A99: Phone : 8285751469 | D99: GOURAV
A100: Name : Jann
...

Sheet 22-11-24
A1: CLIENTS DETAILS | B1: REMARK | C1: INVESTMENT | D1: EMP… | G1: TOTAL LEADS - 47
A2: Name : Sudip vilas thakurdesai | G2: Date -22.11.24
A3: Phone : 7350264828 | B3: CB | D3: RAJ | G3: FT | H3: 2
A4: Name : Afroz | G4: INTERESTED | H4: 2
A5: Phone : 8007811664 | B5: NI | D5: GOURAV | G5: FOLLOWUP | H5: 4
A6: Name : Amol Maruti Kadu | G6: CB | H6: 2
A7: Phone : 7020331752 | D7: GOURAV | G7: BUSY | H7: 2
A8: Name : Deepak M | G8: CD | H8: 1
A9: Phone : 8870433869 | D9: GOURAV | G9: NI | H9: 2
A10: Name : Ramza | G10: SF
A11: Phone : 9019142878 | B11: INTERESTED | D11: SANGEETA | G11: INVALID | H11: 2
A12: Name : Mujeeb | G12: NPC | H12: 12
A13: Phone : 9846259015 | B13: FT | D13: RANJANA | E13: 45870 | G13: OTHERS | H13: 18
A14: Name : Shrikant koti
A15: Phone : 9148442781 | D15: GOURAV
A16: Name : Vicky Vijay
A17: Phone : 8637491881 | B17: NI | D17: AJAY
A18: Name : Mahesh Pahan
A19: Phone : 8434086593 | B19: FOLLOWUP | D19: MANSING
A20: Name : sumeet girepunje
A21: Phone : 7089406194 | B21: NI | D21: VYOM
A22: Name : dadu
A23: Phone : 9579540801 | B23: NPC | D23: VYOM
A24: Name : Rohith M
A25: Phone : 9025311309 | B25: NPC | D25: MAHENDRA
A26: Name : Muhammed Asharaf
A27: Phone : 8281550681 | B27: NPC | D27: RAJ
A28: Name : Isha Joshi
A29: Phone : 9320198899 | B29: FOLLOWUP | C29: 15K | D29: KAMINI
A30: Name : Deepika
A31: Phone : 7038276524 | B31: NI | D31: AJAY
A32: Name : Dhruba Ghosh
A33: Phone : 9952034605 | B33: NI | D33: HARIOM
A34: Name : Sidrameshwar Chandrashekhar Hiremath
A35: Phone : 9922443899 | B35: NI | D35: VYOM
A36: Name : Prajwal k
A37: Phone : 7349116530 | B37: NI | D37: KAMINI
A38: Name : Nagu
A39: Phone : 7013022419 | B39: BUSY | D39: RAJ
A40: Name : RPRohilla
A41: Phone : 9868535861 | B41: NI | D41: RAJ
A42: Name : Abhishek Pati
A43: Phone : 8328890266 | B43: FT | D43: LAXMI | F43: 17/12/2024
A44: Name : M s raghavan
A45: Phone : 9790854380 | B45: NPC | D45: SHALINA
A46: Name : vickky
A47: Phone : 7720877918 | B47: NI | D47: VYOM
A48: Name : Sivani
A49: Phone : 8870696930 | B49: SW | D49: RAJ
A50: Name : Sumati bagarty
A51: Phone : 9019826321 | B51: NI | D51: TANMESH
A52: Name : S MUTHU
A53: Phone : 9865429165 | B53: NPC | D53: AMIT
A54: Name : Basavaraj R
A55: Phone : 7259960349 | B55: NI | D55: KAMINI
A56: Name : Baby
A57: Phone : 9052267405 | B57: NPC | D57: VYOM
A58: Name : Nikhil Aiwale
A59: Phone : 9923306010 | B59: NPC | D59: RAJ
A60: Name : karan yadav
A61: Phone : 8178112079 | B61: NI | D61: HARIOM
A62: Name : Rajkumat
A63: Phone : 7523981260 | B63: NI | D63: VYOM
A64: Name : Gauri Maskare
A65: Phone : 7709856990 | B65: FT | D65: MAHENDRA
A66: Name : G NAGESWARARAO
A67: Phone : 9848716999 | B67: NI | D67: VYOM
A68: Name : Varun Ahlawat
A69: Phone : 7678564534 | B69: NPC | D69: RAJ
A70: Name : Cravan
A71: Phone : 9653310813 | B71: NI | D71: AMIT
A72: Name : Abhinav
A73: Phone : 9060553104 | B73: CB | D73: VIKASH
A74: Name : Hitesh Patel
A75: Phone : 9945010990 | B75: FT | D75: HARIOM
A76: Name : Amit Singh
A77: Phone : 6232032685 | B77: INVALID | D77: KAMINI
A78: Name : Nilesh gorakh gaikwad
A79: Phone : 9545547000 | B79: NI | D79: SHALINA
A80: Name : sandeep k
A81: Phone : 8660466240 | B81: NPC | D81: RISHI
A82: Name : abcbnmjhgty456
A83: Phone : 9999999999 | B83: INVALID | D83: MAHENDRA
A84: Name : PraveenKumar
A85: Phone : 7708678548 | B85: FOLLOWUP | D85: AMAR
A86: Name : Lalan Prasad
A87: Phone : 7219020764 | B87: NPC | D87: SHALINA
A88: Name : Amol Wagh
A89: Phone : 8805566307 | B89: NPC | D89: VYOM
A90: Name : Ajay Jadhav
A91: Phone : 8208907200 | B91: NPC | D91: VYOM
A92: Name : V.S.Negi
A93: Phone : 9915350144 | B93: INTERESTED | D93: VYOM
A94: Name : Sagar Ramesh lekhwani
A95: Phone : 9975399959 | B95: NI | D95: VYOM

Sheet 23-11-24
A1: CLIENTS DETAILS | B1: REMARK | C1: INVESTMENT | D1: EMP… | G1: TOTAL LEADS - 12
A2: Name : ravindra.badiger | G2: Date -23.11.24
A3: Phone : 7204842512 | B3: NI | D3: VYOM | G3: FT | H3: 2
A4: Name : Vishal Khillare | G4: INTERESTED
A5: Phone : 8625898747 | B5: NPC | D5: KAMINI | G5: FOLLOWUP
A6: Name : Kavita | G6: CB | H6: 1
A7: Phone : 9274478485 | B7: SW | D7: HARIOM | G7: BUSY
A8: Name : Sairaj Patil | G8: CD
A9: Phone : 8625898747 | B9: NPC | D9: AMIT | G9: NI | H9: 2
A10: Name : kunal rathod | G10: SF
A11: Phone : 7796776677 | B11: FT | C11: 15K | D11: AMIT | G11: INVALID
A12: Name : Pratik jha | G12: NPC | H12: 7
A13: Phone : 9508221729 | B13: NI | D13: KAMINI | G13: OTHERS | H13: 1
A14: Name : Aklk
A15: Phone : 9844269855 | B15: NI | D15: VYOM
A16: Name : Dhananjay mardi
A17: Phone : 8825960650 | B17: NPC | D17: VYOM
A18: Name : Sampath Kumar
A19: Phone : 9789095087 | B19: FOLLOWUP | D19: SANGEETA VAMANKAR
A20: Name : Rabin Hansda
A21: Phone : 9363277330 | B21: NI | D21: VYOM
A22: Name : AMEE
A23: Phone : 9082735518 | B23: NPC | D23: VYOM
A24: Name : SUVENDU SAMANTA
A25: Phone : 9658216554 | B25: FT | D25: NARMADA

Sheet 25-11-2024
A1: CLIENTS DETAILS | B1: REMARK | C1: INVESTMENT | D1: EMP… | G1: TOTAL LEADS - 31
A2: Name : Shashidhar | G2: Date -25.11.24
A3: Phone : 9036272331 | B3: NPC | D3: VYOM | G3: FT | H3: 2 | J3: PAYMENT DONE 1 FT
A4: Name : T E Badri Narayanan | G4: INTERESTED | H4: 1
A5: Phone : 9080094955 | B5: NPC | D5: VYOM | G5: FOLLOWUP | H5: 3
A6: Name : Pravin pandey | G6: CB | H6: 4
A7: Phone : 9210580390 | B7: PAYMENT DONE | D7: VISHNU | G7: BUSY | H7: 2
A8: Name : RajeshSanqwan | G8: CD | H8: 1
A9: Phone : 8307278017 | B9: FT | D9: ABHAY | G9: NI | H9: 3
A10: Name : Jayakumar kaliannan | G10: SF
A11: Phone : 9566718765 | B11: BUSY | D11: KAMINI | G11: INVALID | H11: 5
A12: Name : Sharan | G12: NPC | H12: 10
A13: Phone : 8248574848 | B13: INVALID | D13: RAJ | G13: OTHERS | H13: 1
A14: Name : Satyam jha
A15: Phone : 8920686302 | B15: FOLLOWUP | D15: VYOM
A16: Name : Shanmuga Sundharam K
A17: Phone : 6381295095 | B17: NI | D17: VISHNU
A18: Name : Santosh Biradar
A19: Phone : 7483541534 | B19: NI | D19: ABHAY
A20: Name : Praveenkumar b
A21: Phone : 9535660499 | B21: INTERSTED | D21: MANSING
A22: Name : Paresh
A23: Phone : 9873096124 | B23: INVALID | D23: RAJ
A24: Name : Muthu Chennai
A25: Phone : 8667338669 | B25: FOLLOWUP | D25: VYOM
A26: Name : Nishad N
A27: Phone : 9645520189 | B27: NPC | D27: AJAY
A28: Name : Bharath DR
A29: Phone : 7022597540 | B29: NI | D29: VISHNU
A30: Name : Fernandes
A31: Phone : 8722476209 | B31: NPC | D31: VYOM
A32: Name : rajubai
A33: Phone : 9943927257 | B33: NI | D33: KAMINI
A34: Name : Sujay
A35: Phone : 9975781622 | B35: CB | D35: ABHAY
A36: Name : m logaprabu
A37: Phone : 9282145598 | B37: INVALID | D37: VYOM
A38: Name : vinayak sadul
A39: Phone : 9860052828 | B39: NPC | D39: AJAY
A40: Name : Sunil arde
A41: Phone : 8668814079 | B41: INTERSTED | D41: VISHNU
A42: Name : Atul kumar Mishra
A43: Phone : 9776518057 | B43: FT | D43: ABHAY | F43: 24/12/2024
A44: Name : Fhvc
A45: Phone : 9886448855 | B45: INVALID | D45: VYOM
A46: Name : Kavita Yadav
A47: Phone : 9953254065 | B47: BUSY | D47: RAJ
A48: Name : cdvx
A49: Phone : 9554251562 | B49: NPC | D49: AJAY
A50: Name : Imran Shaikh
A51: Phone : 7796652505 | B51: FOLLOWUP | D51: ABHAY
A52: Name : Dnyaneshwar kundlik bagade
A53: Phone : 7738420119 | B53: NI | D53: VYOM
A54: Name : Gourab
A55: Phone : 9124081554 | B55: NI | D55: KAMINI
A56: Name : Lal yadav
A57: Phone : 8491816649 | B57: NPC | D57: AJAY
A58: Name : SUDIN E CHANDRAN
A59: Phone : 9633847729 | B59: NPC | D59: VYOM
A60: Name : Rohitkumar Deshmukh
A61: Phone : 9130060019 | B61: NI | D61: VISHNU
A62: Name : X
A63: Phone : 8556655358 | B63: INVALID | D63: RAJ

Sheet 25-11-24  TODAY
A1: CLIENTS DETAILS | B1: REMARK | C1: INVESTMENT | D1: EMP… | G1: ="TOTAL LEADS = " & COUNTA(A2:A500)/2 -> TOTAL LEADS = 20
A2: Name : P. Arya Bhat | G2: Date -25.11.24
A3: Phone : 6302162729 | B3: FT | C3: STOCK CASH | D3: RC | G3: FT | H3: 4
A4: Name : Narendra chaudhari | G4: INTERESTED
A5: Phone : 9850749748 | B5: NI | D5: RC | G5: FOLLOWUP | H5: 2
A6: Name : G ch kindalu | G6: CB | H6: 1
A7: Phone : 8500700808 | B7: NI | D7: RC | G7: BUSY | H7: 2
A8: Name : Nawaz veer | G8: CD | H8: 1
A9: Phone : 9606562236 | B9: NI | D9: KAMINI | G9: NI | H9: 1
A10: Name : Abhishek kumarsbdbdbb | G10: SF
